<?xml version="1.0" encoding="UTF-8"?>

<!-- generated on 2026-05-13T23:19:28.899379+03:00 by Eclipse SUMO sumo 1.26.0
<sumoConfiguration xmlns:xsi="http://www.w3.org/2001/XMLSchema-instance" xsi:noNamespaceSchemaLocation="http://sumo.dlr.de/xsd/sumoConfiguration.xsd">

    <input>
        <net-file value="yeni_normal_sure.net.xml"/>
        <route-files value="arac_talepleri/deneme_1.rou.xml"/>
        <additional-files value="Detectors/detector_deneme.add.xml"/>
    </input>

    <time>
        <step-length value="1"/>
    </time>

    <processing>
        <lateral-resolution value="0"/>
    </processing>

    <traci_server>
        <remote-port value="58276"/>
    </traci_server>

    <random_number>
        <seed value="1"/>
    </random_number>

</sumoConfiguration>
-->

<detector xmlns:xsi="http://www.w3.org/2001/XMLSchema-instance" xsi:noNamespaceSchemaLocation="http://sumo.dlr.de/xsd/det_e2_file.xsd">
   <interval begin="0.00" end="300.00" id="e2_3" sampledSeconds="463.45" nVehEntered="43" nVehLeft="43" nVehSeen="43" meanSpeed="4.89" meanTimeLoss="8.35" meanOccupancy="10.58" maxOccupancy="35.71" meanMaxJamLengthInVehicles="0.69" meanMaxJamLengthInMeters="4.40" maxJamLengthInVehicles="4" maxJamLengthInMeters="28.51" jamLengthInVehiclesSum="208" jamLengthInMetersSum="1324.71" meanHaltingDuration="14.93" maxHaltingDuration="36.00" haltingDurationSum="209.00" meanIntervalHaltingDuration="14.93" maxIntervalHaltingDuration="36.00" intervalHaltingDurationSum="209.00" startedHalts="18.00" meanVehicleNumber="1.65" maxVehicleNumber="5" />
   <interval begin="0.00" end="300.00" id="turkis_b_e_1" sampledSeconds="786.09" nVehEntered="76" nVehLeft="75" nVehSeen="76" meanSpeed="8.44" meanTimeLoss="6.63" meanOccupancy="4.26" maxOccupancy="15.00" meanMaxJamLengthInVehicles="1.00" meanMaxJamLengthInMeters="6.67" maxJamLengthInVehicles="6" maxJamLengthInMeters="43.96" jamLengthInVehiclesSum="299" jamLengthInMetersSum="1999.53" meanHaltingDuration="24.83" maxHaltingDuration="48.00" haltingDurationSum="298.00" meanIntervalHaltingDuration="24.83" maxIntervalHaltingDuration="48.00" intervalHaltingDurationSum="298.00" startedHalts="18.00" meanVehicleNumber="2.69" maxVehicleNumber="9" />
   <interval begin="0.00" end="300.00" id="yenimahalle_b_e_a_1" sampledSeconds="156.26" nVehEntered="54" nVehLeft="54" nVehSeen="54" meanSpeed="5.26" meanTimeLoss="2.17" meanOccupancy="15.33" maxOccupancy="70.70" meanMaxJamLengthInVehicles="0.08" meanMaxJamLengthInMeters="0.30" maxJamLengthInVehicles="2" maxJamLengthInMeters="11.30" jamLengthInVehiclesSum="25" jamLengthInMetersSum="89.60" meanHaltingDuration="7.67" maxHaltingDuration="17.00" haltingDurationSum="23.00" meanIntervalHaltingDuration="7.67" maxIntervalHaltingDuration="17.00" intervalHaltingDurationSum="23.00" startedHalts="4.00" meanVehicleNumber="0.69" maxVehicleNumber="2" />
   <interval begin="300.00" end="600.00" id="e2_3" sampledSeconds="830.90" nVehEntered="53" nVehLeft="49" nVehSeen="53" meanSpeed="3.07" meanTimeLoss="13.47" meanOccupancy="18.64" maxOccupancy="42.86" meanMaxJamLengthInVehicles="1.57" meanMaxJamLengthInMeters="10.39" maxJamLengthInVehicles="5" maxJamLengthInMeters="36.01" jamLengthInVehiclesSum="476" jamLengthInMetersSum="3139.41" meanHaltingDuration="17.37" maxHaltingDuration="73.00" haltingDurationSum="469.00" meanIntervalHaltingDuration="17.37" maxIntervalHaltingDuration="73.00" intervalHaltingDurationSum="469.00" startedHalts="36.00" meanVehicleNumber="2.88" maxVehicleNumber="7" />
   <interval begin="300.00" end="600.00" id="turkis_b_e_1" sampledSeconds="830.50" nVehEntered="77" nVehLeft="78" nVehSeen="78" meanSpeed="7.70" meanTimeLoss="7.08" meanOccupancy="4.49" maxOccupancy="11.67" meanMaxJamLengthInVehicles="1.07" meanMaxJamLengthInMeters="7.04" maxJamLengthInVehicles="5" maxJamLengthInMeters="35.00" jamLengthInVehiclesSum="322" jamLengthInMetersSum="2112.35" meanHaltingDuration="18.72" maxHaltingDuration="46.00" haltingDurationSum="337.00" meanIntervalHaltingDuration="18.72" maxIntervalHaltingDuration="46.00" intervalHaltingDurationSum="337.00" startedHalts="26.00" meanVehicleNumber="2.85" maxVehicleNumber="7" />
   <interval begin="300.00" end="600.00" id="yenimahalle_b_e_a_1" sampledSeconds="413.62" nVehEntered="30" nVehLeft="28" nVehSeen="30" meanSpeed="1.01" meanTimeLoss="13.13" meanOccupancy="49.46" maxOccupancy="78.51" meanMaxJamLengthInVehicles="1.11" meanMaxJamLengthInMeters="6.19" maxJamLengthInVehicles="2" maxJamLengthInMeters="11.92" jamLengthInVehiclesSum="334" jamLengthInMetersSum="1857.10" meanHaltingDuration="82.00" maxHaltingDuration="142.00" haltingDurationSum="328.00" meanIntervalHaltingDuration="82.00" maxIntervalHaltingDuration="142.00" intervalHaltingDurationSum="328.00" startedHalts="7.00" meanVehicleNumber="1.46" maxVehicleNumber="2" />
   <interval begin="600.00" end="900.00" id="e2_3" sampledSeconds="2770.47" nVehEntered="7" nVehLeft="1" nVehSeen="11" meanSpeed="0.07" meanTimeLoss="251.04" meanOccupancy="62.37" maxOccupancy="67.18" meanMaxJamLengthInVehicles="9.03" meanMaxJamLengthInMeters="63.43" maxJamLengthInVehicles="10" maxJamLengthInMeters="70.00" jamLengthInVehiclesSum="2708" jamLengthInMetersSum="19029.53" meanHaltingDuration="275.10" maxHaltingDuration="372.00" haltingDurationSum="2751.00" meanIntervalHaltingDuration="253.90" maxIntervalHaltingDuration="300.00" intervalHaltingDurationSum="2539.00" startedHalts="7.00" meanVehicleNumber="9.25" maxVehicleNumber="10" />
   <interval begin="600.00" end="900.00" id="turkis_b_e_1" sampledSeconds="965.78" nVehEntered="76" nVehLeft="67" nVehSeen="76" meanSpeed="9.00" meanTimeLoss="7.68" meanOccupancy="5.29" maxOccupancy="15.00" meanMaxJamLengthInVehicles="0.98" meanMaxJamLengthInMeters="6.44" maxJamLengthInVehicles="5" maxJamLengthInMeters="35.03" jamLengthInVehiclesSum="295" jamLengthInMetersSum="1931.57" meanHaltingDuration="23.61" maxHaltingDuration="46.00" haltingDurationSum="307.00" meanIntervalHaltingDuration="23.61" maxIntervalHaltingDuration="46.00" intervalHaltingDurationSum="307.00" startedHalts="20.00" meanVehicleNumber="3.28" maxVehicleNumber="9" />
   <interval begin="600.00" end="900.00" id="yenimahalle_b_e_a_1" sampledSeconds="596.99" nVehEntered="1" nVehLeft="1" nVehSeen="3" meanSpeed="0.03" meanTimeLoss="198.68" meanOccupancy="77.84" maxOccupancy="79.16" meanMaxJamLengthInVehicles="1.98" meanMaxJamLengthInMeters="11.78" maxJamLengthInVehicles="2" maxJamLengthInMeters="12.00" jamLengthInVehiclesSum="593" jamLengthInMetersSum="3535.36" meanHaltingDuration="211.50" maxHaltingDuration="410.00" haltingDurationSum="846.00" meanIntervalHaltingDuration="148.50" maxIntervalHaltingDuration="300.00" intervalHaltingDurationSum="594.00" startedHalts="3.00" meanVehicleNumber="1.99" maxVehicleNumber="2" />
   <interval begin="900.00" end="1200.00" id="e2_3" sampledSeconds="2980.16" nVehEntered="1" nVehLeft="1" nVehSeen="11" meanSpeed="0.03" meanTimeLoss="270.61" meanOccupancy="66.29" maxOccupancy="67.18" meanMaxJamLengthInVehicles="9.93" meanMaxJamLengthInMeters="69.32" maxJamLengthInVehicles="10" maxJamLengthInMeters="70.00" jamLengthInVehiclesSum="2980" jamLengthInMetersSum="20795.20" meanHaltingDuration="513.70" maxHaltingDuration="672.00" haltingDurationSum="5137.00" meanIntervalHaltingDuration="275.50" maxIntervalHaltingDuration="300.00" intervalHaltingDurationSum="2755.00" startedHalts="1.00" meanVehicleNumber="9.94" maxVehicleNumber="10" />
   <interval begin="900.00" end="1200.00" id="turkis_b_e_1" sampledSeconds="1326.83" nVehEntered="65" nVehLeft="71" nVehSeen="74" meanSpeed="8.41" meanTimeLoss="11.34" meanOccupancy="7.27" maxOccupancy="19.63" meanMaxJamLengthInVehicles="1.34" meanMaxJamLengthInMeters="9.18" maxJamLengthInVehicles="7" maxJamLengthInMeters="50.14" jamLengthInVehiclesSum="403" jamLengthInMetersSum="2753.65" meanHaltingDuration="23.15" maxHaltingDuration="45.00" haltingDurationSum="463.00" meanIntervalHaltingDuration="20.90" maxIntervalHaltingDuration="45.00" intervalHaltingDurationSum="418.00" startedHalts="24.00" meanVehicleNumber="4.51" maxVehicleNumber="12" />
   <interval begin="900.00" end="1200.00" id="yenimahalle_b_e_a_1" sampledSeconds="600.35" nVehEntered="1" nVehLeft="1" nVehSeen="3" meanSpeed="0.03" meanTimeLoss="199.80" meanOccupancy="75.05" maxOccupancy="79.16" meanMaxJamLengthInVehicles="2.00" meanMaxJamLengthInMeters="11.58" maxJamLengthInVehicles="2" maxJamLengthInMeters="12.00" jamLengthInVehiclesSum="600" jamLengthInMetersSum="3474.23" meanHaltingDuration="280.50" maxHaltingDuration="433.00" haltingDurationSum="561.00" meanIntervalHaltingDuration="214.00" maxIntervalHaltingDuration="300.00" intervalHaltingDurationSum="428.00" startedHalts="1.00" meanVehicleNumber="2.00" maxVehicleNumber="3" />
   <interval begin="1200.00" end="1500.00" id="e2_3" sampledSeconds="2972.07" nVehEntered="1" nVehLeft="1" nVehSeen="11" meanSpeed="0.03" meanTimeLoss="269.88" meanOccupancy="66.55" maxOccupancy="67.18" meanMaxJamLengthInVehicles="9.91" meanMaxJamLengthInMeters="69.44" maxJamLengthInVehicles="10" maxJamLengthInMeters="70.00" jamLengthInVehiclesSum="2972" jamLengthInMetersSum="20833.12" meanHaltingDuration="719.60" maxHaltingDuration="971.00" haltingDurationSum="7196.00" meanIntervalHaltingDuration="273.10" maxIntervalHaltingDuration="300.00" intervalHaltingDurationSum="2731.00" startedHalts="1.00" meanVehicleNumber="9.91" maxVehicleNumber="10" />
   <interval begin="1200.00" end="1500.00" id="turkis_b_e_1" sampledSeconds="2272.40" nVehEntered="67" nVehLeft="62" nVehSeen="70" meanSpeed="6.26" meanTimeLoss="23.46" meanOccupancy="12.59" maxOccupancy="21.67" meanMaxJamLengthInVehicles="3.37" meanMaxJamLengthInMeters="23.38" maxJamLengthInVehicles="8" maxJamLengthInMeters="58.89" jamLengthInVehiclesSum="1013" jamLengthInMetersSum="7028.30" meanHaltingDuration="19.06" maxHaltingDuration="74.00" haltingDurationSum="991.00" meanIntervalHaltingDuration="19.06" maxIntervalHaltingDuration="74.00" intervalHaltingDurationSum="991.00" startedHalts="70.00" meanVehicleNumber="7.67" maxVehicleNumber="13" />
   <interval begin="1200.00" end="1500.00" id="yenimahalle_b_e_a_1" sampledSeconds="596.92" nVehEntered="1" nVehLeft="1" nVehSeen="3" meanSpeed="0.03" meanTimeLoss="198.69" meanOccupancy="78.00" maxOccupancy="79.16" meanMaxJamLengthInVehicles="1.98" meanMaxJamLengthInMeters="11.86" maxJamLengthInVehicles="2" maxJamLengthInMeters="12.00" jamLengthInVehiclesSum="595" jamLengthInMetersSum="3556.99" meanHaltingDuration="385.00" maxHaltingDuration="656.00" haltingDurationSum="1155.00" meanIntervalHaltingDuration="198.00" maxIntervalHaltingDuration="300.00" intervalHaltingDurationSum="594.00" startedHalts="2.00" meanVehicleNumber="1.99" maxVehicleNumber="2" />
   <interval begin="1500.00" end="1800.00" id="e2_3" sampledSeconds="2991.85" nVehEntered="0" nVehLeft="1" nVehSeen="10" meanSpeed="0.02" meanTimeLoss="298.92" meanOccupancy="66.45" maxOccupancy="67.18" meanMaxJamLengthInVehicles="9.97" meanMaxJamLengthInMeters="69.41" maxJamLengthInVehicles="10" maxJamLengthInMeters="70.00" jamLengthInVehiclesSum="2992" jamLengthInMetersSum="20822.23" meanHaltingDuration="991.67" maxHaltingDuration="1177.00" haltingDurationSum="8925.00" meanIntervalHaltingDuration="300.00" maxIntervalHaltingDuration="300.00" intervalHaltingDurationSum="2700.00" startedHalts="0.00" meanVehicleNumber="9.97" maxVehicleNumber="10" />
   <interval begin="1500.00" end="1800.00" id="turkis_b_e_1" sampledSeconds="2213.59" nVehEntered="83" nVehLeft="85" nVehSeen="91" meanSpeed="6.33" meanTimeLoss="17.58" meanOccupancy="12.32" maxOccupancy="23.33" meanMaxJamLengthInVehicles="3.28" meanMaxJamLengthInMeters="23.44" maxJamLengthInVehicles="8" maxJamLengthInMeters="57.57" jamLengthInVehiclesSum="1020" jamLengthInMetersSum="7241.31" meanHaltingDuration="23.79" maxHaltingDuration="85.00" haltingDurationSum="999.00" meanIntervalHaltingDuration="22.86" maxIntervalHaltingDuration="85.00" intervalHaltingDurationSum="960.00" startedHalts="64.00" meanVehicleNumber="7.50" maxVehicleNumber="14" />
   <interval begin="1500.00" end="1800.00" id="yenimahalle_b_e_a_1" sampledSeconds="600.21" nVehEntered="1" nVehLeft="1" nVehSeen="3" meanSpeed="0.03" meanTimeLoss="199.78" meanOccupancy="74.83" maxOccupancy="79.16" meanMaxJamLengthInVehicles="2.00" meanMaxJamLengthInMeters="11.55" maxJamLengthInVehicles="2" maxJamLengthInMeters="12.00" jamLengthInVehiclesSum="600" jamLengthInMetersSum="3466.10" meanHaltingDuration="218.50" maxHaltingDuration="371.00" haltingDurationSum="437.00" meanIntervalHaltingDuration="183.00" maxIntervalHaltingDuration="300.00" intervalHaltingDurationSum="366.00" startedHalts="1.00" meanVehicleNumber="2.00" maxVehicleNumber="3" />
   <interval begin="1800.00" end="2100.00" id="e2_3" sampledSeconds="2988.13" nVehEntered="1" nVehLeft="0" nVehSeen="10" meanSpeed="0.01" meanTimeLoss="298.73" meanOccupancy="66.76" maxOccupancy="67.03" meanMaxJamLengthInVehicles="9.96" meanMaxJamLengthInMeters="69.29" maxJamLengthInVehicles="10" maxJamLengthInMeters="70.00" jamLengthInVehiclesSum="2988" jamLengthInMetersSum="20786.60" meanHaltingDuration="1191.40" maxHaltingDuration="1477.00" haltingDurationSum="11914.00" meanIntervalHaltingDuration="298.90" maxIntervalHaltingDuration="300.00" intervalHaltingDurationSum="2989.00" startedHalts="1.00" meanVehicleNumber="9.96" maxVehicleNumber="10" />
   <interval begin="1800.00" end="2100.00" id="turkis_b_e_1" sampledSeconds="3070.82" nVehEntered="83" nVehLeft="86" nVehSeen="89" meanSpeed="5.40" meanTimeLoss="26.44" meanOccupancy="17.10" maxOccupancy="26.43" meanMaxJamLengthInVehicles="4.98" meanMaxJamLengthInMeters="35.98" maxJamLengthInVehicles="10" maxJamLengthInMeters="77.94" jamLengthInVehiclesSum="1572" jamLengthInMetersSum="11262.12" meanHaltingDuration="19.46" maxHaltingDuration="104.00" haltingDurationSum="1401.00" meanIntervalHaltingDuration="19.28" maxIntervalHaltingDuration="104.00" intervalHaltingDurationSum="1388.00" startedHalts="100.00" meanVehicleNumber="10.39" maxVehicleNumber="16" />
   <interval begin="1800.00" end="2100.00" id="yenimahalle_b_e_a_1" sampledSeconds="599.67" nVehEntered="1" nVehLeft="1" nVehSeen="3" meanSpeed="0.02" meanTimeLoss="199.65" meanOccupancy="77.85" maxOccupancy="79.16" meanMaxJamLengthInVehicles="2.00" meanMaxJamLengthInMeters="11.88" maxJamLengthInVehicles="2" maxJamLengthInMeters="12.00" jamLengthInVehiclesSum="599" jamLengthInMetersSum="3564.39" meanHaltingDuration="185.00" maxHaltingDuration="366.00" haltingDurationSum="370.00" meanIntervalHaltingDuration="152.00" maxIntervalHaltingDuration="300.00" intervalHaltingDurationSum="304.00" startedHalts="1.00" meanVehicleNumber="2.00" maxVehicleNumber="2" />
   <interval begin="2100.00" end="2400.00" id="e2_3" sampledSeconds="2981.52" nVehEntered="1" nVehLeft="1" nVehSeen="11" meanSpeed="0.02" meanTimeLoss="270.77" meanOccupancy="65.68" maxOccupancy="66.72" meanMaxJamLengthInVehicles="9.94" meanMaxJamLengthInMeters="68.89" maxJamLengthInVehicles="10" maxJamLengthInMeters="70.00" jamLengthInVehiclesSum="2982" jamLengthInMetersSum="20668.10" meanHaltingDuration="1334.70" maxHaltingDuration="1775.00" haltingDurationSum="13347.00" meanIntervalHaltingDuration="291.00" maxIntervalHaltingDuration="300.00" intervalHaltingDurationSum="2910.00" startedHalts="1.00" meanVehicleNumber="9.94" maxVehicleNumber="10" />
   <interval begin="2100.00" end="2400.00" id="turkis_b_e_1" sampledSeconds="5188.35" nVehEntered="99" nVehLeft="85" nVehSeen="102" meanSpeed="2.63" meanTimeLoss="45.00" meanOccupancy="28.93" maxOccupancy="40.00" meanMaxJamLengthInVehicles="10.33" meanMaxJamLengthInMeters="83.04" maxJamLengthInVehicles="23" maxJamLengthInMeters="191.40" jamLengthInVehiclesSum="3657" jamLengthInMetersSum="28852.39" meanHaltingDuration="25.87" maxHaltingDuration="92.00" haltingDurationSum="3337.00" meanIntervalHaltingDuration="25.87" maxIntervalHaltingDuration="92.00" intervalHaltingDurationSum="3337.00" startedHalts="171.00" meanVehicleNumber="17.41" maxVehicleNumber="24" />
   <interval begin="2100.00" end="2400.00" id="yenimahalle_b_e_a_1" sampledSeconds="600.00" nVehEntered="0" nVehLeft="0" nVehSeen="2" meanSpeed="0.01" meanTimeLoss="299.87" meanOccupancy="73.01" maxOccupancy="77.86" meanMaxJamLengthInVehicles="2.00" meanMaxJamLengthInMeters="11.29" maxJamLengthInVehicles="2" maxJamLengthInMeters="11.85" jamLengthInVehiclesSum="600" jamLengthInMetersSum="3385.89" meanHaltingDuration="485.00" maxHaltingDuration="666.00" haltingDurationSum="970.00" meanIntervalHaltingDuration="300.00" maxIntervalHaltingDuration="300.00" intervalHaltingDurationSum="600.00" startedHalts="0.00" meanVehicleNumber="2.00" maxVehicleNumber="2" />
   <interval begin="2400.00" end="2700.00" id="e2_3" sampledSeconds="2928.39" nVehEntered="3" nVehLeft="3" nVehSeen="13" meanSpeed="0.08" meanTimeLoss="224.52" meanOccupancy="65.50" maxOccupancy="67.18" meanMaxJamLengthInVehicles="9.65" meanMaxJamLengthInMeters="68.09" maxJamLengthInVehicles="10" maxJamLengthInMeters="70.00" jamLengthInVehiclesSum="2905" jamLengthInMetersSum="20498.66" meanHaltingDuration="693.28" maxHaltingDuration="1918.00" haltingDurationSum="12479.00" meanIntervalHaltingDuration="147.89" maxIntervalHaltingDuration="300.00" intervalHaltingDurationSum="2662.00" startedHalts="11.00" meanVehicleNumber="9.77" maxVehicleNumber="10" />
   <interval begin="2400.00" end="2700.00" id="turkis_b_e_1" sampledSeconds="6879.31" nVehEntered="88" nVehLeft="74" nVehSeen="105" meanSpeed="1.04" meanTimeLoss="62.46" meanOccupancy="38.30" maxOccupancy="53.78" meanMaxJamLengthInVehicles="12.76" meanMaxJamLengthInMeters="108.12" maxJamLengthInVehicles="31" maxJamLengthInMeters="255.45" jamLengthInVehiclesSum="5676" jamLengthInMetersSum="46357.64" meanHaltingDuration="30.35" maxHaltingDuration="116.00" haltingDurationSum="5766.00" meanIntervalHaltingDuration="27.28" maxIntervalHaltingDuration="87.00" intervalHaltingDurationSum="5183.00" startedHalts="225.00" meanVehicleNumber="23.03" maxVehicleNumber="33" />
   <interval begin="2400.00" end="2700.00" id="yenimahalle_b_e_a_1" sampledSeconds="594.48" nVehEntered="2" nVehLeft="2" nVehSeen="4" meanSpeed="0.06" meanTimeLoss="148.09" meanOccupancy="76.97" maxOccupancy="79.16" meanMaxJamLengthInVehicles="1.94" meanMaxJamLengthInMeters="11.56" maxJamLengthInVehicles="2" maxJamLengthInMeters="12.00" jamLengthInVehiclesSum="581" jamLengthInMetersSum="3466.76" meanHaltingDuration="222.28" maxHaltingDuration="734.00" haltingDurationSum="1556.00" meanIntervalHaltingDuration="83.71" maxIntervalHaltingDuration="135.00" intervalHaltingDurationSum="586.00" startedHalts="7.00" meanVehicleNumber="1.99" maxVehicleNumber="2" />
   <interval begin="2700.00" end="3000.00" id="e2_3" sampledSeconds="2984.18" nVehEntered="1" nVehLeft="1" nVehSeen="11" meanSpeed="0.02" meanTimeLoss="271.00" meanOccupancy="66.01" maxOccupancy="67.18" meanMaxJamLengthInVehicles="9.95" meanMaxJamLengthInMeters="69.08" maxJamLengthInVehicles="10" maxJamLengthInMeters="70.00" jamLengthInVehiclesSum="2984" jamLengthInMetersSum="20722.92" meanHaltingDuration="625.60" maxHaltingDuration="1531.00" haltingDurationSum="6256.00" meanIntervalHaltingDuration="284.70" maxIntervalHaltingDuration="300.00" intervalHaltingDurationSum="2847.00" startedHalts="1.00" meanVehicleNumber="9.95" maxVehicleNumber="10" />
   <interval begin="2700.00" end="3000.00" id="turkis_b_e_1" sampledSeconds="9815.00" nVehEntered="59" nVehLeft="60" nVehSeen="90" meanSpeed="0.27" meanTimeLoss="107.73" meanOccupancy="54.26" maxOccupancy="58.33" meanMaxJamLengthInVehicles="19.41" meanMaxJamLengthInMeters="161.39" maxJamLengthInVehicles="35" maxJamLengthInMeters="290.84" jamLengthInVehiclesSum="8771" jamLengthInMetersSum="70662.33" meanHaltingDuration="29.54" maxHaltingDuration="109.00" haltingDurationSum="9011.00" meanIntervalHaltingDuration="26.90" maxIntervalHaltingDuration="109.00" intervalHaltingDurationSum="8206.00" startedHalts="316.00" meanVehicleNumber="32.78" maxVehicleNumber="35" />
   <interval begin="2700.00" end="3000.00" id="yenimahalle_b_e_a_1" sampledSeconds="600.40" nVehEntered="1" nVehLeft="1" nVehSeen="3" meanSpeed="0.03" meanTimeLoss="199.85" meanOccupancy="72.88" maxOccupancy="79.16" meanMaxJamLengthInVehicles="2.00" meanMaxJamLengthInMeters="11.32" maxJamLengthInVehicles="2" maxJamLengthInMeters="12.00" jamLengthInVehiclesSum="600" jamLengthInMetersSum="3395.03" meanHaltingDuration="327.00" maxHaltingDuration="435.00" haltingDurationSum="654.00" meanIntervalHaltingDuration="259.50" maxIntervalHaltingDuration="300.00" intervalHaltingDurationSum="519.00" startedHalts="1.00" meanVehicleNumber="2.00" maxVehicleNumber="3" />
   <interval begin="3000.00" end="3300.00" id="e2_3" sampledSeconds="2978.39" nVehEntered="1" nVehLeft="1" nVehSeen="11" meanSpeed="0.03" meanTimeLoss="270.45" meanOccupancy="66.40" maxOccupancy="67.18" meanMaxJamLengthInVehicles="9.93" meanMaxJamLengthInMeters="69.30" maxJamLengthInVehicles="10" maxJamLengthInMeters="70.00" jamLengthInVehiclesSum="2979" jamLengthInMetersSum="20791.30" meanHaltingDuration="865.80" maxHaltingDuration="1831.00" haltingDurationSum="8658.00" meanIntervalHaltingDuration="282.80" maxIntervalHaltingDuration="300.00" intervalHaltingDurationSum="2828.00" startedHalts="1.00" meanVehicleNumber="9.93" maxVehicleNumber="10" />
   <interval begin="3000.00" end="3300.00" id="turkis_b_e_1" sampledSeconds="10167.41" nVehEntered="27" nVehLeft="28" nVehSeen="57" meanSpeed="0.18" meanTimeLoss="176.90" meanOccupancy="55.56" maxOccupancy="60.02" meanMaxJamLengthInVehicles="21.91" meanMaxJamLengthInMeters="174.18" maxJamLengthInVehicles="37" maxJamLengthInMeters="290.60" jamLengthInVehiclesSum="9496" jamLengthInMetersSum="73758.67" meanHaltingDuration="48.06" maxHaltingDuration="173.00" haltingDurationSum="9709.00" meanIntervalHaltingDuration="44.93" maxIntervalHaltingDuration="173.00" intervalHaltingDurationSum="9076.00" startedHalts="194.00" meanVehicleNumber="33.90" maxVehicleNumber="37" />
   <interval begin="3000.00" end="3300.00" id="yenimahalle_b_e_a_1" sampledSeconds="596.78" nVehEntered="1" nVehLeft="1" nVehSeen="3" meanSpeed="0.03" meanTimeLoss="198.63" meanOccupancy="77.17" maxOccupancy="79.16" meanMaxJamLengthInVehicles="1.99" meanMaxJamLengthInMeters="11.81" maxJamLengthInVehicles="2" maxJamLengthInMeters="12.00" jamLengthInVehiclesSum="597" jamLengthInMetersSum="3542.35" meanHaltingDuration="340.50" maxHaltingDuration="519.00" haltingDurationSum="681.00" meanIntervalHaltingDuration="231.00" maxIntervalHaltingDuration="300.00" intervalHaltingDurationSum="462.00" startedHalts="1.00" meanVehicleNumber="1.99" maxVehicleNumber="2" />
   <interval begin="3300.00" end="3600.00" id="e2_3" sampledSeconds="2986.02" nVehEntered="1" nVehLeft="1" nVehSeen="11" meanSpeed="0.02" meanTimeLoss="271.18" meanOccupancy="66.22" maxOccupancy="67.18" meanMaxJamLengthInVehicles="9.95" meanMaxJamLengthInMeters="69.16" maxJamLengthInVehicles="10" maxJamLengthInMeters="70.00" jamLengthInVehiclesSum="2986" jamLengthInMetersSum="20746.68" meanHaltingDuration="1071.90" maxHaltingDuration="2131.00" haltingDurationSum="10719.00" meanIntervalHaltingDuration="278.60" maxIntervalHaltingDuration="300.00" intervalHaltingDurationSum="2786.00" startedHalts="1.00" meanVehicleNumber="9.96" maxVehicleNumber="10" />
   <interval begin="3300.00" end="3600.00" id="turkis_b_e_1" sampledSeconds="10311.74" nVehEntered="37" nVehLeft="39" nVehSeen="66" meanSpeed="0.21" meanTimeLoss="154.76" meanOccupancy="56.91" maxOccupancy="61.68" meanMaxJamLengthInVehicles="24.83" meanMaxJamLengthInMeters="197.24" maxJamLengthInVehicles="37" maxJamLengthInMeters="297.67" jamLengthInVehiclesSum="9611" jamLengthInMetersSum="74990.38" meanHaltingDuration="46.68" maxHaltingDuration="265.00" haltingDurationSum="9989.00" meanIntervalHaltingDuration="44.16" maxIntervalHaltingDuration="265.00" intervalHaltingDurationSum="9451.00" startedHalts="209.00" meanVehicleNumber="34.41" maxVehicleNumber="38" />
   <interval begin="3300.00" end="3600.00" id="yenimahalle_b_e_a_1" sampledSeconds="599.95" nVehEntered="1" nVehLeft="1" nVehSeen="3" meanSpeed="0.03" meanTimeLoss="199.68" meanOccupancy="74.86" maxOccupancy="79.16" meanMaxJamLengthInVehicles="2.00" meanMaxJamLengthInMeters="11.56" maxJamLengthInVehicles="2" maxJamLengthInMeters="12.00" jamLengthInVehiclesSum="600" jamLengthInMetersSum="3467.53" meanHaltingDuration="309.50" maxHaltingDuration="462.00" haltingDurationSum="619.00" meanIntervalHaltingDuration="228.50" maxIntervalHaltingDuration="300.00" intervalHaltingDurationSum="457.00" startedHalts="1.00" meanVehicleNumber="2.00" maxVehicleNumber="3" />
   <interval begin="3600.00" end="3900.00" id="e2_3" sampledSeconds="2952.15" nVehEntered="3" nVehLeft="3" nVehSeen="13" meanSpeed="0.04" meanTimeLoss="226.66" meanOccupancy="65.13" maxOccupancy="67.18" meanMaxJamLengthInVehicles="9.69" meanMaxJamLengthInMeters="67.63" maxJamLengthInVehicles="10" maxJamLengthInMeters="70.00" jamLengthInVehiclesSum="2928" jamLengthInMetersSum="20410.74" meanHaltingDuration="655.06" maxHaltingDuration="2431.00" haltingDurationSum="10481.00" meanIntervalHaltingDuration="142.56" maxIntervalHaltingDuration="300.00" intervalHaltingDurationSum="2281.00" startedHalts="9.00" meanVehicleNumber="9.85" maxVehicleNumber="10" />
   <interval begin="3600.00" end="3900.00" id="turkis_b_e_1" sampledSeconds="9514.57" nVehEntered="58" nVehLeft="50" nVehSeen="85" meanSpeed="0.38" meanTimeLoss="110.04" meanOccupancy="52.36" maxOccupancy="60.73" meanMaxJamLengthInVehicles="18.42" meanMaxJamLengthInMeters="150.07" maxJamLengthInVehicles="37" maxJamLengthInMeters="299.00" jamLengthInVehiclesSum="8489" jamLengthInMetersSum="66724.16" meanHaltingDuration="34.20" maxHaltingDuration="145.00" haltingDurationSum="8722.00" meanIntervalHaltingDuration="31.38" maxIntervalHaltingDuration="107.00" intervalHaltingDurationSum="8001.00" startedHalts="258.00" meanVehicleNumber="31.75" maxVehicleNumber="37" />
   <interval begin="3600.00" end="3900.00" id="yenimahalle_b_e_a_1" sampledSeconds="599.92" nVehEntered="1" nVehLeft="1" nVehSeen="3" meanSpeed="0.03" meanTimeLoss="199.67" meanOccupancy="73.71" maxOccupancy="79.16" meanMaxJamLengthInVehicles="2.00" meanMaxJamLengthInMeters="11.42" maxJamLengthInVehicles="2" maxJamLengthInMeters="12.00" jamLengthInVehiclesSum="600" jamLengthInMetersSum="3426.16" meanHaltingDuration="275.50" maxHaltingDuration="457.00" haltingDurationSum="551.00" meanIntervalHaltingDuration="197.00" maxIntervalHaltingDuration="300.00" intervalHaltingDurationSum="394.00" startedHalts="1.00" meanVehicleNumber="2.00" maxVehicleNumber="3" />
   <interval begin="3900.00" end="4200.00" id="e2_3" sampledSeconds="3000.00" nVehEntered="0" nVehLeft="0" nVehSeen="10" meanSpeed="0.01" meanTimeLoss="299.89" meanOccupancy="66.99" maxOccupancy="67.15" meanMaxJamLengthInVehicles="10.00" meanMaxJamLengthInMeters="69.53" maxJamLengthInVehicles="10" maxJamLengthInMeters="70.00" jamLengthInVehiclesSum="3000" jamLengthInMetersSum="20860.40" meanHaltingDuration="782.80" maxHaltingDuration="2731.00" haltingDurationSum="7828.00" meanIntervalHaltingDuration="300.00" maxIntervalHaltingDuration="300.00" intervalHaltingDurationSum="3000.00" startedHalts="0.00" meanVehicleNumber="10.00" maxVehicleNumber="10" />
   <interval begin="3900.00" end="4200.00" id="turkis_b_e_1" sampledSeconds="9422.70" nVehEntered="62" nVehLeft="66" nVehSeen="97" meanSpeed="0.41" meanTimeLoss="95.41" meanOccupancy="52.10" maxOccupancy="60.00" meanMaxJamLengthInVehicles="16.31" meanMaxJamLengthInMeters="137.48" maxJamLengthInVehicles="36" maxJamLengthInMeters="297.53" jamLengthInVehiclesSum="8120" jamLengthInMetersSum="65869.90" meanHaltingDuration="24.79" maxHaltingDuration="144.00" haltingDurationSum="8083.00" meanIntervalHaltingDuration="22.27" maxIntervalHaltingDuration="144.00" intervalHaltingDurationSum="7261.00" startedHalts="337.00" meanVehicleNumber="31.46" maxVehicleNumber="36" />
   <interval begin="3900.00" end="4200.00" id="yenimahalle_b_e_a_1" sampledSeconds="600.06" nVehEntered="1" nVehLeft="1" nVehSeen="3" meanSpeed="0.02" meanTimeLoss="199.80" meanOccupancy="77.46" maxOccupancy="79.16" meanMaxJamLengthInVehicles="2.00" meanMaxJamLengthInMeters="11.85" maxJamLengthInVehicles="2" maxJamLengthInMeters="12.00" jamLengthInVehiclesSum="600" jamLengthInMetersSum="3554.32" meanHaltingDuration="203.50" maxHaltingDuration="394.00" haltingDurationSum="407.00" meanIntervalHaltingDuration="156.50" maxIntervalHaltingDuration="300.00" intervalHaltingDurationSum="313.00" startedHalts="1.00" meanVehicleNumber="2.00" maxVehicleNumber="3" />
   <interval begin="4200.00" end="4500.00" id="e2_3" sampledSeconds="2953.22" nVehEntered="5" nVehLeft="5" nVehSeen="15" meanSpeed="0.06" meanTimeLoss="196.34" meanOccupancy="65.71" maxOccupancy="67.15" meanMaxJamLengthInVehicles="9.71" meanMaxJamLengthInMeters="67.87" maxJamLengthInVehicles="10" maxJamLengthInMeters="70.00" jamLengthInVehiclesSum="2924" jamLengthInMetersSum="20398.95" meanHaltingDuration="393.33" maxHaltingDuration="2465.00" haltingDurationSum="7080.00" meanIntervalHaltingDuration="145.78" maxIntervalHaltingDuration="300.00" intervalHaltingDurationSum="2624.00" startedHalts="13.00" meanVehicleNumber="9.86" maxVehicleNumber="10" />
   <interval begin="4200.00" end="4500.00" id="turkis_b_e_1" sampledSeconds="9512.66" nVehEntered="57" nVehLeft="58" nVehSeen="88" meanSpeed="0.48" meanTimeLoss="105.85" meanOccupancy="52.59" maxOccupancy="61.67" meanMaxJamLengthInVehicles="22.77" meanMaxJamLengthInMeters="181.25" maxJamLengthInVehicles="37" maxJamLengthInMeters="297.54" jamLengthInVehiclesSum="8515" jamLengthInMetersSum="66380.09" meanHaltingDuration="40.45" maxHaltingDuration="220.00" haltingDurationSum="7727.00" meanIntervalHaltingDuration="37.94" maxIntervalHaltingDuration="220.00" intervalHaltingDurationSum="7247.00" startedHalts="195.00" meanVehicleNumber="31.75" maxVehicleNumber="37" />
   <interval begin="4200.00" end="4500.00" id="yenimahalle_b_e_a_1" sampledSeconds="598.40" nVehEntered="1" nVehLeft="1" nVehSeen="3" meanSpeed="0.04" meanTimeLoss="199.10" meanOccupancy="75.10" maxOccupancy="79.16" meanMaxJamLengthInVehicles="1.97" meanMaxJamLengthInMeters="11.43" maxJamLengthInVehicles="2" maxJamLengthInMeters="12.00" jamLengthInVehiclesSum="592" jamLengthInMetersSum="3428.60" meanHaltingDuration="250.25" maxHaltingDuration="463.00" haltingDurationSum="1001.00" meanIntervalHaltingDuration="148.50" maxIntervalHaltingDuration="228.00" intervalHaltingDurationSum="594.00" startedHalts="2.00" meanVehicleNumber="2.00" maxVehicleNumber="2" />
   <interval begin="4500.00" end="4800.00" id="e2_3" sampledSeconds="2983.36" nVehEntered="1" nVehLeft="1" nVehSeen="11" meanSpeed="0.02" meanTimeLoss="270.93" meanOccupancy="66.78" maxOccupancy="67.84" meanMaxJamLengthInVehicles="9.82" meanMaxJamLengthInMeters="68.85" maxJamLengthInVehicles="10" maxJamLengthInMeters="70.00" jamLengthInVehiclesSum="2960" jamLengthInMetersSum="20715.81" meanHaltingDuration="320.89" maxHaltingDuration="894.00" haltingDurationSum="6097.00" meanIntervalHaltingDuration="143.10" maxIntervalHaltingDuration="261.00" intervalHaltingDurationSum="2719.00" startedHalts="10.00" meanVehicleNumber="9.95" maxVehicleNumber="10" />
   <interval begin="4500.00" end="4800.00" id="turkis_b_e_1" sampledSeconds="10065.59" nVehEntered="41" nVehLeft="43" nVehSeen="71" meanSpeed="0.38" meanTimeLoss="139.46" meanOccupancy="55.02" maxOccupancy="63.57" meanMaxJamLengthInVehicles="22.74" meanMaxJamLengthInMeters="176.45" maxJamLengthInVehicles="39" maxJamLengthInMeters="299.00" jamLengthInVehiclesSum="9064" jamLengthInMetersSum="69163.08" meanHaltingDuration="38.97" maxHaltingDuration="128.00" haltingDurationSum="9235.00" meanIntervalHaltingDuration="36.24" maxIntervalHaltingDuration="128.00" intervalHaltingDurationSum="8589.00" startedHalts="228.00" meanVehicleNumber="33.59" maxVehicleNumber="39" />
   <interval begin="4500.00" end="4800.00" id="yenimahalle_b_e_a_1" sampledSeconds="600.00" nVehEntered="0" nVehLeft="0" nVehSeen="2" meanSpeed="0.01" meanTimeLoss="299.88" meanOccupancy="64.17" maxOccupancy="78.93" meanMaxJamLengthInVehicles="2.00" meanMaxJamLengthInMeters="10.22" maxJamLengthInVehicles="2" maxJamLengthInMeters="12.00" jamLengthInVehiclesSum="600" jamLengthInMetersSum="3066.89" meanHaltingDuration="527.50" maxHaltingDuration="528.00" haltingDurationSum="1055.00" meanIntervalHaltingDuration="300.00" maxIntervalHaltingDuration="300.00" intervalHaltingDurationSum="600.00" startedHalts="0.00" meanVehicleNumber="2.00" maxVehicleNumber="2" />
   <interval begin="4800.00" end="5100.00" id="e2_3" sampledSeconds="2969.30" nVehEntered="1" nVehLeft="1" nVehSeen="11" meanSpeed="0.01" meanTimeLoss="269.81" meanOccupancy="65.19" maxOccupancy="66.61" meanMaxJamLengthInVehicles="9.88" meanMaxJamLengthInMeters="69.10" maxJamLengthInVehicles="10" maxJamLengthInMeters="70.00" jamLengthInVehiclesSum="2969" jamLengthInMetersSum="20753.88" meanHaltingDuration="330.30" maxHaltingDuration="345.00" haltingDurationSum="3303.00" meanIntervalHaltingDuration="293.70" maxIntervalHaltingDuration="300.00" intervalHaltingDurationSum="2937.00" startedHalts="1.00" meanVehicleNumber="9.90" maxVehicleNumber="10" />
   <interval begin="4800.00" end="5100.00" id="turkis_b_e_1" sampledSeconds="9115.82" nVehEntered="71" nVehLeft="66" nVehSeen="99" meanSpeed="0.64" meanTimeLoss="89.46" meanOccupancy="50.12" maxOccupancy="58.06" meanMaxJamLengthInVehicles="17.27" meanMaxJamLengthInMeters="138.98" maxJamLengthInVehicles="34" maxJamLengthInMeters="299.00" jamLengthInVehiclesSum="7765" jamLengthInMetersSum="60474.48" meanHaltingDuration="31.07" maxHaltingDuration="160.00" haltingDurationSum="8108.00" meanIntervalHaltingDuration="27.17" maxIntervalHaltingDuration="96.00" intervalHaltingDurationSum="7091.00" startedHalts="283.00" meanVehicleNumber="30.44" maxVehicleNumber="35" />
   <interval begin="4800.00" end="5100.00" id="yenimahalle_b_e_a_1" sampledSeconds="601.97" nVehEntered="1" nVehLeft="1" nVehSeen="3" meanSpeed="0.02" meanTimeLoss="200.45" meanOccupancy="75.01" maxOccupancy="77.03" meanMaxJamLengthInVehicles="2.01" meanMaxJamLengthInMeters="11.57" maxJamLengthInVehicles="3" maxJamLengthInMeters="12.00" jamLengthInVehiclesSum="602" jamLengthInMetersSum="3471.79" meanHaltingDuration="557.50" maxHaltingDuration="827.00" haltingDurationSum="1115.00" meanIntervalHaltingDuration="294.00" maxIntervalHaltingDuration="300.00" intervalHaltingDurationSum="588.00" startedHalts="1.00" meanVehicleNumber="2.01" maxVehicleNumber="3" />
   <interval begin="5100.00" end="5400.00" id="e2_3" sampledSeconds="2857.19" nVehEntered="4" nVehLeft="4" nVehSeen="14" meanSpeed="0.08" meanTimeLoss="203.35" meanOccupancy="64.30" maxOccupancy="66.61" meanMaxJamLengthInVehicles="9.44" meanMaxJamLengthInMeters="67.76" maxJamLengthInVehicles="10" maxJamLengthInMeters="70.00" jamLengthInVehiclesSum="2843" jamLengthInMetersSum="20406.95" meanHaltingDuration="368.38" maxHaltingDuration="640.00" haltingDurationSum="4789.00" meanIntervalHaltingDuration="193.69" maxIntervalHaltingDuration="300.00" intervalHaltingDurationSum="2518.00" startedHalts="7.00" meanVehicleNumber="9.53" maxVehicleNumber="10" />
   <interval begin="5100.00" end="5400.00" id="turkis_b_e_1" sampledSeconds="10060.48" nVehEntered="40" nVehLeft="36" nVehSeen="73" meanSpeed="0.27" meanTimeLoss="136.15" meanOccupancy="55.27" maxOccupancy="60.43" meanMaxJamLengthInVehicles="21.49" meanMaxJamLengthInMeters="174.55" maxJamLengthInVehicles="37" maxJamLengthInMeters="299.00" jamLengthInVehiclesSum="9186" jamLengthInMetersSum="72790.64" meanHaltingDuration="43.66" maxHaltingDuration="233.00" haltingDurationSum="10260.00" meanIntervalHaltingDuration="38.15" maxIntervalHaltingDuration="208.00" intervalHaltingDurationSum="8966.00" startedHalts="226.00" meanVehicleNumber="33.55" maxVehicleNumber="37" />
   <interval begin="5100.00" end="5400.00" id="yenimahalle_b_e_a_1" sampledSeconds="597.59" nVehEntered="1" nVehLeft="1" nVehSeen="3" meanSpeed="0.03" meanTimeLoss="198.92" meanOccupancy="69.03" maxOccupancy="78.54" meanMaxJamLengthInVehicles="1.99" meanMaxJamLengthInMeters="10.82" maxJamLengthInVehicles="2" maxJamLengthInMeters="12.00" jamLengthInVehiclesSum="597" jamLengthInMetersSum="3245.43" meanHaltingDuration="426.50" maxHaltingDuration="588.00" haltingDurationSum="853.00" meanIntervalHaltingDuration="282.50" maxIntervalHaltingDuration="300.00" intervalHaltingDurationSum="565.00" startedHalts="1.00" meanVehicleNumber="1.99" maxVehicleNumber="2" />
   <interval begin="5400.00" end="5700.00" id="e2_3" sampledSeconds="2797.06" nVehEntered="1" nVehLeft="2" nVehSeen="11" meanSpeed="0.03" meanTimeLoss="253.99" meanOccupancy="61.51" maxOccupancy="66.41" meanMaxJamLengthInVehicles="9.13" meanMaxJamLengthInMeters="64.29" maxJamLengthInVehicles="10" maxJamLengthInMeters="70.00" jamLengthInVehiclesSum="2771" jamLengthInMetersSum="19479.56" meanHaltingDuration="330.18" maxHaltingDuration="871.00" haltingDurationSum="5613.00" meanIntervalHaltingDuration="146.41" maxIntervalHaltingDuration="242.00" intervalHaltingDurationSum="2489.00" startedHalts="9.00" meanVehicleNumber="9.33" maxVehicleNumber="10" />
   <interval begin="5400.00" end="5700.00" id="turkis_b_e_1" sampledSeconds="9029.28" nVehEntered="66" nVehLeft="74" nVehSeen="103" meanSpeed="0.56" meanTimeLoss="85.44" meanOccupancy="49.33" maxOccupancy="62.06" meanMaxJamLengthInVehicles="19.60" meanMaxJamLengthInMeters="160.67" maxJamLengthInVehicles="38" maxJamLengthInMeters="300.00" jamLengthInVehiclesSum="7861" jamLengthInMetersSum="62700.09" meanHaltingDuration="33.57" maxHaltingDuration="194.00" haltingDurationSum="8123.00" meanIntervalHaltingDuration="29.07" maxIntervalHaltingDuration="155.00" intervalHaltingDurationSum="7034.00" startedHalts="234.00" meanVehicleNumber="30.17" maxVehicleNumber="38" />
   <interval begin="5400.00" end="5700.00" id="yenimahalle_b_e_a_1" sampledSeconds="599.99" nVehEntered="1" nVehLeft="1" nVehSeen="3" meanSpeed="0.03" meanTimeLoss="199.68" meanOccupancy="69.94" maxOccupancy="73.64" meanMaxJamLengthInVehicles="1.99" meanMaxJamLengthInMeters="10.92" maxJamLengthInVehicles="2" maxJamLengthInMeters="12.00" jamLengthInVehiclesSum="598" jamLengthInMetersSum="3277.47" meanHaltingDuration="481.67" maxHaltingDuration="620.00" haltingDurationSum="1445.00" meanIntervalHaltingDuration="197.33" maxIntervalHaltingDuration="300.00" intervalHaltingDurationSum="592.00" startedHalts="2.00" meanVehicleNumber="2.00" maxVehicleNumber="3" />
   <interval begin="5700.00" end="6000.00" id="e2_3" sampledSeconds="2926.83" nVehEntered="2" nVehLeft="1" nVehSeen="11" meanSpeed="0.01" meanTimeLoss="265.96" meanOccupancy="64.58" maxOccupancy="66.41" meanMaxJamLengthInVehicles="9.73" meanMaxJamLengthInMeters="68.07" maxJamLengthInVehicles="10" maxJamLengthInMeters="70.00" jamLengthInVehiclesSum="2923" jamLengthInMetersSum="20440.91" meanHaltingDuration="309.45" maxHaltingDuration="398.00" haltingDurationSum="3404.00" meanIntervalHaltingDuration="255.82" maxIntervalHaltingDuration="300.00" intervalHaltingDurationSum="2814.00" startedHalts="3.00" meanVehicleNumber="9.76" maxVehicleNumber="10" />
   <interval begin="5700.00" end="6000.00" id="turkis_b_e_1" sampledSeconds="9977.39" nVehEntered="46" nVehLeft="38" nVehSeen="75" meanSpeed="0.44" meanTimeLoss="130.36" meanOccupancy="54.87" maxOccupancy="63.33" meanMaxJamLengthInVehicles="23.74" meanMaxJamLengthInMeters="181.40" maxJamLengthInVehicles="38" maxJamLengthInMeters="299.00" jamLengthInVehiclesSum="8904" jamLengthInMetersSum="67899.18" meanHaltingDuration="42.52" maxHaltingDuration="160.00" haltingDurationSum="9226.00" meanIntervalHaltingDuration="40.60" maxIntervalHaltingDuration="160.00" intervalHaltingDurationSum="8810.00" startedHalts="213.00" meanVehicleNumber="33.30" maxVehicleNumber="38" />
   <interval begin="5700.00" end="6000.00" id="yenimahalle_b_e_a_1" sampledSeconds="597.19" nVehEntered="1" nVehLeft="1" nVehSeen="3" meanSpeed="0.03" meanTimeLoss="198.76" meanOccupancy="76.55" maxOccupancy="79.16" meanMaxJamLengthInVehicles="1.99" meanMaxJamLengthInMeters="11.73" maxJamLengthInVehicles="2" maxJamLengthInMeters="12.00" jamLengthInVehiclesSum="597" jamLengthInMetersSum="3518.60" meanHaltingDuration="381.50" maxHaltingDuration="560.00" haltingDurationSum="763.00" meanIntervalHaltingDuration="251.50" maxIntervalHaltingDuration="300.00" intervalHaltingDurationSum="503.00" startedHalts="1.00" meanVehicleNumber="1.99" maxVehicleNumber="2" />
   <interval begin="6000.00" end="6300.00" id="e2_3" sampledSeconds="2976.55" nVehEntered="1" nVehLeft="1" nVehSeen="11" meanSpeed="0.02" meanTimeLoss="270.40" meanOccupancy="64.99" maxOccupancy="67.18" meanMaxJamLengthInVehicles="9.91" meanMaxJamLengthInMeters="69.31" maxJamLengthInVehicles="10" maxJamLengthInMeters="70.00" jamLengthInVehiclesSum="2976" jamLengthInMetersSum="20816.06" meanHaltingDuration="582.20" maxHaltingDuration="698.00" haltingDurationSum="5822.00" meanIntervalHaltingDuration="281.60" maxIntervalHaltingDuration="300.00" intervalHaltingDurationSum="2816.00" startedHalts="1.00" meanVehicleNumber="9.92" maxVehicleNumber="10" />
   <interval begin="6000.00" end="6300.00" id="turkis_b_e_1" sampledSeconds="10214.51" nVehEntered="31" nVehLeft="36" nVehSeen="68" meanSpeed="0.31" meanTimeLoss="148.14" meanOccupancy="55.82" maxOccupancy="62.05" meanMaxJamLengthInVehicles="23.73" meanMaxJamLengthInMeters="184.75" maxJamLengthInVehicles="38" maxJamLengthInMeters="299.00" jamLengthInVehiclesSum="9453" jamLengthInMetersSum="72539.43" meanHaltingDuration="56.19" maxHaltingDuration="226.00" haltingDurationSum="11518.00" meanIntervalHaltingDuration="45.10" maxIntervalHaltingDuration="172.00" intervalHaltingDurationSum="9245.00" startedHalts="184.00" meanVehicleNumber="34.08" maxVehicleNumber="38" />
   <interval begin="6000.00" end="6300.00" id="yenimahalle_b_e_a_1" sampledSeconds="600.75" nVehEntered="1" nVehLeft="1" nVehSeen="3" meanSpeed="0.03" meanTimeLoss="199.95" meanOccupancy="75.02" maxOccupancy="79.16" meanMaxJamLengthInVehicles="2.00" meanMaxJamLengthInMeters="11.58" maxJamLengthInVehicles="3" maxJamLengthInMeters="12.00" jamLengthInVehiclesSum="601" jamLengthInMetersSum="3475.09" meanHaltingDuration="349.00" maxHaltingDuration="503.00" haltingDurationSum="698.00" meanIntervalHaltingDuration="247.50" maxIntervalHaltingDuration="300.00" intervalHaltingDurationSum="495.00" startedHalts="1.00" meanVehicleNumber="2.01" maxVehicleNumber="3" />
   <interval begin="6300.00" end="6600.00" id="e2_3" sampledSeconds="2970.74" nVehEntered="1" nVehLeft="1" nVehSeen="11" meanSpeed="0.03" meanTimeLoss="269.77" meanOccupancy="66.38" maxOccupancy="67.19" meanMaxJamLengthInVehicles="9.90" meanMaxJamLengthInMeters="69.45" maxJamLengthInVehicles="10" maxJamLengthInMeters="70.00" jamLengthInVehiclesSum="2971" jamLengthInMetersSum="20833.94" meanHaltingDuration="792.10" maxHaltingDuration="996.00" haltingDurationSum="7921.00" meanIntervalHaltingDuration="279.70" maxIntervalHaltingDuration="300.00" intervalHaltingDurationSum="2797.00" startedHalts="1.00" meanVehicleNumber="9.91" maxVehicleNumber="10" />
   <interval begin="6300.00" end="6600.00" id="turkis_b_e_1" sampledSeconds="9056.69" nVehEntered="80" nVehLeft="86" nVehSeen="112" meanSpeed="0.89" meanTimeLoss="77.67" meanOccupancy="49.64" maxOccupancy="60.73" meanMaxJamLengthInVehicles="19.59" meanMaxJamLengthInMeters="154.47" maxJamLengthInVehicles="37" maxJamLengthInMeters="299.00" jamLengthInVehiclesSum="7624" jamLengthInMetersSum="58949.36" meanHaltingDuration="33.16" maxHaltingDuration="130.00" haltingDurationSum="7063.00" meanIntervalHaltingDuration="29.35" maxIntervalHaltingDuration="130.00" intervalHaltingDurationSum="6252.00" startedHalts="223.00" meanVehicleNumber="30.29" maxVehicleNumber="37" />
   <interval begin="6300.00" end="6600.00" id="yenimahalle_b_e_a_1" sampledSeconds="597.00" nVehEntered="1" nVehLeft="1" nVehSeen="3" meanSpeed="0.03" meanTimeLoss="198.66" meanOccupancy="78.01" maxOccupancy="79.16" meanMaxJamLengthInVehicles="1.99" meanMaxJamLengthInMeters="11.90" maxJamLengthInVehicles="2" maxJamLengthInMeters="12.00" jamLengthInVehiclesSum="597" jamLengthInMetersSum="3570.26" meanHaltingDuration="317.00" maxHaltingDuration="495.00" haltingDurationSum="634.00" meanIntervalHaltingDuration="219.50" maxIntervalHaltingDuration="300.00" intervalHaltingDurationSum="439.00" startedHalts="1.00" meanVehicleNumber="1.99" maxVehicleNumber="2" />
   <interval begin="6600.00" end="6900.00" id="e2_3" sampledSeconds="2960.37" nVehEntered="1" nVehLeft="1" nVehSeen="11" meanSpeed="0.02" meanTimeLoss="268.83" meanOccupancy="66.08" maxOccupancy="67.18" meanMaxJamLengthInVehicles="9.87" meanMaxJamLengthInMeters="69.16" maxJamLengthInVehicles="10" maxJamLengthInMeters="70.00" jamLengthInVehiclesSum="2961" jamLengthInMetersSum="20747.26" meanHaltingDuration="966.00" maxHaltingDuration="1263.00" haltingDurationSum="9660.00" meanIntervalHaltingDuration="273.50" maxIntervalHaltingDuration="300.00" intervalHaltingDurationSum="2735.00" startedHalts="1.00" meanVehicleNumber="9.87" maxVehicleNumber="10" />
   <interval begin="6600.00" end="6900.00" id="turkis_b_e_1" sampledSeconds="10437.16" nVehEntered="50" nVehLeft="40" nVehSeen="76" meanSpeed="0.47" meanTimeLoss="134.50" meanOccupancy="57.40" maxOccupancy="62.60" meanMaxJamLengthInVehicles="25.10" meanMaxJamLengthInMeters="192.30" maxJamLengthInVehicles="38" maxJamLengthInMeters="299.00" jamLengthInVehiclesSum="9249" jamLengthInMetersSum="70048.46" meanHaltingDuration="41.67" maxHaltingDuration="225.00" haltingDurationSum="9209.00" meanIntervalHaltingDuration="40.96" maxIntervalHaltingDuration="225.00" intervalHaltingDurationSum="9053.00" startedHalts="231.00" meanVehicleNumber="34.84" maxVehicleNumber="39" />
   <interval begin="6600.00" end="6900.00" id="yenimahalle_b_e_a_1" sampledSeconds="600.78" nVehEntered="1" nVehLeft="1" nVehSeen="3" meanSpeed="0.03" meanTimeLoss="199.96" meanOccupancy="74.70" maxOccupancy="79.16" meanMaxJamLengthInVehicles="2.00" meanMaxJamLengthInMeters="11.54" maxJamLengthInVehicles="3" maxJamLengthInMeters="12.00" jamLengthInVehiclesSum="601" jamLengthInMetersSum="3463.46" meanHaltingDuration="286.00" maxHaltingDuration="439.00" haltingDurationSum="572.00" meanIntervalHaltingDuration="216.50" maxIntervalHaltingDuration="300.00" intervalHaltingDurationSum="433.00" startedHalts="1.00" meanVehicleNumber="2.01" maxVehicleNumber="3" />
   <interval begin="6900.00" end="7200.00" id="e2_3" sampledSeconds="2943.49" nVehEntered="0" nVehLeft="1" nVehSeen="10" meanSpeed="0.02" meanTimeLoss="294.09" meanOccupancy="66.09" maxOccupancy="66.94" meanMaxJamLengthInVehicles="9.81" meanMaxJamLengthInMeters="68.93" maxJamLengthInVehicles="10" maxJamLengthInMeters="70.00" jamLengthInVehiclesSum="2944" jamLengthInMetersSum="20678.35" meanHaltingDuration="1260.11" maxHaltingDuration="1563.00" haltingDurationSum="11341.00" meanIntervalHaltingDuration="300.00" maxIntervalHaltingDuration="300.00" intervalHaltingDurationSum="2700.00" startedHalts="0.00" meanVehicleNumber="9.81" maxVehicleNumber="10" />
   <interval begin="6900.00" end="7200.00" id="turkis_b_e_1" sampledSeconds="9864.56" nVehEntered="42" nVehLeft="46" nVehSeen="78" meanSpeed="0.50" meanTimeLoss="123.75" meanOccupancy="54.00" maxOccupancy="61.80" meanMaxJamLengthInVehicles="20.98" meanMaxJamLengthInMeters="164.56" maxJamLengthInVehicles="38" maxJamLengthInMeters="299.00" jamLengthInVehiclesSum="8712" jamLengthInMetersSum="66668.72" meanHaltingDuration="36.22" maxHaltingDuration="123.00" haltingDurationSum="9308.00" meanIntervalHaltingDuration="31.49" maxIntervalHaltingDuration="112.00" intervalHaltingDurationSum="8092.00" startedHalts="249.00" meanVehicleNumber="32.91" maxVehicleNumber="38" />
   <interval begin="6900.00" end="7200.00" id="yenimahalle_b_e_a_1" sampledSeconds="597.03" nVehEntered="1" nVehLeft="1" nVehSeen="3" meanSpeed="0.03" meanTimeLoss="198.70" meanOccupancy="77.83" maxOccupancy="79.16" meanMaxJamLengthInVehicles="1.98" meanMaxJamLengthInMeters="11.84" maxJamLengthInVehicles="2" maxJamLengthInMeters="12.00" jamLengthInVehiclesSum="595" jamLengthInMetersSum="3550.69" meanHaltingDuration="389.00" maxHaltingDuration="661.00" haltingDurationSum="1167.00" meanIntervalHaltingDuration="198.33" maxIntervalHaltingDuration="300.00" intervalHaltingDurationSum="595.00" startedHalts="2.00" meanVehicleNumber="2.00" maxVehicleNumber="2" />
   <interval begin="7200.00" end="7500.00" id="e2_3" sampledSeconds="2959.21" nVehEntered="1" nVehLeft="0" nVehSeen="10" meanSpeed="0.01" meanTimeLoss="295.84" meanOccupancy="65.69" maxOccupancy="66.23" meanMaxJamLengthInVehicles="9.86" meanMaxJamLengthInMeters="68.92" maxJamLengthInVehicles="10" maxJamLengthInMeters="70.00" jamLengthInVehiclesSum="2959" jamLengthInMetersSum="20674.93" meanHaltingDuration="1430.10" maxHaltingDuration="1863.00" haltingDurationSum="14301.00" meanIntervalHaltingDuration="296.00" maxIntervalHaltingDuration="300.00" intervalHaltingDurationSum="2960.00" startedHalts="1.00" meanVehicleNumber="9.87" maxVehicleNumber="10" />
   <interval begin="7200.00" end="7500.00" id="turkis_b_e_1" sampledSeconds="9627.43" nVehEntered="57" nVehLeft="62" nVehSeen="89" meanSpeed="0.46" meanTimeLoss="106.04" meanOccupancy="52.99" maxOccupancy="62.12" meanMaxJamLengthInVehicles="18.72" meanMaxJamLengthInMeters="148.99" maxJamLengthInVehicles="37" maxJamLengthInMeters="299.00" jamLengthInVehiclesSum="8505" jamLengthInMetersSum="65792.77" meanHaltingDuration="34.09" maxHaltingDuration="117.00" haltingDurationSum="8728.00" meanIntervalHaltingDuration="31.58" maxIntervalHaltingDuration="117.00" intervalHaltingDurationSum="8084.00" startedHalts="254.00" meanVehicleNumber="32.14" maxVehicleNumber="38" />
   <interval begin="7200.00" end="7500.00" id="yenimahalle_b_e_a_1" sampledSeconds="600.00" nVehEntered="0" nVehLeft="0" nVehSeen="2" meanSpeed="0.00" meanTimeLoss="299.96" meanOccupancy="76.84" maxOccupancy="79.16" meanMaxJamLengthInVehicles="2.00" meanMaxJamLengthInMeters="11.73" maxJamLengthInVehicles="2" maxJamLengthInMeters="12.00" jamLengthInVehiclesSum="600" jamLengthInMetersSum="3519.20" meanHaltingDuration="553.00" maxHaltingDuration="733.00" haltingDurationSum="1106.00" meanIntervalHaltingDuration="300.00" maxIntervalHaltingDuration="300.00" intervalHaltingDurationSum="600.00" startedHalts="0.00" meanVehicleNumber="2.00" maxVehicleNumber="2" />
   <interval begin="7500.00" end="7800.00" id="e2_3" sampledSeconds="2945.28" nVehEntered="1" nVehLeft="1" nVehSeen="11" meanSpeed="0.02" meanTimeLoss="267.49" meanOccupancy="65.95" maxOccupancy="67.84" meanMaxJamLengthInVehicles="9.71" meanMaxJamLengthInMeters="68.53" maxJamLengthInVehicles="10" maxJamLengthInMeters="70.00" jamLengthInVehiclesSum="2935" jamLengthInMetersSum="20713.33" meanHaltingDuration="1149.33" maxHaltingDuration="2162.00" haltingDurationSum="17240.00" meanIntervalHaltingDuration="195.93" maxIntervalHaltingDuration="300.00" intervalHaltingDurationSum="2939.00" startedHalts="6.00" meanVehicleNumber="9.82" maxVehicleNumber="10" />
   <interval begin="7500.00" end="7800.00" id="turkis_b_e_1" sampledSeconds="9327.27" nVehEntered="57" nVehLeft="53" nVehSeen="84" meanSpeed="0.61" meanTimeLoss="108.15" meanOccupancy="51.28" maxOccupancy="61.67" meanMaxJamLengthInVehicles="17.64" meanMaxJamLengthInMeters="139.56" maxJamLengthInVehicles="35" maxJamLengthInMeters="299.00" jamLengthInVehiclesSum="8025" jamLengthInMetersSum="61882.58" meanHaltingDuration="30.46" maxHaltingDuration="177.00" haltingDurationSum="8559.00" meanIntervalHaltingDuration="26.43" maxIntervalHaltingDuration="99.00" intervalHaltingDurationSum="7427.00" startedHalts="293.00" meanVehicleNumber="31.12" maxVehicleNumber="37" />
   <interval begin="7500.00" end="7800.00" id="yenimahalle_b_e_a_1" sampledSeconds="596.49" nVehEntered="2" nVehLeft="2" nVehSeen="4" meanSpeed="0.03" meanTimeLoss="148.91" meanOccupancy="72.68" maxOccupancy="75.54" meanMaxJamLengthInVehicles="1.97" meanMaxJamLengthInMeters="11.14" maxJamLengthInVehicles="2" maxJamLengthInMeters="11.57" jamLengthInVehiclesSum="592" jamLengthInMetersSum="3340.58" meanHaltingDuration="138.00" maxHaltingDuration="140.00" haltingDurationSum="276.00" meanIntervalHaltingDuration="138.00" maxIntervalHaltingDuration="140.00" intervalHaltingDurationSum="276.00" startedHalts="2.00" meanVehicleNumber="1.99" maxVehicleNumber="2" />
   <interval begin="7800.00" end="8100.00" id="e2_3" sampledSeconds="3000.00" nVehEntered="0" nVehLeft="0" nVehSeen="10" meanSpeed="0.02" meanTimeLoss="299.80" meanOccupancy="66.33" maxOccupancy="67.69" meanMaxJamLengthInVehicles="10.00" meanMaxJamLengthInMeters="69.52" maxJamLengthInVehicles="10" maxJamLengthInMeters="70.00" jamLengthInVehiclesSum="3000" jamLengthInMetersSum="20855.54" meanHaltingDuration="1130.30" maxHaltingDuration="2462.00" haltingDurationSum="11303.00" meanIntervalHaltingDuration="300.00" maxIntervalHaltingDuration="300.00" intervalHaltingDurationSum="3000.00" startedHalts="0.00" meanVehicleNumber="10.00" maxVehicleNumber="10" />
   <interval begin="7800.00" end="8100.00" id="turkis_b_e_1" sampledSeconds="9801.79" nVehEntered="41" nVehLeft="42" nVehSeen="72" meanSpeed="0.37" meanTimeLoss="133.98" meanOccupancy="53.48" maxOccupancy="60.00" meanMaxJamLengthInVehicles="17.76" meanMaxJamLengthInMeters="144.15" maxJamLengthInVehicles="35" maxJamLengthInMeters="299.00" jamLengthInVehiclesSum="8717" jamLengthInMetersSum="69126.56" meanHaltingDuration="31.03" maxHaltingDuration="110.00" haltingDurationSum="8907.00" meanIntervalHaltingDuration="29.76" maxIntervalHaltingDuration="110.00" intervalHaltingDurationSum="8541.00" startedHalts="279.00" meanVehicleNumber="32.71" maxVehicleNumber="36" />
   <interval begin="7800.00" end="8100.00" id="yenimahalle_b_e_a_1" sampledSeconds="600.07" nVehEntered="1" nVehLeft="1" nVehSeen="3" meanSpeed="0.03" meanTimeLoss="199.73" meanOccupancy="71.69" maxOccupancy="79.16" meanMaxJamLengthInVehicles="2.00" meanMaxJamLengthInMeters="11.18" maxJamLengthInVehicles="2" maxJamLengthInMeters="12.00" jamLengthInVehiclesSum="600" jamLengthInMetersSum="3353.73" meanHaltingDuration="275.00" maxHaltingDuration="436.00" haltingDurationSum="550.00" meanIntervalHaltingDuration="207.00" maxIntervalHaltingDuration="300.00" intervalHaltingDurationSum="414.00" startedHalts="1.00" meanVehicleNumber="2.00" maxVehicleNumber="3" />
   <interval begin="8100.00" end="8400.00" id="e2_3" sampledSeconds="2922.16" nVehEntered="1" nVehLeft="1" nVehSeen="11" meanSpeed="0.01" meanTimeLoss="265.51" meanOccupancy="65.62" maxOccupancy="66.27" meanMaxJamLengthInVehicles="9.71" meanMaxJamLengthInMeters="68.61" maxJamLengthInVehicles="10" maxJamLengthInMeters="70.00" jamLengthInVehiclesSum="2918" jamLengthInMetersSum="20601.86" meanHaltingDuration="969.50" maxHaltingDuration="2613.00" haltingDurationSum="11634.00" meanIntervalHaltingDuration="232.75" maxIntervalHaltingDuration="300.00" intervalHaltingDurationSum="2793.00" startedHalts="3.00" meanVehicleNumber="9.74" maxVehicleNumber="10" />
   <interval begin="8100.00" end="8400.00" id="turkis_b_e_1" sampledSeconds="9528.76" nVehEntered="73" nVehLeft="67" nVehSeen="103" meanSpeed="0.62" meanTimeLoss="90.00" meanOccupancy="52.46" maxOccupancy="62.81" meanMaxJamLengthInVehicles="18.64" meanMaxJamLengthInMeters="145.36" maxJamLengthInVehicles="37" maxJamLengthInMeters="299.00" jamLengthInVehiclesSum="8024" jamLengthInMetersSum="60769.10" meanHaltingDuration="25.21" maxHaltingDuration="117.00" haltingDurationSum="7715.00" meanIntervalHaltingDuration="23.81" maxIntervalHaltingDuration="117.00" intervalHaltingDurationSum="7285.00" startedHalts="318.00" meanVehicleNumber="31.81" maxVehicleNumber="38" />
   <interval begin="8100.00" end="8400.00" id="yenimahalle_b_e_a_1" sampledSeconds="601.06" nVehEntered="1" nVehLeft="1" nVehSeen="3" meanSpeed="0.02" meanTimeLoss="200.13" meanOccupancy="76.19" maxOccupancy="79.16" meanMaxJamLengthInVehicles="2.00" meanMaxJamLengthInMeters="11.70" maxJamLengthInVehicles="3" maxJamLengthInMeters="12.00" jamLengthInVehiclesSum="601" jamLengthInMetersSum="3510.56" meanHaltingDuration="223.50" maxHaltingDuration="414.00" haltingDurationSum="447.00" meanIntervalHaltingDuration="166.50" maxIntervalHaltingDuration="300.00" intervalHaltingDurationSum="333.00" startedHalts="1.00" meanVehicleNumber="2.01" maxVehicleNumber="3" />
   <interval begin="8400.00" end="8700.00" id="e2_3" sampledSeconds="2920.10" nVehEntered="1" nVehLeft="1" nVehSeen="11" meanSpeed="0.02" meanTimeLoss="265.25" meanOccupancy="65.95" maxOccupancy="67.84" meanMaxJamLengthInVehicles="9.69" meanMaxJamLengthInMeters="68.25" maxJamLengthInVehicles="10" maxJamLengthInMeters="70.00" jamLengthInVehiclesSum="2914" jamLengthInMetersSum="20516.88" meanHaltingDuration="836.69" maxHaltingDuration="2375.00" haltingDurationSum="10877.00" meanIntervalHaltingDuration="224.31" maxIntervalHaltingDuration="300.00" intervalHaltingDurationSum="2916.00" startedHalts="4.00" meanVehicleNumber="9.74" maxVehicleNumber="10" />
   <interval begin="8400.00" end="8700.00" id="turkis_b_e_1" sampledSeconds="9841.76" nVehEntered="42" nVehLeft="52" nVehSeen="78" meanSpeed="0.43" meanTimeLoss="123.79" meanOccupancy="53.99" maxOccupancy="61.67" meanMaxJamLengthInVehicles="23.28" meanMaxJamLengthInMeters="180.67" maxJamLengthInVehicles="37" maxJamLengthInMeters="297.99" jamLengthInVehiclesSum="8990" jamLengthInMetersSum="68610.04" meanHaltingDuration="51.21" maxHaltingDuration="170.00" haltingDurationSum="10038.00" meanIntervalHaltingDuration="44.62" maxIntervalHaltingDuration="144.00" intervalHaltingDurationSum="8746.00" startedHalts="173.00" meanVehicleNumber="32.88" maxVehicleNumber="37" />
   <interval begin="8400.00" end="8700.00" id="yenimahalle_b_e_a_1" sampledSeconds="600.00" nVehEntered="0" nVehLeft="0" nVehSeen="2" meanSpeed="0.01" meanTimeLoss="299.92" meanOccupancy="73.42" maxOccupancy="76.22" meanMaxJamLengthInVehicles="2.00" meanMaxJamLengthInMeters="11.33" maxJamLengthInVehicles="2" maxJamLengthInMeters="11.65" jamLengthInVehiclesSum="600" jamLengthInMetersSum="3398.45" meanHaltingDuration="523.50" maxHaltingDuration="714.00" haltingDurationSum="1047.00" meanIntervalHaltingDuration="300.00" maxIntervalHaltingDuration="300.00" intervalHaltingDurationSum="600.00" startedHalts="0.00" meanVehicleNumber="2.00" maxVehicleNumber="2" />
   <interval begin="8700.00" end="9000.00" id="e2_3" sampledSeconds="3000.00" nVehEntered="0" nVehLeft="0" nVehSeen="10" meanSpeed="0.02" meanTimeLoss="299.76" meanOccupancy="64.67" maxOccupancy="66.25" meanMaxJamLengthInVehicles="9.86" meanMaxJamLengthInMeters="68.19" maxJamLengthInVehicles="10" maxJamLengthInMeters="70.00" jamLengthInVehiclesSum="2986" jamLengthInMetersSum="20598.31" meanHaltingDuration="644.50" maxHaltingDuration="2497.00" haltingDurationSum="10312.00" meanIntervalHaltingDuration="187.00" maxIntervalHaltingDuration="300.00" intervalHaltingDurationSum="2992.00" startedHalts="6.00" meanVehicleNumber="10.00" maxVehicleNumber="10" />
   <interval begin="8700.00" end="9000.00" id="turkis_b_e_1" sampledSeconds="9132.07" nVehEntered="77" nVehLeft="73" nVehSeen="103" meanSpeed="0.62" meanTimeLoss="86.21" meanOccupancy="50.34" maxOccupancy="63.33" meanMaxJamLengthInVehicles="16.47" meanMaxJamLengthInMeters="135.28" maxJamLengthInVehicles="37" maxJamLengthInMeters="296.89" jamLengthInVehiclesSum="7754" jamLengthInMetersSum="61314.05" meanHaltingDuration="28.87" maxHaltingDuration="145.00" haltingDurationSum="7996.00" meanIntervalHaltingDuration="26.58" maxIntervalHaltingDuration="129.00" intervalHaltingDurationSum="7362.00" startedHalts="294.00" meanVehicleNumber="30.50" maxVehicleNumber="38" />
   <interval begin="8700.00" end="9000.00" id="yenimahalle_b_e_a_1" sampledSeconds="600.68" nVehEntered="1" nVehLeft="1" nVehSeen="3" meanSpeed="0.03" meanTimeLoss="199.90" meanOccupancy="73.27" maxOccupancy="79.16" meanMaxJamLengthInVehicles="2.00" meanMaxJamLengthInMeters="11.38" maxJamLengthInVehicles="3" maxJamLengthInMeters="12.00" jamLengthInVehiclesSum="601" jamLengthInMetersSum="3415.43" meanHaltingDuration="444.00" maxHaltingDuration="633.00" haltingDurationSum="888.00" meanIntervalHaltingDuration="277.50" maxIntervalHaltingDuration="300.00" intervalHaltingDurationSum="555.00" startedHalts="1.00" meanVehicleNumber="2.01" maxVehicleNumber="3" />
   <interval begin="9000.00" end="9300.00" id="e2_3" sampledSeconds="2900.84" nVehEntered="1" nVehLeft="1" nVehSeen="11" meanSpeed="0.03" meanTimeLoss="263.39" meanOccupancy="63.77" maxOccupancy="66.24" meanMaxJamLengthInVehicles="9.56" meanMaxJamLengthInMeters="67.57" maxJamLengthInVehicles="10" maxJamLengthInMeters="70.00" jamLengthInVehiclesSum="2889" jamLengthInMetersSum="20382.96" meanHaltingDuration="660.36" maxHaltingDuration="2797.00" haltingDurationSum="9245.00" meanIntervalHaltingDuration="203.93" maxIntervalHaltingDuration="300.00" intervalHaltingDurationSum="2855.00" startedHalts="5.00" meanVehicleNumber="9.67" maxVehicleNumber="10" />
   <interval begin="9000.00" end="9300.00" id="turkis_b_e_1" sampledSeconds="9491.42" nVehEntered="63" nVehLeft="60" nVehSeen="93" meanSpeed="0.55" meanTimeLoss="99.56" meanOccupancy="52.28" maxOccupancy="60.00" meanMaxJamLengthInVehicles="17.95" meanMaxJamLengthInMeters="141.79" maxJamLengthInVehicles="36" maxJamLengthInMeters="298.78" jamLengthInVehiclesSum="8086" jamLengthInMetersSum="62362.85" meanHaltingDuration="28.28" maxHaltingDuration="231.00" haltingDurationSum="8343.00" meanIntervalHaltingDuration="24.38" maxIntervalHaltingDuration="154.00" intervalHaltingDurationSum="7192.00" startedHalts="302.00" meanVehicleNumber="31.67" maxVehicleNumber="36" />
   <interval begin="9000.00" end="9300.00" id="yenimahalle_b_e_a_1" sampledSeconds="600.74" nVehEntered="1" nVehLeft="1" nVehSeen="3" meanSpeed="0.03" meanTimeLoss="199.94" meanOccupancy="74.13" maxOccupancy="79.16" meanMaxJamLengthInVehicles="2.00" meanMaxJamLengthInMeters="11.48" maxJamLengthInVehicles="3" maxJamLengthInMeters="12.00" jamLengthInVehiclesSum="601" jamLengthInMetersSum="3442.98" meanHaltingDuration="363.00" maxHaltingDuration="555.00" haltingDurationSum="726.00" meanIntervalHaltingDuration="235.50" maxIntervalHaltingDuration="300.00" intervalHaltingDurationSum="471.00" startedHalts="1.00" meanVehicleNumber="2.01" maxVehicleNumber="3" />
   <interval begin="9300.00" end="9600.00" id="e2_3" sampledSeconds="2895.89" nVehEntered="1" nVehLeft="1" nVehSeen="11" meanSpeed="0.02" meanTimeLoss="263.06" meanOccupancy="65.10" maxOccupancy="66.65" meanMaxJamLengthInVehicles="9.63" meanMaxJamLengthInMeters="68.30" maxJamLengthInVehicles="10" maxJamLengthInMeters="70.00" jamLengthInVehiclesSum="2894" jamLengthInMetersSum="20530.72" meanHaltingDuration="816.91" maxHaltingDuration="3097.00" haltingDurationSum="8986.00" meanIntervalHaltingDuration="257.00" maxIntervalHaltingDuration="300.00" intervalHaltingDurationSum="2827.00" startedHalts="2.00" meanVehicleNumber="9.66" maxVehicleNumber="10" />
   <interval begin="9300.00" end="9600.00" id="turkis_b_e_1" sampledSeconds="9653.71" nVehEntered="58" nVehLeft="55" nVehSeen="91" meanSpeed="0.46" meanTimeLoss="103.98" meanOccupancy="52.97" maxOccupancy="62.88" meanMaxJamLengthInVehicles="19.57" meanMaxJamLengthInMeters="154.59" maxJamLengthInVehicles="38" maxJamLengthInMeters="299.00" jamLengthInVehiclesSum="8415" jamLengthInMetersSum="64669.79" meanHaltingDuration="29.18" maxHaltingDuration="127.00" haltingDurationSum="8432.00" meanIntervalHaltingDuration="27.49" maxIntervalHaltingDuration="127.00" intervalHaltingDurationSum="7945.00" startedHalts="291.00" meanVehicleNumber="32.21" maxVehicleNumber="38" />
   <interval begin="9300.00" end="9600.00" id="yenimahalle_b_e_a_1" sampledSeconds="597.70" nVehEntered="1" nVehLeft="1" nVehSeen="3" meanSpeed="0.03" meanTimeLoss="198.92" meanOccupancy="78.07" maxOccupancy="79.16" meanMaxJamLengthInVehicles="1.99" meanMaxJamLengthInMeters="11.92" maxJamLengthInVehicles="2" maxJamLengthInMeters="12.00" jamLengthInVehiclesSum="598" jamLengthInMetersSum="3574.94" meanHaltingDuration="285.50" maxHaltingDuration="471.00" haltingDurationSum="571.00" meanIntervalHaltingDuration="200.00" maxIntervalHaltingDuration="300.00" intervalHaltingDurationSum="400.00" startedHalts="1.00" meanVehicleNumber="2.00" maxVehicleNumber="2" />
   <interval begin="9600.00" end="9900.00" id="e2_3" sampledSeconds="2953.60" nVehEntered="1" nVehLeft="2" nVehSeen="11" meanSpeed="0.02" meanTimeLoss="268.31" meanOccupancy="66.59" maxOccupancy="67.84" meanMaxJamLengthInVehicles="9.83" meanMaxJamLengthInMeters="69.80" maxJamLengthInVehicles="10" maxJamLengthInMeters="70.00" jamLengthInVehiclesSum="2952" jamLengthInMetersSum="20947.96" meanHaltingDuration="915.00" maxHaltingDuration="3397.00" haltingDurationSum="9150.00" meanIntervalHaltingDuration="268.60" maxIntervalHaltingDuration="300.00" intervalHaltingDurationSum="2686.00" startedHalts="1.00" meanVehicleNumber="9.85" maxVehicleNumber="10" />
   <interval begin="9600.00" end="9900.00" id="turkis_b_e_1" sampledSeconds="10092.05" nVehEntered="41" nVehLeft="43" nVehSeen="77" meanSpeed="0.32" meanTimeLoss="129.27" meanOccupancy="55.56" maxOccupancy="59.54" meanMaxJamLengthInVehicles="20.74" meanMaxJamLengthInMeters="162.73" maxJamLengthInVehicles="36" maxJamLengthInMeters="299.00" jamLengthInVehiclesSum="9097" jamLengthInMetersSum="69913.98" meanHaltingDuration="39.20" maxHaltingDuration="187.00" haltingDurationSum="9761.00" meanIntervalHaltingDuration="34.04" maxIntervalHaltingDuration="107.00" intervalHaltingDurationSum="8477.00" startedHalts="237.00" meanVehicleNumber="33.67" maxVehicleNumber="36" />
   <interval begin="9600.00" end="9900.00" id="yenimahalle_b_e_a_1" sampledSeconds="599.75" nVehEntered="1" nVehLeft="1" nVehSeen="3" meanSpeed="0.03" meanTimeLoss="199.61" meanOccupancy="74.86" maxOccupancy="79.16" meanMaxJamLengthInVehicles="2.00" meanMaxJamLengthInMeters="11.56" maxJamLengthInVehicles="2" maxJamLengthInMeters="12.00" jamLengthInVehiclesSum="600" jamLengthInMetersSum="3467.67" meanHaltingDuration="246.50" maxHaltingDuration="400.00" haltingDurationSum="493.00" meanIntervalHaltingDuration="196.50" maxIntervalHaltingDuration="300.00" intervalHaltingDurationSum="393.00" startedHalts="1.00" meanVehicleNumber="2.00" maxVehicleNumber="3" />
   <interval begin="9900.00" end="10200.00" id="e2_3" sampledSeconds="2974.57" nVehEntered="1" nVehLeft="0" nVehSeen="10" meanSpeed="0.02" meanTimeLoss="297.20" meanOccupancy="66.48" maxOccupancy="67.18" meanMaxJamLengthInVehicles="9.88" meanMaxJamLengthInMeters="69.30" maxJamLengthInVehicles="10" maxJamLengthInMeters="70.00" jamLengthInVehiclesSum="2968" jamLengthInMetersSum="20804.38" meanHaltingDuration="948.25" maxHaltingDuration="3697.00" haltingDurationSum="11379.00" meanIntervalHaltingDuration="247.58" maxIntervalHaltingDuration="300.00" intervalHaltingDurationSum="2971.00" startedHalts="3.00" meanVehicleNumber="9.92" maxVehicleNumber="10" />
   <interval begin="9900.00" end="10200.00" id="turkis_b_e_1" sampledSeconds="9189.47" nVehEntered="66" nVehLeft="71" nVehSeen="100" meanSpeed="0.63" meanTimeLoss="89.31" meanOccupancy="50.50" maxOccupancy="60.00" meanMaxJamLengthInVehicles="18.78" meanMaxJamLengthInMeters="149.60" maxJamLengthInVehicles="33" maxJamLengthInMeters="286.53" jamLengthInVehiclesSum="7802" jamLengthInMetersSum="60568.11" meanHaltingDuration="28.71" maxHaltingDuration="132.00" haltingDurationSum="7866.00" meanIntervalHaltingDuration="25.09" maxIntervalHaltingDuration="104.00" intervalHaltingDurationSum="6875.00" startedHalts="282.00" meanVehicleNumber="30.70" maxVehicleNumber="36" />
   <interval begin="9900.00" end="10200.00" id="yenimahalle_b_e_a_1" sampledSeconds="603.47" nVehEntered="1" nVehLeft="1" nVehSeen="3" meanSpeed="0.02" meanTimeLoss="200.91" meanOccupancy="76.38" maxOccupancy="79.16" meanMaxJamLengthInVehicles="2.00" meanMaxJamLengthInMeters="11.65" maxJamLengthInVehicles="3" maxJamLengthInMeters="12.00" jamLengthInVehiclesSum="599" jamLengthInMetersSum="3495.34" meanHaltingDuration="272.00" maxHaltingDuration="662.00" haltingDurationSum="1088.00" meanIntervalHaltingDuration="148.75" maxIntervalHaltingDuration="263.00" intervalHaltingDurationSum="595.00" startedHalts="3.00" meanVehicleNumber="2.01" maxVehicleNumber="3" />
   <interval begin="10200.00" end="10500.00" id="e2_3" sampledSeconds="2979.35" nVehEntered="1" nVehLeft="1" nVehSeen="11" meanSpeed="0.01" meanTimeLoss="270.74" meanOccupancy="66.36" maxOccupancy="67.03" meanMaxJamLengthInVehicles="9.93" meanMaxJamLengthInMeters="69.01" maxJamLengthInVehicles="10" maxJamLengthInMeters="69.78" jamLengthInVehiclesSum="2979" jamLengthInMetersSum="20703.97" meanHaltingDuration="937.80" maxHaltingDuration="1672.00" haltingDurationSum="9378.00" meanIntervalHaltingDuration="293.20" maxIntervalHaltingDuration="300.00" intervalHaltingDurationSum="2932.00" startedHalts="1.00" meanVehicleNumber="9.93" maxVehicleNumber="10" />
   <interval begin="10200.00" end="10500.00" id="turkis_b_e_1" sampledSeconds="9271.21" nVehEntered="83" nVehLeft="77" nVehSeen="112" meanSpeed="0.57" meanTimeLoss="80.66" meanOccupancy="50.78" maxOccupancy="59.32" meanMaxJamLengthInVehicles="17.32" meanMaxJamLengthInMeters="139.61" maxJamLengthInVehicles="36" maxJamLengthInMeters="299.00" jamLengthInVehiclesSum="7942" jamLengthInMetersSum="61871.95" meanHaltingDuration="25.59" maxHaltingDuration="80.00" haltingDurationSum="7497.00" meanIntervalHaltingDuration="24.30" maxIntervalHaltingDuration="80.00" intervalHaltingDurationSum="7119.00" startedHalts="313.00" meanVehicleNumber="30.96" maxVehicleNumber="36" />
   <interval begin="10200.00" end="10500.00" id="yenimahalle_b_e_a_1" sampledSeconds="600.00" nVehEntered="0" nVehLeft="0" nVehSeen="2" meanSpeed="0.01" meanTimeLoss="299.90" meanOccupancy="76.36" maxOccupancy="79.16" meanMaxJamLengthInVehicles="2.00" meanMaxJamLengthInMeters="11.68" maxJamLengthInVehicles="2" maxJamLengthInMeters="12.00" jamLengthInVehiclesSum="600" jamLengthInMetersSum="3505.03" meanHaltingDuration="335.00" maxHaltingDuration="336.00" haltingDurationSum="670.00" meanIntervalHaltingDuration="300.00" maxIntervalHaltingDuration="300.00" intervalHaltingDurationSum="600.00" startedHalts="0.00" meanVehicleNumber="2.00" maxVehicleNumber="2" />
   <interval begin="10500.00" end="10800.00" id="e2_3" sampledSeconds="2980.83" nVehEntered="2" nVehLeft="2" nVehSeen="12" meanSpeed="0.03" meanTimeLoss="248.13" meanOccupancy="66.00" maxOccupancy="67.04" meanMaxJamLengthInVehicles="9.93" meanMaxJamLengthInMeters="69.11" maxJamLengthInVehicles="10" maxJamLengthInMeters="70.00" jamLengthInVehiclesSum="2979" jamLengthInMetersSum="20733.62" meanHaltingDuration="1155.70" maxHaltingDuration="1972.00" haltingDurationSum="11557.00" meanIntervalHaltingDuration="285.80" maxIntervalHaltingDuration="300.00" intervalHaltingDurationSum="2858.00" startedHalts="2.00" meanVehicleNumber="9.94" maxVehicleNumber="10" />
   <interval begin="10500.00" end="10800.00" id="turkis_b_e_1" sampledSeconds="9469.50" nVehEntered="60" nVehLeft="60" nVehSeen="95" meanSpeed="0.54" meanTimeLoss="97.35" meanOccupancy="51.87" maxOccupancy="60.00" meanMaxJamLengthInVehicles="18.78" meanMaxJamLengthInMeters="149.65" maxJamLengthInVehicles="36" maxJamLengthInMeters="299.00" jamLengthInVehiclesSum="8199" jamLengthInMetersSum="63460.48" meanHaltingDuration="27.96" maxHaltingDuration="100.00" haltingDurationSum="8249.00" meanIntervalHaltingDuration="25.63" maxIntervalHaltingDuration="100.00" intervalHaltingDurationSum="7562.00" startedHalts="300.00" meanVehicleNumber="31.59" maxVehicleNumber="36" />
   <interval begin="10500.00" end="10800.00" id="yenimahalle_b_e_a_1" sampledSeconds="598.98" nVehEntered="1" nVehLeft="1" nVehSeen="3" meanSpeed="0.03" meanTimeLoss="199.36" meanOccupancy="73.92" maxOccupancy="79.16" meanMaxJamLengthInVehicles="2.00" meanMaxJamLengthInMeters="11.43" maxJamLengthInVehicles="2" maxJamLengthInMeters="12.00" jamLengthInVehiclesSum="599" jamLengthInMetersSum="3428.08" meanHaltingDuration="441.00" maxHaltingDuration="634.00" haltingDurationSum="882.00" meanIntervalHaltingDuration="274.00" maxIntervalHaltingDuration="300.00" intervalHaltingDurationSum="548.00" startedHalts="1.00" meanVehicleNumber="2.00" maxVehicleNumber="2" />
   <interval begin="10800.00" end="11100.00" id="e2_3" sampledSeconds="2882.56" nVehEntered="2" nVehLeft="2" nVehSeen="12" meanSpeed="0.05" meanTimeLoss="239.68" meanOccupancy="64.69" maxOccupancy="67.18" meanMaxJamLengthInVehicles="9.39" meanMaxJamLengthInMeters="66.99" maxJamLengthInVehicles="10" maxJamLengthInMeters="70.00" jamLengthInVehiclesSum="2852" jamLengthInMetersSum="20315.05" meanHaltingDuration="612.00" maxHaltingDuration="2103.00" haltingDurationSum="12852.00" meanIntervalHaltingDuration="126.76" maxIntervalHaltingDuration="300.00" intervalHaltingDurationSum="2662.00" startedHalts="13.00" meanVehicleNumber="9.61" maxVehicleNumber="10" />
   <interval begin="10800.00" end="11100.00" id="turkis_b_e_1" sampledSeconds="9774.84" nVehEntered="48" nVehLeft="51" nVehSeen="83" meanSpeed="0.36" meanTimeLoss="115.89" meanOccupancy="53.90" maxOccupancy="61.16" meanMaxJamLengthInVehicles="19.72" meanMaxJamLengthInMeters="159.07" maxJamLengthInVehicles="36" maxJamLengthInMeters="299.00" jamLengthInVehiclesSum="8662" jamLengthInMetersSum="68429.40" meanHaltingDuration="31.66" maxHaltingDuration="94.00" haltingDurationSum="9276.00" meanIntervalHaltingDuration="28.55" maxIntervalHaltingDuration="94.00" intervalHaltingDurationSum="8366.00" startedHalts="290.00" meanVehicleNumber="32.63" maxVehicleNumber="37" />
   <interval begin="10800.00" end="11100.00" id="yenimahalle_b_e_a_1" sampledSeconds="600.03" nVehEntered="1" nVehLeft="1" nVehSeen="3" meanSpeed="0.03" meanTimeLoss="199.71" meanOccupancy="73.81" maxOccupancy="79.16" meanMaxJamLengthInVehicles="2.00" meanMaxJamLengthInMeters="11.44" maxJamLengthInVehicles="2" maxJamLengthInMeters="12.00" jamLengthInVehiclesSum="600" jamLengthInMetersSum="3430.81" meanHaltingDuration="358.50" maxHaltingDuration="548.00" haltingDurationSum="717.00" meanIntervalHaltingDuration="234.50" maxIntervalHaltingDuration="300.00" intervalHaltingDurationSum="469.00" startedHalts="1.00" meanVehicleNumber="2.00" maxVehicleNumber="3" />
   <interval begin="11100.00" end="11400.00" id="e2_3" sampledSeconds="2984.53" nVehEntered="0" nVehLeft="1" nVehSeen="10" meanSpeed="0.02" meanTimeLoss="298.21" meanOccupancy="65.61" maxOccupancy="67.18" meanMaxJamLengthInVehicles="9.92" meanMaxJamLengthInMeters="69.37" maxJamLengthInVehicles="10" maxJamLengthInMeters="70.00" jamLengthInVehiclesSum="2981" jamLengthInMetersSum="20840.60" meanHaltingDuration="501.91" maxHaltingDuration="2206.00" haltingDurationSum="5521.00" meanIntervalHaltingDuration="245.27" maxIntervalHaltingDuration="300.00" intervalHaltingDurationSum="2698.00" startedHalts="2.00" meanVehicleNumber="9.95" maxVehicleNumber="10" />
   <interval begin="11100.00" end="11400.00" id="turkis_b_e_1" sampledSeconds="9379.01" nVehEntered="72" nVehLeft="75" nVehSeen="104" meanSpeed="0.48" meanTimeLoss="88.24" meanOccupancy="51.94" maxOccupancy="61.67" meanMaxJamLengthInVehicles="17.94" meanMaxJamLengthInMeters="145.30" maxJamLengthInVehicles="36" maxJamLengthInMeters="298.71" jamLengthInVehiclesSum="8173" jamLengthInMetersSum="64514.20" meanHaltingDuration="34.47" maxHaltingDuration="127.00" haltingDurationSum="8307.00" meanIntervalHaltingDuration="29.35" maxIntervalHaltingDuration="127.00" intervalHaltingDurationSum="7074.00" startedHalts="253.00" meanVehicleNumber="31.32" maxVehicleNumber="37" />
   <interval begin="11100.00" end="11400.00" id="yenimahalle_b_e_a_1" sampledSeconds="600.20" nVehEntered="1" nVehLeft="1" nVehSeen="3" meanSpeed="0.03" meanTimeLoss="199.79" meanOccupancy="73.88" maxOccupancy="79.16" meanMaxJamLengthInVehicles="2.00" meanMaxJamLengthInMeters="11.46" maxJamLengthInVehicles="3" maxJamLengthInMeters="12.00" jamLengthInVehiclesSum="601" jamLengthInMetersSum="3436.62" meanHaltingDuration="279.00" maxHaltingDuration="469.00" haltingDurationSum="558.00" meanIntervalHaltingDuration="194.50" maxIntervalHaltingDuration="300.00" intervalHaltingDurationSum="389.00" startedHalts="1.00" meanVehicleNumber="2.01" maxVehicleNumber="3" />
   <interval begin="11400.00" end="11700.00" id="e2_3" sampledSeconds="2927.80" nVehEntered="1" nVehLeft="1" nVehSeen="10" meanSpeed="0.01" meanTimeLoss="292.60" meanOccupancy="66.32" maxOccupancy="67.18" meanMaxJamLengthInVehicles="9.71" meanMaxJamLengthInMeters="68.88" maxJamLengthInVehicles="10" maxJamLengthInMeters="70.00" jamLengthInVehiclesSum="2921" jamLengthInMetersSum="20726.41" meanHaltingDuration="584.17" maxHaltingDuration="2506.00" haltingDurationSum="7010.00" meanIntervalHaltingDuration="218.83" maxIntervalHaltingDuration="300.00" intervalHaltingDurationSum="2626.00" startedHalts="4.00" meanVehicleNumber="9.76" maxVehicleNumber="10" />
   <interval begin="11400.00" end="11700.00" id="turkis_b_e_1" sampledSeconds="9467.30" nVehEntered="55" nVehLeft="55" nVehSeen="84" meanSpeed="0.26" meanTimeLoss="111.47" meanOccupancy="52.37" maxOccupancy="63.33" meanMaxJamLengthInVehicles="20.49" meanMaxJamLengthInMeters="167.35" maxJamLengthInVehicles="38" maxJamLengthInMeters="298.61" jamLengthInVehiclesSum="8636" jamLengthInMetersSum="68684.58" meanHaltingDuration="37.76" maxHaltingDuration="142.00" haltingDurationSum="8420.00" meanIntervalHaltingDuration="35.04" maxIntervalHaltingDuration="142.00" intervalHaltingDurationSum="7814.00" startedHalts="231.00" meanVehicleNumber="31.59" maxVehicleNumber="38" />
   <interval begin="11400.00" end="11700.00" id="yenimahalle_b_e_a_1" sampledSeconds="597.65" nVehEntered="1" nVehLeft="1" nVehSeen="3" meanSpeed="0.03" meanTimeLoss="198.96" meanOccupancy="78.01" maxOccupancy="79.16" meanMaxJamLengthInVehicles="1.99" meanMaxJamLengthInMeters="11.90" maxJamLengthInVehicles="2" maxJamLengthInMeters="12.00" jamLengthInVehiclesSum="597" jamLengthInMetersSum="3569.20" meanHaltingDuration="202.00" maxHaltingDuration="389.00" haltingDurationSum="404.00" meanIntervalHaltingDuration="157.50" maxIntervalHaltingDuration="300.00" intervalHaltingDurationSum="315.00" startedHalts="1.00" meanVehicleNumber="1.99" maxVehicleNumber="2" />
   <interval begin="11700.00" end="12000.00" id="e2_3" sampledSeconds="2937.25" nVehEntered="1" nVehLeft="0" nVehSeen="10" meanSpeed="0.02" meanTimeLoss="293.45" meanOccupancy="66.06" maxOccupancy="67.18" meanMaxJamLengthInVehicles="9.72" meanMaxJamLengthInMeters="68.88" maxJamLengthInVehicles="10" maxJamLengthInMeters="70.00" jamLengthInVehiclesSum="2932" jamLengthInMetersSum="20766.00" meanHaltingDuration="782.00" maxHaltingDuration="2806.00" haltingDurationSum="9384.00" meanIntervalHaltingDuration="244.58" maxIntervalHaltingDuration="300.00" intervalHaltingDurationSum="2935.00" startedHalts="3.00" meanVehicleNumber="9.79" maxVehicleNumber="10" />
   <interval begin="11700.00" end="12000.00" id="turkis_b_e_1" sampledSeconds="10629.89" nVehEntered="33" nVehLeft="30" nVehSeen="62" meanSpeed="0.22" meanTimeLoss="169.75" meanOccupancy="58.29" maxOccupancy="64.67" meanMaxJamLengthInVehicles="24.01" meanMaxJamLengthInMeters="183.00" maxJamLengthInVehicles="39" maxJamLengthInMeters="299.00" jamLengthInVehiclesSum="9911" jamLengthInMetersSum="74334.64" meanHaltingDuration="57.17" maxHaltingDuration="151.00" haltingDurationSum="10691.00" meanIntervalHaltingDuration="52.12" maxIntervalHaltingDuration="151.00" intervalHaltingDurationSum="9746.00" startedHalts="181.00" meanVehicleNumber="35.46" maxVehicleNumber="39" />
   <interval begin="11700.00" end="12000.00" id="yenimahalle_b_e_a_1" sampledSeconds="600.25" nVehEntered="1" nVehLeft="1" nVehSeen="3" meanSpeed="0.02" meanTimeLoss="199.89" meanOccupancy="77.72" maxOccupancy="79.16" meanMaxJamLengthInVehicles="2.00" meanMaxJamLengthInMeters="11.88" maxJamLengthInVehicles="2" maxJamLengthInMeters="12.00" jamLengthInVehiclesSum="600" jamLengthInMetersSum="3564.50" meanHaltingDuration="162.00" maxHaltingDuration="315.00" haltingDurationSum="324.00" meanIntervalHaltingDuration="154.50" maxIntervalHaltingDuration="300.00" intervalHaltingDurationSum="309.00" startedHalts="1.00" meanVehicleNumber="2.00" maxVehicleNumber="3" />
</detector>
