<?xml version="1.0" encoding="UTF-8"?>

<!-- generated on 2026-05-18T19:44:15.782242+03:00 by Eclipse SUMO sumo 1.26.0
<sumoConfiguration xmlns:xsi="http://www.w3.org/2001/XMLSchema-instance" xsi:noNamespaceSchemaLocation="http://sumo.dlr.de/xsd/sumoConfiguration.xsd">

    <input>
        <net-file value="d:\Sumo_Samsun\yeni_normal_sure.net.xml"/>
        <route-files value="d:\Sumo_Samsun\arac_talepleri/deneme_1.rou.xml"/>
        <additional-files value="d:\Sumo_Samsun\Detectors/detector_deneme.add.xml"/>
    </input>

    <time>
        <step-length value="1"/>
    </time>

    <processing>
        <lateral-resolution value="0"/>
    </processing>

    <traci_server>
        <remote-port value="51869"/>
    </traci_server>

    <random_number>
        <seed value="20"/>
    </random_number>

</sumoConfiguration>
-->

<detector xmlns:xsi="http://www.w3.org/2001/XMLSchema-instance" xsi:noNamespaceSchemaLocation="http://sumo.dlr.de/xsd/det_e2_file.xsd">
   <interval begin="0.00" end="300.00" id="pelitkoy_b_e_a_0" sampledSeconds="72.40" nVehEntered="40" nVehLeft="40" nVehSeen="40" meanSpeed="7.23" meanTimeLoss="1.11" meanOccupancy="7.31" maxOccupancy="50.00" meanMaxJamLengthInVehicles="0.00" meanMaxJamLengthInMeters="0.00" maxJamLengthInVehicles="0" maxJamLengthInMeters="0.00" jamLengthInVehiclesSum="0" jamLengthInMetersSum="0.00" meanHaltingDuration="1.00" maxHaltingDuration="1.00" haltingDurationSum="3.00" meanIntervalHaltingDuration="1.00" maxIntervalHaltingDuration="1.00" intervalHaltingDurationSum="3.00" startedHalts="3.00" meanVehicleNumber="0.35" maxVehicleNumber="2" />
   <interval begin="300.00" end="600.00" id="pelitkoy_b_e_a_0" sampledSeconds="33.96" nVehEntered="27" nVehLeft="27" nVehSeen="27" meanSpeed="11.15" meanTimeLoss="0.49" meanOccupancy="3.37" maxOccupancy="50.00" meanMaxJamLengthInVehicles="0.00" meanMaxJamLengthInMeters="0.00" maxJamLengthInVehicles="0" maxJamLengthInMeters="0.00" jamLengthInVehiclesSum="0" jamLengthInMetersSum="0.00" meanHaltingDuration="0.00" maxHaltingDuration="0.00" haltingDurationSum="0.00" meanIntervalHaltingDuration="0.00" maxIntervalHaltingDuration="0.00" intervalHaltingDurationSum="0.00" startedHalts="0.00" meanVehicleNumber="0.19" maxVehicleNumber="2" />
   <interval begin="600.00" end="900.00" id="pelitkoy_b_e_a_0" sampledSeconds="87.52" nVehEntered="54" nVehLeft="54" nVehSeen="54" meanSpeed="7.72" meanTimeLoss="0.93" meanOccupancy="8.46" maxOccupancy="50.00" meanMaxJamLengthInVehicles="0.00" meanMaxJamLengthInMeters="0.00" maxJamLengthInVehicles="0" maxJamLengthInMeters="0.00" jamLengthInVehiclesSum="0" jamLengthInMetersSum="0.00" meanHaltingDuration="0.00" maxHaltingDuration="0.00" haltingDurationSum="0.00" meanIntervalHaltingDuration="0.00" maxIntervalHaltingDuration="0.00" intervalHaltingDurationSum="0.00" startedHalts="0.00" meanVehicleNumber="0.45" maxVehicleNumber="2" />
   <interval begin="900.00" end="1200.00" id="pelitkoy_b_e_a_0" sampledSeconds="81.81" nVehEntered="45" nVehLeft="45" nVehSeen="45" meanSpeed="7.35" meanTimeLoss="1.10" meanOccupancy="8.86" maxOccupancy="50.00" meanMaxJamLengthInVehicles="0.00" meanMaxJamLengthInMeters="0.00" maxJamLengthInVehicles="0" maxJamLengthInMeters="0.00" jamLengthInVehiclesSum="0" jamLengthInMetersSum="0.00" meanHaltingDuration="1.00" maxHaltingDuration="1.00" haltingDurationSum="1.00" meanIntervalHaltingDuration="1.00" maxIntervalHaltingDuration="1.00" intervalHaltingDurationSum="1.00" startedHalts="1.00" meanVehicleNumber="0.39" maxVehicleNumber="2" />
   <interval begin="1200.00" end="1500.00" id="pelitkoy_b_e_a_0" sampledSeconds="72.15" nVehEntered="41" nVehLeft="41" nVehSeen="41" meanSpeed="7.09" meanTimeLoss="1.07" meanOccupancy="7.37" maxOccupancy="50.71" meanMaxJamLengthInVehicles="0.00" meanMaxJamLengthInMeters="0.00" maxJamLengthInVehicles="0" maxJamLengthInMeters="0.00" jamLengthInVehiclesSum="0" jamLengthInMetersSum="0.00" meanHaltingDuration="1.00" maxHaltingDuration="1.00" haltingDurationSum="2.00" meanIntervalHaltingDuration="1.00" maxIntervalHaltingDuration="1.00" intervalHaltingDurationSum="2.00" startedHalts="2.00" meanVehicleNumber="0.34" maxVehicleNumber="2" />
   <interval begin="1500.00" end="1800.00" id="pelitkoy_b_e_a_0" sampledSeconds="83.23" nVehEntered="47" nVehLeft="46" nVehSeen="47" meanSpeed="7.06" meanTimeLoss="1.12" meanOccupancy="8.50" maxOccupancy="50.00" meanMaxJamLengthInVehicles="0.00" meanMaxJamLengthInMeters="0.00" maxJamLengthInVehicles="0" maxJamLengthInMeters="0.00" jamLengthInVehiclesSum="0" jamLengthInMetersSum="0.00" meanHaltingDuration="1.00" maxHaltingDuration="1.00" haltingDurationSum="1.00" meanIntervalHaltingDuration="1.00" maxIntervalHaltingDuration="1.00" intervalHaltingDurationSum="1.00" startedHalts="1.00" meanVehicleNumber="0.40" maxVehicleNumber="2" />
   <interval begin="1800.00" end="2100.00" id="pelitkoy_b_e_a_0" sampledSeconds="83.24" nVehEntered="50" nVehLeft="51" nVehSeen="51" meanSpeed="7.93" meanTimeLoss="0.93" meanOccupancy="8.69" maxOccupancy="50.00" meanMaxJamLengthInVehicles="0.00" meanMaxJamLengthInMeters="0.00" maxJamLengthInVehicles="0" maxJamLengthInMeters="0.00" jamLengthInVehiclesSum="0" jamLengthInMetersSum="0.00" meanHaltingDuration="0.00" maxHaltingDuration="0.00" haltingDurationSum="0.00" meanIntervalHaltingDuration="0.00" maxIntervalHaltingDuration="0.00" intervalHaltingDurationSum="0.00" startedHalts="0.00" meanVehicleNumber="0.43" maxVehicleNumber="2" />
   <interval begin="2100.00" end="2400.00" id="pelitkoy_b_e_a_0" sampledSeconds="83.77" nVehEntered="49" nVehLeft="49" nVehSeen="49" meanSpeed="7.52" meanTimeLoss="1.03" meanOccupancy="9.36" maxOccupancy="50.00" meanMaxJamLengthInVehicles="0.00" meanMaxJamLengthInMeters="0.00" maxJamLengthInVehicles="0" maxJamLengthInMeters="0.00" jamLengthInVehiclesSum="0" jamLengthInMetersSum="0.00" meanHaltingDuration="0.00" maxHaltingDuration="0.00" haltingDurationSum="0.00" meanIntervalHaltingDuration="0.00" maxIntervalHaltingDuration="0.00" intervalHaltingDurationSum="0.00" startedHalts="0.00" meanVehicleNumber="0.42" maxVehicleNumber="2" />
   <interval begin="2400.00" end="2700.00" id="pelitkoy_b_e_a_0" sampledSeconds="68.07" nVehEntered="46" nVehLeft="46" nVehSeen="46" meanSpeed="9.09" meanTimeLoss="0.74" meanOccupancy="6.93" maxOccupancy="50.00" meanMaxJamLengthInVehicles="0.00" meanMaxJamLengthInMeters="0.00" maxJamLengthInVehicles="0" maxJamLengthInMeters="0.00" jamLengthInVehiclesSum="0" jamLengthInMetersSum="0.00" meanHaltingDuration="0.00" maxHaltingDuration="0.00" haltingDurationSum="0.00" meanIntervalHaltingDuration="0.00" maxIntervalHaltingDuration="0.00" intervalHaltingDurationSum="0.00" startedHalts="0.00" meanVehicleNumber="0.36" maxVehicleNumber="2" />
   <interval begin="2700.00" end="3000.00" id="pelitkoy_b_e_a_0" sampledSeconds="73.13" nVehEntered="42" nVehLeft="41" nVehSeen="42" meanSpeed="7.71" meanTimeLoss="1.04" meanOccupancy="7.68" maxOccupancy="50.00" meanMaxJamLengthInVehicles="0.00" meanMaxJamLengthInMeters="0.00" maxJamLengthInVehicles="0" maxJamLengthInMeters="0.00" jamLengthInVehiclesSum="0" jamLengthInMetersSum="0.00" meanHaltingDuration="0.00" maxHaltingDuration="0.00" haltingDurationSum="0.00" meanIntervalHaltingDuration="0.00" maxIntervalHaltingDuration="0.00" intervalHaltingDurationSum="0.00" startedHalts="0.00" meanVehicleNumber="0.36" maxVehicleNumber="2" />
   <interval begin="3000.00" end="3300.00" id="pelitkoy_b_e_a_0" sampledSeconds="77.10" nVehEntered="48" nVehLeft="49" nVehSeen="49" meanSpeed="8.37" meanTimeLoss="0.86" meanOccupancy="7.91" maxOccupancy="50.00" meanMaxJamLengthInVehicles="0.00" meanMaxJamLengthInMeters="0.00" maxJamLengthInVehicles="0" maxJamLengthInMeters="0.00" jamLengthInVehiclesSum="0" jamLengthInMetersSum="0.00" meanHaltingDuration="0.00" maxHaltingDuration="0.00" haltingDurationSum="0.00" meanIntervalHaltingDuration="0.00" maxIntervalHaltingDuration="0.00" intervalHaltingDurationSum="0.00" startedHalts="0.00" meanVehicleNumber="0.41" maxVehicleNumber="2" />
   <interval begin="3300.00" end="3600.00" id="pelitkoy_b_e_a_0" sampledSeconds="47.48" nVehEntered="36" nVehLeft="36" nVehSeen="36" meanSpeed="11.00" meanTimeLoss="0.54" meanOccupancy="4.84" maxOccupancy="50.00" meanMaxJamLengthInVehicles="0.00" meanMaxJamLengthInMeters="0.00" maxJamLengthInVehicles="0" maxJamLengthInMeters="0.00" jamLengthInVehiclesSum="0" jamLengthInMetersSum="0.00" meanHaltingDuration="0.00" maxHaltingDuration="0.00" haltingDurationSum="0.00" meanIntervalHaltingDuration="0.00" maxIntervalHaltingDuration="0.00" intervalHaltingDurationSum="0.00" startedHalts="0.00" meanVehicleNumber="0.27" maxVehicleNumber="2" />
   <interval begin="3600.00" end="3900.00" id="pelitkoy_b_e_a_0" sampledSeconds="75.68" nVehEntered="49" nVehLeft="49" nVehSeen="49" meanSpeed="8.73" meanTimeLoss="0.83" meanOccupancy="8.08" maxOccupancy="50.00" meanMaxJamLengthInVehicles="0.00" meanMaxJamLengthInMeters="0.00" maxJamLengthInVehicles="0" maxJamLengthInMeters="0.00" jamLengthInVehiclesSum="0" jamLengthInMetersSum="0.00" meanHaltingDuration="0.00" maxHaltingDuration="0.00" haltingDurationSum="0.00" meanIntervalHaltingDuration="0.00" maxIntervalHaltingDuration="0.00" intervalHaltingDurationSum="0.00" startedHalts="0.00" meanVehicleNumber="0.40" maxVehicleNumber="2" />
   <interval begin="3900.00" end="4200.00" id="pelitkoy_b_e_a_0" sampledSeconds="61.08" nVehEntered="40" nVehLeft="40" nVehSeen="40" meanSpeed="8.97" meanTimeLoss="0.76" meanOccupancy="6.25" maxOccupancy="50.00" meanMaxJamLengthInVehicles="0.00" meanMaxJamLengthInMeters="0.00" maxJamLengthInVehicles="0" maxJamLengthInMeters="0.00" jamLengthInVehiclesSum="0" jamLengthInMetersSum="0.00" meanHaltingDuration="1.00" maxHaltingDuration="1.00" haltingDurationSum="1.00" meanIntervalHaltingDuration="1.00" maxIntervalHaltingDuration="1.00" intervalHaltingDurationSum="1.00" startedHalts="1.00" meanVehicleNumber="0.32" maxVehicleNumber="2" />
   <interval begin="4200.00" end="4500.00" id="pelitkoy_b_e_a_0" sampledSeconds="84.48" nVehEntered="50" nVehLeft="50" nVehSeen="50" meanSpeed="8.08" meanTimeLoss="0.95" meanOccupancy="8.53" maxOccupancy="50.00" meanMaxJamLengthInVehicles="0.00" meanMaxJamLengthInMeters="0.00" maxJamLengthInVehicles="0" maxJamLengthInMeters="0.00" jamLengthInVehiclesSum="0" jamLengthInMetersSum="0.00" meanHaltingDuration="0.00" maxHaltingDuration="0.00" haltingDurationSum="0.00" meanIntervalHaltingDuration="0.00" maxIntervalHaltingDuration="0.00" intervalHaltingDurationSum="0.00" startedHalts="0.00" meanVehicleNumber="0.43" maxVehicleNumber="2" />
   <interval begin="4500.00" end="4800.00" id="pelitkoy_b_e_a_0" sampledSeconds="57.69" nVehEntered="41" nVehLeft="41" nVehSeen="41" meanSpeed="10.06" meanTimeLoss="0.63" meanOccupancy="6.13" maxOccupancy="50.00" meanMaxJamLengthInVehicles="0.00" meanMaxJamLengthInMeters="0.00" maxJamLengthInVehicles="0" maxJamLengthInMeters="0.00" jamLengthInVehiclesSum="0" jamLengthInMetersSum="0.00" meanHaltingDuration="0.00" maxHaltingDuration="0.00" haltingDurationSum="0.00" meanIntervalHaltingDuration="0.00" maxIntervalHaltingDuration="0.00" intervalHaltingDurationSum="0.00" startedHalts="0.00" meanVehicleNumber="0.32" maxVehicleNumber="2" />
   <interval begin="4800.00" end="5100.00" id="pelitkoy_b_e_a_0" sampledSeconds="59.69" nVehEntered="44" nVehLeft="44" nVehSeen="44" meanSpeed="9.66" meanTimeLoss="0.67" meanOccupancy="6.77" maxOccupancy="50.00" meanMaxJamLengthInVehicles="0.00" meanMaxJamLengthInMeters="0.00" maxJamLengthInVehicles="0" maxJamLengthInMeters="0.00" jamLengthInVehiclesSum="0" jamLengthInMetersSum="0.00" meanHaltingDuration="1.00" maxHaltingDuration="1.00" haltingDurationSum="1.00" meanIntervalHaltingDuration="1.00" maxIntervalHaltingDuration="1.00" intervalHaltingDurationSum="1.00" startedHalts="1.00" meanVehicleNumber="0.33" maxVehicleNumber="2" />
   <interval begin="5100.00" end="5400.00" id="pelitkoy_b_e_a_0" sampledSeconds="41.28" nVehEntered="31" nVehLeft="31" nVehSeen="31" meanSpeed="10.65" meanTimeLoss="0.57" meanOccupancy="4.56" maxOccupancy="50.00" meanMaxJamLengthInVehicles="0.00" meanMaxJamLengthInMeters="0.00" maxJamLengthInVehicles="0" maxJamLengthInMeters="0.00" jamLengthInVehiclesSum="0" jamLengthInMetersSum="0.00" meanHaltingDuration="0.00" maxHaltingDuration="0.00" haltingDurationSum="0.00" meanIntervalHaltingDuration="0.00" maxIntervalHaltingDuration="0.00" intervalHaltingDurationSum="0.00" startedHalts="0.00" meanVehicleNumber="0.23" maxVehicleNumber="1" />
   <interval begin="5400.00" end="5700.00" id="pelitkoy_b_e_a_0" sampledSeconds="59.50" nVehEntered="42" nVehLeft="41" nVehSeen="42" meanSpeed="9.62" meanTimeLoss="0.68" meanOccupancy="5.88" maxOccupancy="50.00" meanMaxJamLengthInVehicles="0.00" meanMaxJamLengthInMeters="0.00" maxJamLengthInVehicles="0" maxJamLengthInMeters="0.00" jamLengthInVehiclesSum="0" jamLengthInMetersSum="0.00" meanHaltingDuration="0.00" maxHaltingDuration="0.00" haltingDurationSum="0.00" meanIntervalHaltingDuration="0.00" maxIntervalHaltingDuration="0.00" intervalHaltingDurationSum="0.00" startedHalts="0.00" meanVehicleNumber="0.32" maxVehicleNumber="2" />
   <interval begin="5700.00" end="6000.00" id="pelitkoy_b_e_a_0" sampledSeconds="62.27" nVehEntered="42" nVehLeft="43" nVehSeen="43" meanSpeed="9.28" meanTimeLoss="0.73" meanOccupancy="6.71" maxOccupancy="50.00" meanMaxJamLengthInVehicles="0.00" meanMaxJamLengthInMeters="0.00" maxJamLengthInVehicles="0" maxJamLengthInMeters="0.00" jamLengthInVehiclesSum="0" jamLengthInMetersSum="0.00" meanHaltingDuration="1.00" maxHaltingDuration="1.00" haltingDurationSum="1.00" meanIntervalHaltingDuration="1.00" maxIntervalHaltingDuration="1.00" intervalHaltingDurationSum="1.00" startedHalts="1.00" meanVehicleNumber="0.33" maxVehicleNumber="2" />
   <interval begin="6000.00" end="6300.00" id="pelitkoy_b_e_a_0" sampledSeconds="42.46" nVehEntered="37" nVehLeft="36" nVehSeen="37" meanSpeed="12.09" meanTimeLoss="0.40" meanOccupancy="4.96" maxOccupancy="50.00" meanMaxJamLengthInVehicles="0.00" meanMaxJamLengthInMeters="0.00" maxJamLengthInVehicles="0" maxJamLengthInMeters="0.00" jamLengthInVehiclesSum="0" jamLengthInMetersSum="0.00" meanHaltingDuration="0.00" maxHaltingDuration="0.00" haltingDurationSum="0.00" meanIntervalHaltingDuration="0.00" maxIntervalHaltingDuration="0.00" intervalHaltingDurationSum="0.00" startedHalts="0.00" meanVehicleNumber="0.26" maxVehicleNumber="1" />
   <interval begin="6300.00" end="6600.00" id="pelitkoy_b_e_a_0" sampledSeconds="48.37" nVehEntered="37" nVehLeft="38" nVehSeen="38" meanSpeed="11.12" meanTimeLoss="0.49" meanOccupancy="4.92" maxOccupancy="50.00" meanMaxJamLengthInVehicles="0.00" meanMaxJamLengthInMeters="0.00" maxJamLengthInVehicles="0" maxJamLengthInMeters="0.00" jamLengthInVehiclesSum="0" jamLengthInMetersSum="0.00" meanHaltingDuration="0.00" maxHaltingDuration="0.00" haltingDurationSum="0.00" meanIntervalHaltingDuration="0.00" maxIntervalHaltingDuration="0.00" intervalHaltingDurationSum="0.00" startedHalts="0.00" meanVehicleNumber="0.27" maxVehicleNumber="2" />
   <interval begin="6600.00" end="6900.00" id="pelitkoy_b_e_a_0" sampledSeconds="57.35" nVehEntered="42" nVehLeft="42" nVehSeen="42" meanSpeed="10.35" meanTimeLoss="0.60" meanOccupancy="6.32" maxOccupancy="50.00" meanMaxJamLengthInVehicles="0.00" meanMaxJamLengthInMeters="0.00" maxJamLengthInVehicles="0" maxJamLengthInMeters="0.00" jamLengthInVehiclesSum="0" jamLengthInMetersSum="0.00" meanHaltingDuration="0.00" maxHaltingDuration="0.00" haltingDurationSum="0.00" meanIntervalHaltingDuration="0.00" maxIntervalHaltingDuration="0.00" intervalHaltingDurationSum="0.00" startedHalts="0.00" meanVehicleNumber="0.33" maxVehicleNumber="2" />
   <interval begin="6900.00" end="7200.00" id="pelitkoy_b_e_a_0" sampledSeconds="42.46" nVehEntered="36" nVehLeft="36" nVehSeen="36" meanSpeed="12.31" meanTimeLoss="0.39" meanOccupancy="4.64" maxOccupancy="50.00" meanMaxJamLengthInVehicles="0.00" meanMaxJamLengthInMeters="0.00" maxJamLengthInVehicles="0" maxJamLengthInMeters="0.00" jamLengthInVehiclesSum="0" jamLengthInMetersSum="0.00" meanHaltingDuration="0.00" maxHaltingDuration="0.00" haltingDurationSum="0.00" meanIntervalHaltingDuration="0.00" maxIntervalHaltingDuration="0.00" intervalHaltingDurationSum="0.00" startedHalts="0.00" meanVehicleNumber="0.25" maxVehicleNumber="2" />
   <interval begin="7200.00" end="7500.00" id="pelitkoy_b_e_a_0" sampledSeconds="55.41" nVehEntered="40" nVehLeft="40" nVehSeen="40" meanSpeed="10.25" meanTimeLoss="0.60" meanOccupancy="6.16" maxOccupancy="50.00" meanMaxJamLengthInVehicles="0.00" meanMaxJamLengthInMeters="0.00" maxJamLengthInVehicles="0" maxJamLengthInMeters="0.00" jamLengthInVehiclesSum="0" jamLengthInMetersSum="0.00" meanHaltingDuration="0.00" maxHaltingDuration="0.00" haltingDurationSum="0.00" meanIntervalHaltingDuration="0.00" maxIntervalHaltingDuration="0.00" intervalHaltingDurationSum="0.00" startedHalts="0.00" meanVehicleNumber="0.30" maxVehicleNumber="2" />
   <interval begin="7500.00" end="7800.00" id="pelitkoy_b_e_a_0" sampledSeconds="61.63" nVehEntered="43" nVehLeft="43" nVehSeen="43" meanSpeed="9.21" meanTimeLoss="0.70" meanOccupancy="6.13" maxOccupancy="50.00" meanMaxJamLengthInVehicles="0.00" meanMaxJamLengthInMeters="0.00" maxJamLengthInVehicles="0" maxJamLengthInMeters="0.00" jamLengthInVehiclesSum="0" jamLengthInMetersSum="0.00" meanHaltingDuration="1.00" maxHaltingDuration="1.00" haltingDurationSum="1.00" meanIntervalHaltingDuration="1.00" maxIntervalHaltingDuration="1.00" intervalHaltingDurationSum="1.00" startedHalts="1.00" meanVehicleNumber="0.33" maxVehicleNumber="2" />
   <interval begin="7800.00" end="8100.00" id="pelitkoy_b_e_a_0" sampledSeconds="32.81" nVehEntered="27" nVehLeft="27" nVehSeen="27" meanSpeed="12.27" meanTimeLoss="0.39" meanOccupancy="3.98" maxOccupancy="50.00" meanMaxJamLengthInVehicles="0.00" meanMaxJamLengthInMeters="0.00" maxJamLengthInVehicles="0" maxJamLengthInMeters="0.00" jamLengthInVehiclesSum="0" jamLengthInMetersSum="0.00" meanHaltingDuration="0.00" maxHaltingDuration="0.00" haltingDurationSum="0.00" meanIntervalHaltingDuration="0.00" maxIntervalHaltingDuration="0.00" intervalHaltingDurationSum="0.00" startedHalts="0.00" meanVehicleNumber="0.19" maxVehicleNumber="2" />
   <interval begin="8100.00" end="8400.00" id="pelitkoy_b_e_a_0" sampledSeconds="33.19" nVehEntered="30" nVehLeft="30" nVehSeen="30" meanSpeed="13.53" meanTimeLoss="0.29" meanOccupancy="4.05" maxOccupancy="50.00" meanMaxJamLengthInVehicles="0.00" meanMaxJamLengthInMeters="0.00" maxJamLengthInVehicles="0" maxJamLengthInMeters="0.00" jamLengthInVehiclesSum="0" jamLengthInMetersSum="0.00" meanHaltingDuration="0.00" maxHaltingDuration="0.00" haltingDurationSum="0.00" meanIntervalHaltingDuration="0.00" maxIntervalHaltingDuration="0.00" intervalHaltingDurationSum="0.00" startedHalts="0.00" meanVehicleNumber="0.21" maxVehicleNumber="2" />
   <interval begin="8400.00" end="8700.00" id="pelitkoy_b_e_a_0" sampledSeconds="34.17" nVehEntered="31" nVehLeft="30" nVehSeen="31" meanSpeed="13.14" meanTimeLoss="0.32" meanOccupancy="3.87" maxOccupancy="50.00" meanMaxJamLengthInVehicles="0.00" meanMaxJamLengthInMeters="0.00" maxJamLengthInVehicles="0" maxJamLengthInMeters="0.00" jamLengthInVehiclesSum="0" jamLengthInMetersSum="0.00" meanHaltingDuration="0.00" maxHaltingDuration="0.00" haltingDurationSum="0.00" meanIntervalHaltingDuration="0.00" maxIntervalHaltingDuration="0.00" intervalHaltingDurationSum="0.00" startedHalts="0.00" meanVehicleNumber="0.21" maxVehicleNumber="2" />
   <interval begin="8700.00" end="9000.00" id="pelitkoy_b_e_a_0" sampledSeconds="49.00" nVehEntered="40" nVehLeft="41" nVehSeen="41" meanSpeed="12.22" meanTimeLoss="0.40" meanOccupancy="5.48" maxOccupancy="50.00" meanMaxJamLengthInVehicles="0.00" meanMaxJamLengthInMeters="0.00" maxJamLengthInVehicles="0" maxJamLengthInMeters="0.00" jamLengthInVehiclesSum="0" jamLengthInMetersSum="0.00" meanHaltingDuration="0.00" maxHaltingDuration="0.00" haltingDurationSum="0.00" meanIntervalHaltingDuration="0.00" maxIntervalHaltingDuration="0.00" intervalHaltingDurationSum="0.00" startedHalts="0.00" meanVehicleNumber="0.29" maxVehicleNumber="2" />
   <interval begin="9000.00" end="9300.00" id="pelitkoy_b_e_a_0" sampledSeconds="48.97" nVehEntered="38" nVehLeft="38" nVehSeen="38" meanSpeed="11.11" meanTimeLoss="0.51" meanOccupancy="5.25" maxOccupancy="50.00" meanMaxJamLengthInVehicles="0.00" meanMaxJamLengthInMeters="0.00" maxJamLengthInVehicles="0" maxJamLengthInMeters="0.00" jamLengthInVehiclesSum="0" jamLengthInMetersSum="0.00" meanHaltingDuration="0.00" maxHaltingDuration="0.00" haltingDurationSum="0.00" meanIntervalHaltingDuration="0.00" maxIntervalHaltingDuration="0.00" intervalHaltingDurationSum="0.00" startedHalts="0.00" meanVehicleNumber="0.28" maxVehicleNumber="2" />
   <interval begin="9300.00" end="9600.00" id="pelitkoy_b_e_a_0" sampledSeconds="76.14" nVehEntered="49" nVehLeft="49" nVehSeen="49" meanSpeed="9.18" meanTimeLoss="0.78" meanOccupancy="8.33" maxOccupancy="50.00" meanMaxJamLengthInVehicles="0.00" meanMaxJamLengthInMeters="0.00" maxJamLengthInVehicles="0" maxJamLengthInMeters="0.00" jamLengthInVehiclesSum="0" jamLengthInMetersSum="0.00" meanHaltingDuration="1.00" maxHaltingDuration="1.00" haltingDurationSum="1.00" meanIntervalHaltingDuration="1.00" maxIntervalHaltingDuration="1.00" intervalHaltingDurationSum="1.00" startedHalts="1.00" meanVehicleNumber="0.41" maxVehicleNumber="2" />
   <interval begin="9600.00" end="9900.00" id="pelitkoy_b_e_a_0" sampledSeconds="61.06" nVehEntered="41" nVehLeft="41" nVehSeen="41" meanSpeed="9.03" meanTimeLoss="0.75" meanOccupancy="6.71" maxOccupancy="50.00" meanMaxJamLengthInVehicles="0.00" meanMaxJamLengthInMeters="0.00" maxJamLengthInVehicles="0" maxJamLengthInMeters="0.00" jamLengthInVehiclesSum="0" jamLengthInMetersSum="0.00" meanHaltingDuration="0.00" maxHaltingDuration="0.00" haltingDurationSum="0.00" meanIntervalHaltingDuration="0.00" maxIntervalHaltingDuration="0.00" intervalHaltingDurationSum="0.00" startedHalts="0.00" meanVehicleNumber="0.32" maxVehicleNumber="2" />
   <interval begin="9900.00" end="10200.00" id="pelitkoy_b_e_a_0" sampledSeconds="84.61" nVehEntered="49" nVehLeft="48" nVehSeen="49" meanSpeed="7.56" meanTimeLoss="1.03" meanOccupancy="8.73" maxOccupancy="50.71" meanMaxJamLengthInVehicles="0.00" meanMaxJamLengthInMeters="0.00" maxJamLengthInVehicles="1" maxJamLengthInMeters="1.11" jamLengthInVehiclesSum="1" jamLengthInMetersSum="1.11" meanHaltingDuration="2.00" maxHaltingDuration="2.00" haltingDurationSum="2.00" meanIntervalHaltingDuration="2.00" maxIntervalHaltingDuration="2.00" intervalHaltingDurationSum="2.00" startedHalts="1.00" meanVehicleNumber="0.42" maxVehicleNumber="2" />
   <interval begin="10200.00" end="10500.00" id="pelitkoy_b_e_a_0" sampledSeconds="70.53" nVehEntered="47" nVehLeft="48" nVehSeen="48" meanSpeed="8.98" meanTimeLoss="0.75" meanOccupancy="7.19" maxOccupancy="50.00" meanMaxJamLengthInVehicles="0.00" meanMaxJamLengthInMeters="0.00" maxJamLengthInVehicles="0" maxJamLengthInMeters="0.00" jamLengthInVehiclesSum="0" jamLengthInMetersSum="0.00" meanHaltingDuration="0.00" maxHaltingDuration="0.00" haltingDurationSum="0.00" meanIntervalHaltingDuration="0.00" maxIntervalHaltingDuration="0.00" intervalHaltingDurationSum="0.00" startedHalts="0.00" meanVehicleNumber="0.37" maxVehicleNumber="2" />
   <interval begin="10500.00" end="10800.00" id="pelitkoy_b_e_a_0" sampledSeconds="61.44" nVehEntered="40" nVehLeft="40" nVehSeen="40" meanSpeed="8.89" meanTimeLoss="0.80" meanOccupancy="6.03" maxOccupancy="50.71" meanMaxJamLengthInVehicles="0.00" meanMaxJamLengthInMeters="0.00" maxJamLengthInVehicles="1" maxJamLengthInMeters="1.43" jamLengthInVehiclesSum="1" jamLengthInMetersSum="1.43" meanHaltingDuration="2.00" maxHaltingDuration="2.00" haltingDurationSum="2.00" meanIntervalHaltingDuration="2.00" maxIntervalHaltingDuration="2.00" intervalHaltingDurationSum="2.00" startedHalts="1.00" meanVehicleNumber="0.32" maxVehicleNumber="2" />
   <interval begin="10800.00" end="11100.00" id="pelitkoy_b_e_a_0" sampledSeconds="71.09" nVehEntered="48" nVehLeft="48" nVehSeen="48" meanSpeed="9.44" meanTimeLoss="0.71" meanOccupancy="7.72" maxOccupancy="50.00" meanMaxJamLengthInVehicles="0.00" meanMaxJamLengthInMeters="0.00" maxJamLengthInVehicles="0" maxJamLengthInMeters="0.00" jamLengthInVehiclesSum="0" jamLengthInMetersSum="0.00" meanHaltingDuration="0.00" maxHaltingDuration="0.00" haltingDurationSum="0.00" meanIntervalHaltingDuration="0.00" maxIntervalHaltingDuration="0.00" intervalHaltingDurationSum="0.00" startedHalts="0.00" meanVehicleNumber="0.39" maxVehicleNumber="2" />
   <interval begin="11100.00" end="11400.00" id="pelitkoy_b_e_a_0" sampledSeconds="54.31" nVehEntered="40" nVehLeft="40" nVehSeen="40" meanSpeed="10.39" meanTimeLoss="0.60" meanOccupancy="5.93" maxOccupancy="50.00" meanMaxJamLengthInVehicles="0.00" meanMaxJamLengthInMeters="0.00" maxJamLengthInVehicles="0" maxJamLengthInMeters="0.00" jamLengthInVehiclesSum="0" jamLengthInMetersSum="0.00" meanHaltingDuration="0.00" maxHaltingDuration="0.00" haltingDurationSum="0.00" meanIntervalHaltingDuration="0.00" maxIntervalHaltingDuration="0.00" intervalHaltingDurationSum="0.00" startedHalts="0.00" meanVehicleNumber="0.31" maxVehicleNumber="2" />
   <interval begin="11400.00" end="11700.00" id="pelitkoy_b_e_a_0" sampledSeconds="52.99" nVehEntered="37" nVehLeft="37" nVehSeen="37" meanSpeed="10.16" meanTimeLoss="0.66" meanOccupancy="5.99" maxOccupancy="50.00" meanMaxJamLengthInVehicles="0.00" meanMaxJamLengthInMeters="0.00" maxJamLengthInVehicles="0" maxJamLengthInMeters="0.00" jamLengthInVehiclesSum="0" jamLengthInMetersSum="0.00" meanHaltingDuration="0.00" maxHaltingDuration="0.00" haltingDurationSum="0.00" meanIntervalHaltingDuration="0.00" maxIntervalHaltingDuration="0.00" intervalHaltingDurationSum="0.00" startedHalts="0.00" meanVehicleNumber="0.30" maxVehicleNumber="2" />
   <interval begin="11700.00" end="12000.00" id="pelitkoy_b_e_a_0" sampledSeconds="84.48" nVehEntered="53" nVehLeft="52" nVehSeen="53" meanSpeed="7.97" meanTimeLoss="0.92" meanOccupancy="8.65" maxOccupancy="50.00" meanMaxJamLengthInVehicles="0.00" meanMaxJamLengthInMeters="0.00" maxJamLengthInVehicles="0" maxJamLengthInMeters="0.00" jamLengthInVehiclesSum="0" jamLengthInMetersSum="0.00" meanHaltingDuration="1.00" maxHaltingDuration="1.00" haltingDurationSum="1.00" meanIntervalHaltingDuration="1.00" maxIntervalHaltingDuration="1.00" intervalHaltingDurationSum="1.00" startedHalts="1.00" meanVehicleNumber="0.43" maxVehicleNumber="2" />
</detector>
