<?xml version="1.0" encoding="UTF-8"?>

<!-- generated on 2026-05-17T22:01:51.999855+03:00 by Eclipse SUMO sumo 1.26.0
<sumoConfiguration xmlns:xsi="http://www.w3.org/2001/XMLSchema-instance" xsi:noNamespaceSchemaLocation="http://sumo.dlr.de/xsd/sumoConfiguration.xsd">

    <input>
        <net-file value="D:\Sumo_Samsun\DQL_bekleme_suresi\../yeni_normal_sure.net.xml"/>
        <route-files value="D:\Sumo_Samsun\DQL_bekleme_suresi\../arac_talepleri/deneme_1.rou.xml"/>
        <additional-files value="D:\Sumo_Samsun\DQL_bekleme_suresi\detector_default_olcum.add.xml"/>
    </input>

    <time>
        <step-length value="1"/>
    </time>

    <processing>
        <lateral-resolution value="0"/>
    </processing>

    <traci_server>
        <remote-port value="54703"/>
    </traci_server>

    <random_number>
        <seed value="1"/>
    </random_number>

</sumoConfiguration>
-->

<detector xmlns:xsi="http://www.w3.org/2001/XMLSchema-instance" xsi:noNamespaceSchemaLocation="http://sumo.dlr.de/xsd/det_e2_file.xsd">
   <interval begin="0.00" end="300.00" id="atakent_e_b_1" sampledSeconds="915.04" nVehEntered="69" nVehLeft="65" nVehSeen="69" meanSpeed="11.03" meanTimeLoss="7.00" meanOccupancy="4.30" maxOccupancy="14.29" meanMaxJamLengthInVehicles="1.10" meanMaxJamLengthInMeters="7.11" maxJamLengthInVehicles="5" maxJamLengthInMeters="35.23" jamLengthInVehiclesSum="329" jamLengthInMetersSum="2131.66" meanHaltingDuration="21.44" maxHaltingDuration="50.00" haltingDurationSum="343.00" meanIntervalHaltingDuration="21.44" maxIntervalHaltingDuration="50.00" intervalHaltingDurationSum="343.00" startedHalts="20.00" meanVehicleNumber="3.14" maxVehicleNumber="10" />
   <interval begin="300.00" end="600.00" id="atakent_e_b_1" sampledSeconds="1100.96" nVehEntered="75" nVehLeft="76" nVehSeen="79" meanSpeed="10.64" meanTimeLoss="7.65" meanOccupancy="5.18" maxOccupancy="11.43" meanMaxJamLengthInVehicles="1.43" meanMaxJamLengthInMeters="9.46" maxJamLengthInVehicles="6" maxJamLengthInMeters="42.53" jamLengthInVehiclesSum="428" jamLengthInMetersSum="2838.09" meanHaltingDuration="21.85" maxHaltingDuration="44.00" haltingDurationSum="437.00" meanIntervalHaltingDuration="21.85" maxIntervalHaltingDuration="44.00" intervalHaltingDurationSum="437.00" startedHalts="24.00" meanVehicleNumber="3.75" maxVehicleNumber="8" />
   <interval begin="600.00" end="900.00" id="atakent_e_b_1" sampledSeconds="1220.37" nVehEntered="82" nVehLeft="78" nVehSeen="85" meanSpeed="9.57" meanTimeLoss="8.42" meanOccupancy="5.75" maxOccupancy="12.86" meanMaxJamLengthInVehicles="1.73" meanMaxJamLengthInMeters="11.41" maxJamLengthInVehicles="6" maxJamLengthInMeters="42.51" jamLengthInVehiclesSum="518" jamLengthInMetersSum="3421.71" meanHaltingDuration="20.52" maxHaltingDuration="49.00" haltingDurationSum="554.00" meanIntervalHaltingDuration="20.15" maxIntervalHaltingDuration="49.00" intervalHaltingDurationSum="544.00" startedHalts="28.00" meanVehicleNumber="4.16" maxVehicleNumber="9" />
   <interval begin="900.00" end="1200.00" id="atakent_e_b_1" sampledSeconds="1232.64" nVehEntered="80" nVehLeft="85" nVehSeen="87" meanSpeed="10.04" meanTimeLoss="8.09" meanOccupancy="5.78" maxOccupancy="12.86" meanMaxJamLengthInVehicles="1.66" meanMaxJamLengthInMeters="11.17" maxJamLengthInVehicles="6" maxJamLengthInMeters="42.84" jamLengthInVehiclesSum="499" jamLengthInMetersSum="3349.88" meanHaltingDuration="25.36" maxHaltingDuration="48.00" haltingDurationSum="634.00" meanIntervalHaltingDuration="20.48" maxIntervalHaltingDuration="48.00" intervalHaltingDurationSum="512.00" startedHalts="24.00" meanVehicleNumber="4.22" maxVehicleNumber="9" />
   <interval begin="1200.00" end="1500.00" id="atakent_e_b_1" sampledSeconds="1093.65" nVehEntered="71" nVehLeft="70" nVehSeen="73" meanSpeed="10.93" meanTimeLoss="8.03" meanOccupancy="5.16" maxOccupancy="11.43" meanMaxJamLengthInVehicles="1.42" meanMaxJamLengthInMeters="9.35" maxJamLengthInVehicles="6" maxJamLengthInMeters="42.57" jamLengthInVehiclesSum="426" jamLengthInMetersSum="2805.87" meanHaltingDuration="22.30" maxHaltingDuration="46.00" haltingDurationSum="446.00" meanIntervalHaltingDuration="22.30" maxIntervalHaltingDuration="46.00" intervalHaltingDurationSum="446.00" startedHalts="21.00" meanVehicleNumber="3.76" maxVehicleNumber="8" />
   <interval begin="1500.00" end="1800.00" id="atakent_e_b_1" sampledSeconds="1392.22" nVehEntered="88" nVehLeft="83" nVehSeen="91" meanSpeed="8.85" meanTimeLoss="9.38" meanOccupancy="6.60" maxOccupancy="12.86" meanMaxJamLengthInVehicles="2.16" meanMaxJamLengthInMeters="14.64" maxJamLengthInVehicles="6" maxJamLengthInMeters="42.59" jamLengthInVehiclesSum="647" jamLengthInMetersSum="4392.26" meanHaltingDuration="25.55" maxHaltingDuration="48.00" haltingDurationSum="690.00" meanIntervalHaltingDuration="24.74" maxIntervalHaltingDuration="48.00" intervalHaltingDurationSum="668.00" startedHalts="31.00" meanVehicleNumber="4.74" maxVehicleNumber="9" />
   <interval begin="1800.00" end="2100.00" id="atakent_e_b_1" sampledSeconds="1211.30" nVehEntered="76" nVehLeft="83" nVehSeen="84" meanSpeed="9.71" meanTimeLoss="8.36" meanOccupancy="5.70" maxOccupancy="12.86" meanMaxJamLengthInVehicles="1.66" meanMaxJamLengthInMeters="11.16" maxJamLengthInVehicles="6" maxJamLengthInMeters="43.51" jamLengthInVehiclesSum="497" jamLengthInMetersSum="3348.52" meanHaltingDuration="26.80" maxHaltingDuration="48.00" haltingDurationSum="670.00" meanIntervalHaltingDuration="20.64" maxIntervalHaltingDuration="48.00" intervalHaltingDurationSum="516.00" startedHalts="21.00" meanVehicleNumber="4.14" maxVehicleNumber="9" />
   <interval begin="2100.00" end="2400.00" id="atakent_e_b_1" sampledSeconds="1260.30" nVehEntered="82" nVehLeft="79" nVehSeen="83" meanSpeed="9.95" meanTimeLoss="8.69" meanOccupancy="5.97" maxOccupancy="12.86" meanMaxJamLengthInVehicles="1.70" meanMaxJamLengthInMeters="11.26" maxJamLengthInVehicles="6" maxJamLengthInMeters="42.65" jamLengthInVehiclesSum="510" jamLengthInMetersSum="3378.01" meanHaltingDuration="23.13" maxHaltingDuration="50.00" haltingDurationSum="532.00" meanIntervalHaltingDuration="23.13" maxIntervalHaltingDuration="50.00" intervalHaltingDurationSum="532.00" startedHalts="27.00" meanVehicleNumber="4.30" maxVehicleNumber="9" />
   <interval begin="2400.00" end="2700.00" id="atakent_e_b_1" sampledSeconds="1278.88" nVehEntered="88" nVehLeft="86" nVehSeen="92" meanSpeed="8.97" meanTimeLoss="8.41" meanOccupancy="6.04" maxOccupancy="11.43" meanMaxJamLengthInVehicles="1.92" meanMaxJamLengthInMeters="12.88" maxJamLengthInVehicles="6" maxJamLengthInMeters="42.67" jamLengthInVehiclesSum="576" jamLengthInMetersSum="3864.13" meanHaltingDuration="21.71" maxHaltingDuration="49.00" haltingDurationSum="608.00" meanIntervalHaltingDuration="20.75" maxIntervalHaltingDuration="49.00" intervalHaltingDurationSum="581.00" startedHalts="34.00" meanVehicleNumber="4.38" maxVehicleNumber="9" />
   <interval begin="2700.00" end="3000.00" id="atakent_e_b_1" sampledSeconds="1185.51" nVehEntered="79" nVehLeft="83" nVehSeen="85" meanSpeed="10.55" meanTimeLoss="7.56" meanOccupancy="5.58" maxOccupancy="12.67" meanMaxJamLengthInVehicles="1.48" meanMaxJamLengthInMeters="9.79" maxJamLengthInVehicles="6" maxJamLengthInMeters="42.64" jamLengthInVehiclesSum="445" jamLengthInMetersSum="2937.72" meanHaltingDuration="22.92" maxHaltingDuration="50.00" haltingDurationSum="550.00" meanIntervalHaltingDuration="18.71" maxIntervalHaltingDuration="50.00" intervalHaltingDurationSum="449.00" startedHalts="25.00" meanVehicleNumber="4.07" maxVehicleNumber="9" />
   <interval begin="3000.00" end="3300.00" id="atakent_e_b_1" sampledSeconds="1178.77" nVehEntered="87" nVehLeft="86" nVehSeen="89" meanSpeed="10.41" meanTimeLoss="7.22" meanOccupancy="5.61" maxOccupancy="12.86" meanMaxJamLengthInVehicles="1.50" meanMaxJamLengthInMeters="9.92" maxJamLengthInVehicles="6" maxJamLengthInMeters="42.56" jamLengthInVehiclesSum="451" jamLengthInMetersSum="2977.00" meanHaltingDuration="25.55" maxHaltingDuration="48.00" haltingDurationSum="460.00" meanIntervalHaltingDuration="25.55" maxIntervalHaltingDuration="48.00" intervalHaltingDurationSum="460.00" startedHalts="25.00" meanVehicleNumber="4.04" maxVehicleNumber="9" />
   <interval begin="3300.00" end="3600.00" id="atakent_e_b_1" sampledSeconds="1333.31" nVehEntered="76" nVehLeft="71" nVehSeen="79" meanSpeed="8.66" meanTimeLoss="10.56" meanOccupancy="6.29" maxOccupancy="12.86" meanMaxJamLengthInVehicles="2.11" meanMaxJamLengthInMeters="14.27" maxJamLengthInVehicles="6" maxJamLengthInMeters="42.53" jamLengthInVehiclesSum="633" jamLengthInMetersSum="4282.40" meanHaltingDuration="25.04" maxHaltingDuration="48.00" haltingDurationSum="676.00" meanIntervalHaltingDuration="24.37" maxIntervalHaltingDuration="48.00" intervalHaltingDurationSum="658.00" startedHalts="32.00" meanVehicleNumber="4.53" maxVehicleNumber="9" />
   <interval begin="3600.00" end="3900.00" id="atakent_e_b_1" sampledSeconds="1236.70" nVehEntered="83" nVehLeft="88" nVehSeen="91" meanSpeed="9.86" meanTimeLoss="7.64" meanOccupancy="5.82" maxOccupancy="12.86" meanMaxJamLengthInVehicles="1.59" meanMaxJamLengthInMeters="10.53" maxJamLengthInVehicles="6" maxJamLengthInMeters="42.67" jamLengthInVehiclesSum="477" jamLengthInMetersSum="3160.23" meanHaltingDuration="24.37" maxHaltingDuration="49.00" haltingDurationSum="658.00" meanIntervalHaltingDuration="18.41" maxIntervalHaltingDuration="49.00" intervalHaltingDurationSum="497.00" startedHalts="27.00" meanVehicleNumber="4.26" maxVehicleNumber="9" />
   <interval begin="3900.00" end="4200.00" id="atakent_e_b_1" sampledSeconds="1147.35" nVehEntered="77" nVehLeft="77" nVehSeen="80" meanSpeed="10.32" meanTimeLoss="7.95" meanOccupancy="5.43" maxOccupancy="12.24" meanMaxJamLengthInVehicles="1.53" meanMaxJamLengthInMeters="10.16" maxJamLengthInVehicles="6" maxJamLengthInMeters="43.66" jamLengthInVehiclesSum="459" jamLengthInMetersSum="3049.41" meanHaltingDuration="22.33" maxHaltingDuration="45.00" haltingDurationSum="469.00" meanIntervalHaltingDuration="22.33" maxIntervalHaltingDuration="45.00" intervalHaltingDurationSum="469.00" startedHalts="25.00" meanVehicleNumber="3.94" maxVehicleNumber="9" />
   <interval begin="4200.00" end="4500.00" id="atakent_e_b_1" sampledSeconds="1306.42" nVehEntered="80" nVehLeft="76" nVehSeen="83" meanSpeed="9.65" meanTimeLoss="9.25" meanOccupancy="6.19" maxOccupancy="14.29" meanMaxJamLengthInVehicles="1.94" meanMaxJamLengthInMeters="13.10" maxJamLengthInVehicles="6" maxJamLengthInMeters="43.82" jamLengthInVehiclesSum="583" jamLengthInMetersSum="3929.99" meanHaltingDuration="23.85" maxHaltingDuration="48.00" haltingDurationSum="620.00" meanIntervalHaltingDuration="22.96" maxIntervalHaltingDuration="48.00" intervalHaltingDurationSum="597.00" startedHalts="28.00" meanVehicleNumber="4.47" maxVehicleNumber="10" />
   <interval begin="4500.00" end="4800.00" id="atakent_e_b_1" sampledSeconds="1020.31" nVehEntered="74" nVehLeft="79" nVehSeen="81" meanSpeed="11.73" meanTimeLoss="6.16" meanOccupancy="4.78" maxOccupancy="11.43" meanMaxJamLengthInVehicles="1.14" meanMaxJamLengthInMeters="7.36" maxJamLengthInVehicles="5" maxJamLengthInMeters="35.07" jamLengthInVehiclesSum="341" jamLengthInMetersSum="2207.14" meanHaltingDuration="20.95" maxHaltingDuration="43.00" haltingDurationSum="440.00" meanIntervalHaltingDuration="16.57" maxIntervalHaltingDuration="43.00" intervalHaltingDurationSum="348.00" startedHalts="18.00" meanVehicleNumber="3.52" maxVehicleNumber="8" />
   <interval begin="4800.00" end="5100.00" id="atakent_e_b_1" sampledSeconds="1196.33" nVehEntered="76" nVehLeft="73" nVehSeen="78" meanSpeed="9.86" meanTimeLoss="8.79" meanOccupancy="5.65" maxOccupancy="12.86" meanMaxJamLengthInVehicles="1.66" meanMaxJamLengthInMeters="11.00" maxJamLengthInVehicles="6" maxJamLengthInMeters="42.52" jamLengthInVehiclesSum="497" jamLengthInMetersSum="3300.52" meanHaltingDuration="21.67" maxHaltingDuration="51.00" haltingDurationSum="520.00" meanIntervalHaltingDuration="21.67" maxIntervalHaltingDuration="51.00" intervalHaltingDurationSum="520.00" startedHalts="26.00" meanVehicleNumber="4.09" maxVehicleNumber="9" />
   <interval begin="5100.00" end="5400.00" id="atakent_e_b_1" sampledSeconds="1232.79" nVehEntered="76" nVehLeft="72" nVehSeen="81" meanSpeed="9.01" meanTimeLoss="9.23" meanOccupancy="5.82" maxOccupancy="12.86" meanMaxJamLengthInVehicles="1.90" meanMaxJamLengthInMeters="12.86" maxJamLengthInVehicles="6" maxJamLengthInMeters="43.51" jamLengthInVehiclesSum="570" jamLengthInMetersSum="3858.01" meanHaltingDuration="24.40" maxHaltingDuration="49.00" haltingDurationSum="610.00" meanIntervalHaltingDuration="23.12" maxIntervalHaltingDuration="47.00" intervalHaltingDurationSum="578.00" startedHalts="25.00" meanVehicleNumber="4.22" maxVehicleNumber="9" />
   <interval begin="5400.00" end="5700.00" id="atakent_e_b_1" sampledSeconds="1198.56" nVehEntered="77" nVehLeft="85" nVehSeen="86" meanSpeed="9.97" meanTimeLoss="7.90" meanOccupancy="5.64" maxOccupancy="12.86" meanMaxJamLengthInVehicles="1.62" meanMaxJamLengthInMeters="10.78" maxJamLengthInVehicles="6" maxJamLengthInMeters="43.65" jamLengthInVehiclesSum="486" jamLengthInMetersSum="3234.18" meanHaltingDuration="25.83" maxHaltingDuration="50.00" haltingDurationSum="620.00" meanIntervalHaltingDuration="20.71" maxIntervalHaltingDuration="50.00" intervalHaltingDurationSum="497.00" startedHalts="24.00" meanVehicleNumber="4.10" maxVehicleNumber="9" />
   <interval begin="5700.00" end="6000.00" id="atakent_e_b_1" sampledSeconds="1176.16" nVehEntered="69" nVehLeft="66" nVehSeen="70" meanSpeed="9.92" meanTimeLoss="9.65" meanOccupancy="5.54" maxOccupancy="12.86" meanMaxJamLengthInVehicles="1.60" meanMaxJamLengthInMeters="10.58" maxJamLengthInVehicles="6" maxJamLengthInMeters="42.67" jamLengthInVehiclesSum="479" jamLengthInMetersSum="3173.95" meanHaltingDuration="22.23" maxHaltingDuration="47.00" haltingDurationSum="489.00" meanIntervalHaltingDuration="22.23" maxIntervalHaltingDuration="47.00" intervalHaltingDurationSum="489.00" startedHalts="24.00" meanVehicleNumber="4.03" maxVehicleNumber="9" />
   <interval begin="6000.00" end="6300.00" id="atakent_e_b_1" sampledSeconds="1288.52" nVehEntered="82" nVehLeft="80" nVehSeen="86" meanSpeed="9.24" meanTimeLoss="8.95" meanOccupancy="6.10" maxOccupancy="14.29" meanMaxJamLengthInVehicles="1.93" meanMaxJamLengthInMeters="12.99" maxJamLengthInVehicles="7" maxJamLengthInMeters="50.07" jamLengthInVehiclesSum="580" jamLengthInMetersSum="3897.80" meanHaltingDuration="23.46" maxHaltingDuration="50.00" haltingDurationSum="610.00" meanIntervalHaltingDuration="22.88" maxIntervalHaltingDuration="50.00" intervalHaltingDurationSum="595.00" startedHalts="28.00" meanVehicleNumber="4.39" maxVehicleNumber="10" />
   <interval begin="6300.00" end="6600.00" id="atakent_e_b_1" sampledSeconds="1223.60" nVehEntered="80" nVehLeft="85" nVehSeen="86" meanSpeed="9.38" meanTimeLoss="8.38" meanOccupancy="5.74" maxOccupancy="11.43" meanMaxJamLengthInVehicles="1.65" meanMaxJamLengthInMeters="11.11" maxJamLengthInVehicles="6" maxJamLengthInMeters="42.52" jamLengthInVehiclesSum="496" jamLengthInMetersSum="3332.61" meanHaltingDuration="24.50" maxHaltingDuration="48.00" haltingDurationSum="637.00" meanIntervalHaltingDuration="19.88" maxIntervalHaltingDuration="48.00" intervalHaltingDurationSum="517.00" startedHalts="28.00" meanVehicleNumber="4.18" maxVehicleNumber="8" />
   <interval begin="6600.00" end="6900.00" id="atakent_e_b_1" sampledSeconds="1201.11" nVehEntered="79" nVehLeft="74" nVehSeen="80" meanSpeed="9.98" meanTimeLoss="8.40" meanOccupancy="5.68" maxOccupancy="11.43" meanMaxJamLengthInVehicles="1.66" meanMaxJamLengthInMeters="11.08" maxJamLengthInVehicles="6" maxJamLengthInMeters="42.53" jamLengthInVehiclesSum="497" jamLengthInMetersSum="3322.90" meanHaltingDuration="24.14" maxHaltingDuration="49.00" haltingDurationSum="507.00" meanIntervalHaltingDuration="24.14" maxIntervalHaltingDuration="49.00" intervalHaltingDurationSum="507.00" startedHalts="23.00" meanVehicleNumber="4.11" maxVehicleNumber="8" />
   <interval begin="6900.00" end="7200.00" id="atakent_e_b_1" sampledSeconds="1341.51" nVehEntered="84" nVehLeft="82" nVehSeen="90" meanSpeed="10.10" meanTimeLoss="8.42" meanOccupancy="6.35" maxOccupancy="12.86" meanMaxJamLengthInVehicles="1.87" meanMaxJamLengthInMeters="12.46" maxJamLengthInVehicles="6" maxJamLengthInMeters="42.77" jamLengthInVehiclesSum="560" jamLengthInMetersSum="3739.03" meanHaltingDuration="22.33" maxHaltingDuration="48.00" haltingDurationSum="603.00" meanIntervalHaltingDuration="21.59" maxIntervalHaltingDuration="48.00" intervalHaltingDurationSum="583.00" startedHalts="30.00" meanVehicleNumber="4.59" maxVehicleNumber="9" />
   <interval begin="7200.00" end="7500.00" id="atakent_e_b_1" sampledSeconds="1226.55" nVehEntered="81" nVehLeft="89" nVehSeen="89" meanSpeed="10.34" meanTimeLoss="7.71" meanOccupancy="5.76" maxOccupancy="12.86" meanMaxJamLengthInVehicles="1.55" meanMaxJamLengthInMeters="10.31" maxJamLengthInVehicles="6" maxJamLengthInMeters="43.58" jamLengthInVehiclesSum="465" jamLengthInMetersSum="3094.01" meanHaltingDuration="23.54" maxHaltingDuration="47.00" haltingDurationSum="612.00" meanIntervalHaltingDuration="17.88" maxIntervalHaltingDuration="47.00" intervalHaltingDurationSum="465.00" startedHalts="28.00" meanVehicleNumber="4.21" maxVehicleNumber="9" />
   <interval begin="7500.00" end="7800.00" id="atakent_e_b_1" sampledSeconds="1192.33" nVehEntered="79" nVehLeft="77" nVehSeen="79" meanSpeed="10.66" meanTimeLoss="8.31" meanOccupancy="5.60" maxOccupancy="12.86" meanMaxJamLengthInVehicles="1.56" meanMaxJamLengthInMeters="10.37" maxJamLengthInVehicles="6" maxJamLengthInMeters="42.58" jamLengthInVehiclesSum="468" jamLengthInMetersSum="3110.02" meanHaltingDuration="21.30" maxHaltingDuration="45.00" haltingDurationSum="490.00" meanIntervalHaltingDuration="21.30" maxIntervalHaltingDuration="45.00" intervalHaltingDurationSum="490.00" startedHalts="24.00" meanVehicleNumber="4.10" maxVehicleNumber="9" />
   <interval begin="7800.00" end="8100.00" id="atakent_e_b_1" sampledSeconds="1310.17" nVehEntered="90" nVehLeft="84" nVehSeen="92" meanSpeed="9.73" meanTimeLoss="8.32" meanOccupancy="6.20" maxOccupancy="12.86" meanMaxJamLengthInVehicles="1.89" meanMaxJamLengthInMeters="12.66" maxJamLengthInVehicles="6" maxJamLengthInMeters="42.61" jamLengthInVehiclesSum="568" jamLengthInMetersSum="3799.19" meanHaltingDuration="24.12" maxHaltingDuration="49.00" haltingDurationSum="603.00" meanIntervalHaltingDuration="23.44" maxIntervalHaltingDuration="49.00" intervalHaltingDurationSum="586.00" startedHalts="31.00" meanVehicleNumber="4.47" maxVehicleNumber="9" />
   <interval begin="8100.00" end="8400.00" id="atakent_e_b_1" sampledSeconds="1246.73" nVehEntered="79" nVehLeft="84" nVehSeen="87" meanSpeed="10.21" meanTimeLoss="7.90" meanOccupancy="5.85" maxOccupancy="12.86" meanMaxJamLengthInVehicles="1.58" meanMaxJamLengthInMeters="10.47" maxJamLengthInVehicles="6" maxJamLengthInMeters="42.67" jamLengthInVehiclesSum="473" jamLengthInMetersSum="3140.36" meanHaltingDuration="23.41" maxHaltingDuration="50.00" haltingDurationSum="632.00" meanIntervalHaltingDuration="18.22" maxIntervalHaltingDuration="50.00" intervalHaltingDurationSum="492.00" startedHalts="25.00" meanVehicleNumber="4.27" maxVehicleNumber="9" />
   <interval begin="8400.00" end="8700.00" id="atakent_e_b_1" sampledSeconds="1211.19" nVehEntered="80" nVehLeft="81" nVehSeen="83" meanSpeed="9.06" meanTimeLoss="9.00" meanOccupancy="5.71" maxOccupancy="12.58" meanMaxJamLengthInVehicles="1.80" meanMaxJamLengthInMeters="12.18" maxJamLengthInVehicles="6" maxJamLengthInMeters="43.55" jamLengthInVehiclesSum="540" jamLengthInMetersSum="3655.40" meanHaltingDuration="23.50" maxHaltingDuration="51.00" haltingDurationSum="564.00" meanIntervalHaltingDuration="23.50" maxIntervalHaltingDuration="51.00" intervalHaltingDurationSum="564.00" startedHalts="27.00" meanVehicleNumber="4.14" maxVehicleNumber="9" />
   <interval begin="8700.00" end="9000.00" id="atakent_e_b_1" sampledSeconds="1305.05" nVehEntered="83" nVehLeft="76" nVehSeen="85" meanSpeed="9.83" meanTimeLoss="8.85" meanOccupancy="6.18" maxOccupancy="14.29" meanMaxJamLengthInVehicles="1.91" meanMaxJamLengthInMeters="12.77" maxJamLengthInVehicles="6" maxJamLengthInMeters="43.48" jamLengthInVehiclesSum="574" jamLengthInMetersSum="3831.57" meanHaltingDuration="24.12" maxHaltingDuration="50.00" haltingDurationSum="603.00" meanIntervalHaltingDuration="23.80" maxIntervalHaltingDuration="50.00" intervalHaltingDurationSum="595.00" startedHalts="27.00" meanVehicleNumber="4.47" maxVehicleNumber="10" />
   <interval begin="9000.00" end="9300.00" id="atakent_e_b_1" sampledSeconds="1184.62" nVehEntered="78" nVehLeft="85" nVehSeen="87" meanSpeed="9.51" meanTimeLoss="8.04" meanOccupancy="5.56" maxOccupancy="12.86" meanMaxJamLengthInVehicles="1.64" meanMaxJamLengthInMeters="11.05" maxJamLengthInVehicles="6" maxJamLengthInMeters="43.72" jamLengthInVehiclesSum="492" jamLengthInMetersSum="3315.49" meanHaltingDuration="25.11" maxHaltingDuration="49.00" haltingDurationSum="678.00" meanIntervalHaltingDuration="18.96" maxIntervalHaltingDuration="46.00" intervalHaltingDurationSum="512.00" startedHalts="23.00" meanVehicleNumber="4.05" maxVehicleNumber="9" />
   <interval begin="9300.00" end="9600.00" id="atakent_e_b_1" sampledSeconds="1124.37" nVehEntered="73" nVehLeft="70" nVehSeen="75" meanSpeed="11.08" meanTimeLoss="7.81" meanOccupancy="5.32" maxOccupancy="12.86" meanMaxJamLengthInVehicles="1.35" meanMaxJamLengthInMeters="8.82" maxJamLengthInVehicles="6" maxJamLengthInMeters="42.68" jamLengthInVehiclesSum="406" jamLengthInMetersSum="2644.80" meanHaltingDuration="17.88" maxHaltingDuration="44.00" haltingDurationSum="429.00" meanIntervalHaltingDuration="17.88" maxIntervalHaltingDuration="44.00" intervalHaltingDurationSum="429.00" startedHalts="25.00" meanVehicleNumber="3.87" maxVehicleNumber="9" />
   <interval begin="9600.00" end="9900.00" id="atakent_e_b_1" sampledSeconds="1257.18" nVehEntered="82" nVehLeft="80" nVehSeen="87" meanSpeed="9.33" meanTimeLoss="8.72" meanOccupancy="5.95" maxOccupancy="12.86" meanMaxJamLengthInVehicles="1.94" meanMaxJamLengthInMeters="13.02" maxJamLengthInVehicles="6" maxJamLengthInMeters="42.68" jamLengthInVehiclesSum="582" jamLengthInMetersSum="3907.43" meanHaltingDuration="24.42" maxHaltingDuration="48.00" haltingDurationSum="635.00" meanIntervalHaltingDuration="23.19" maxIntervalHaltingDuration="48.00" intervalHaltingDurationSum="603.00" startedHalts="26.00" meanVehicleNumber="4.31" maxVehicleNumber="9" />
   <interval begin="9900.00" end="10200.00" id="atakent_e_b_1" sampledSeconds="1171.56" nVehEntered="77" nVehLeft="83" nVehSeen="84" meanSpeed="9.58" meanTimeLoss="8.11" meanOccupancy="5.48" maxOccupancy="11.43" meanMaxJamLengthInVehicles="1.65" meanMaxJamLengthInMeters="11.09" maxJamLengthInVehicles="7" maxJamLengthInMeters="50.06" jamLengthInVehiclesSum="495" jamLengthInMetersSum="3327.58" meanHaltingDuration="25.48" maxHaltingDuration="50.00" haltingDurationSum="637.00" meanIntervalHaltingDuration="20.24" maxIntervalHaltingDuration="50.00" intervalHaltingDurationSum="506.00" startedHalts="24.00" meanVehicleNumber="4.02" maxVehicleNumber="8" />
   <interval begin="10200.00" end="10500.00" id="atakent_e_b_1" sampledSeconds="1120.54" nVehEntered="85" nVehLeft="83" nVehSeen="86" meanSpeed="10.69" meanTimeLoss="7.17" meanOccupancy="5.29" maxOccupancy="12.86" meanMaxJamLengthInVehicles="1.45" meanMaxJamLengthInMeters="9.63" maxJamLengthInVehicles="6" maxJamLengthInMeters="43.51" jamLengthInVehiclesSum="436" jamLengthInMetersSum="2888.72" meanHaltingDuration="22.30" maxHaltingDuration="51.00" haltingDurationSum="446.00" meanIntervalHaltingDuration="22.30" maxIntervalHaltingDuration="51.00" intervalHaltingDurationSum="446.00" startedHalts="25.00" meanVehicleNumber="3.83" maxVehicleNumber="9" />
   <interval begin="10500.00" end="10800.00" id="atakent_e_b_1" sampledSeconds="1198.88" nVehEntered="79" nVehLeft="76" nVehSeen="82" meanSpeed="9.25" meanTimeLoss="8.84" meanOccupancy="5.67" maxOccupancy="12.86" meanMaxJamLengthInVehicles="1.78" meanMaxJamLengthInMeters="11.92" maxJamLengthInVehicles="6" maxJamLengthInMeters="42.54" jamLengthInVehiclesSum="533" jamLengthInMetersSum="3575.48" meanHaltingDuration="23.54" maxHaltingDuration="44.00" haltingDurationSum="565.00" meanIntervalHaltingDuration="22.88" maxIntervalHaltingDuration="44.00" intervalHaltingDurationSum="549.00" startedHalts="30.00" meanVehicleNumber="4.09" maxVehicleNumber="9" />
   <interval begin="10800.00" end="11100.00" id="atakent_e_b_1" sampledSeconds="1135.51" nVehEntered="78" nVehLeft="81" nVehSeen="84" meanSpeed="9.99" meanTimeLoss="7.65" meanOccupancy="5.34" maxOccupancy="11.43" meanMaxJamLengthInVehicles="1.51" meanMaxJamLengthInMeters="10.04" maxJamLengthInVehicles="6" maxJamLengthInMeters="42.52" jamLengthInVehiclesSum="454" jamLengthInMetersSum="3010.83" meanHaltingDuration="23.84" maxHaltingDuration="49.00" haltingDurationSum="596.00" meanIntervalHaltingDuration="18.96" maxIntervalHaltingDuration="49.00" intervalHaltingDurationSum="474.00" startedHalts="22.00" meanVehicleNumber="3.90" maxVehicleNumber="9" />
   <interval begin="11100.00" end="11400.00" id="atakent_e_b_1" sampledSeconds="1097.98" nVehEntered="81" nVehLeft="80" nVehSeen="84" meanSpeed="10.24" meanTimeLoss="7.34" meanOccupancy="5.18" maxOccupancy="11.43" meanMaxJamLengthInVehicles="1.48" meanMaxJamLengthInMeters="9.78" maxJamLengthInVehicles="5" maxJamLengthInMeters="36.23" jamLengthInVehiclesSum="445" jamLengthInMetersSum="2934.09" meanHaltingDuration="21.00" maxHaltingDuration="49.00" haltingDurationSum="462.00" meanIntervalHaltingDuration="21.00" maxIntervalHaltingDuration="49.00" intervalHaltingDurationSum="462.00" startedHalts="27.00" meanVehicleNumber="3.76" maxVehicleNumber="8" />
   <interval begin="11400.00" end="11700.00" id="atakent_e_b_1" sampledSeconds="1244.46" nVehEntered="83" nVehLeft="80" nVehSeen="87" meanSpeed="9.60" meanTimeLoss="8.40" meanOccupancy="5.88" maxOccupancy="11.43" meanMaxJamLengthInVehicles="1.82" meanMaxJamLengthInMeters="12.09" maxJamLengthInVehicles="6" maxJamLengthInMeters="42.55" jamLengthInVehiclesSum="546" jamLengthInMetersSum="3626.12" meanHaltingDuration="25.35" maxHaltingDuration="49.00" haltingDurationSum="583.00" meanIntervalHaltingDuration="24.52" maxIntervalHaltingDuration="49.00" intervalHaltingDurationSum="564.00" startedHalts="25.00" meanVehicleNumber="4.27" maxVehicleNumber="8" />
   <interval begin="11700.00" end="12000.00" id="atakent_e_b_1" sampledSeconds="1224.69" nVehEntered="78" nVehLeft="84" nVehSeen="85" meanSpeed="10.10" meanTimeLoss="8.07" meanOccupancy="5.74" maxOccupancy="11.43" meanMaxJamLengthInVehicles="1.62" meanMaxJamLengthInMeters="10.87" maxJamLengthInVehicles="6" maxJamLengthInMeters="42.63" jamLengthInVehiclesSum="487" jamLengthInMetersSum="3260.27" meanHaltingDuration="26.16" maxHaltingDuration="50.00" haltingDurationSum="654.00" meanIntervalHaltingDuration="20.00" maxIntervalHaltingDuration="50.00" intervalHaltingDurationSum="500.00" startedHalts="24.00" meanVehicleNumber="4.21" maxVehicleNumber="9" />
</detector>
