<?xml version="1.0" encoding="UTF-8"?>

<!-- generated on 2026-05-17T22:01:52.012467+03:00 by Eclipse SUMO sumo 1.26.0
<sumoConfiguration xmlns:xsi="http://www.w3.org/2001/XMLSchema-instance" xsi:noNamespaceSchemaLocation="http://sumo.dlr.de/xsd/sumoConfiguration.xsd">

    <input>
        <net-file value="D:\Sumo_Samsun\DQL_bekleme_suresi\../yeni_normal_sure.net.xml"/>
        <route-files value="D:\Sumo_Samsun\DQL_bekleme_suresi\../arac_talepleri/deneme_1.rou.xml"/>
        <additional-files value="D:\Sumo_Samsun\DQL_bekleme_suresi\detector_default_olcum.add.xml"/>
    </input>

    <time>
        <step-length value="1"/>
    </time>

    <processing>
        <lateral-resolution value="0"/>
    </processing>

    <traci_server>
        <remote-port value="54703"/>
    </traci_server>

    <random_number>
        <seed value="1"/>
    </random_number>

</sumoConfiguration>
-->

<detector xmlns:xsi="http://www.w3.org/2001/XMLSchema-instance" xsi:noNamespaceSchemaLocation="http://sumo.dlr.de/xsd/det_e2_file.xsd">
   <interval begin="0.00" end="300.00" id="lise_e_b_0" sampledSeconds="1940.43" nVehEntered="62" nVehLeft="48" nVehSeen="62" meanSpeed="7.17" meanTimeLoss="21.01" meanOccupancy="10.76" maxOccupancy="21.65" meanMaxJamLengthInVehicles="3.30" meanMaxJamLengthInMeters="23.14" maxJamLengthInVehicles="10" maxJamLengthInMeters="72.52" jamLengthInVehiclesSum="990" jamLengthInMetersSum="6941.41" meanHaltingDuration="27.76" maxHaltingDuration="61.00" haltingDurationSum="1027.00" meanIntervalHaltingDuration="27.76" maxIntervalHaltingDuration="61.00" intervalHaltingDurationSum="1027.00" startedHalts="37.00" meanVehicleNumber="6.62" maxVehicleNumber="14" />
   <interval begin="300.00" end="600.00" id="lise_e_b_0" sampledSeconds="2123.79" nVehEntered="76" nVehLeft="78" nVehSeen="90" meanSpeed="7.07" meanTimeLoss="15.91" meanOccupancy="11.72" maxOccupancy="22.73" meanMaxJamLengthInVehicles="3.60" meanMaxJamLengthInMeters="25.33" maxJamLengthInVehicles="11" maxJamLengthInMeters="79.91" jamLengthInVehiclesSum="1081" jamLengthInMetersSum="7600.20" meanHaltingDuration="30.57" maxHaltingDuration="60.00" haltingDurationSum="1437.00" meanIntervalHaltingDuration="23.79" maxIntervalHaltingDuration="57.00" intervalHaltingDurationSum="1118.00" startedHalts="37.00" meanVehicleNumber="7.25" maxVehicleNumber="14" />
   <interval begin="600.00" end="900.00" id="lise_e_b_0" sampledSeconds="2173.06" nVehEntered="87" nVehLeft="86" nVehSeen="99" meanSpeed="6.99" meanTimeLoss="14.92" meanOccupancy="12.01" maxOccupancy="23.29" meanMaxJamLengthInVehicles="3.70" meanMaxJamLengthInMeters="26.10" maxJamLengthInVehicles="11" maxJamLengthInMeters="79.91" jamLengthInVehiclesSum="1112" jamLengthInMetersSum="7833.97" meanHaltingDuration="29.29" maxHaltingDuration="61.00" haltingDurationSum="1435.00" meanIntervalHaltingDuration="23.51" maxIntervalHaltingDuration="61.00" intervalHaltingDurationSum="1152.00" startedHalts="40.00" meanVehicleNumber="7.43" maxVehicleNumber="14" />
   <interval begin="900.00" end="1200.00" id="lise_e_b_0" sampledSeconds="2200.25" nVehEntered="75" nVehLeft="76" nVehSeen="88" meanSpeed="6.87" meanTimeLoss="16.96" meanOccupancy="12.14" maxOccupancy="22.48" meanMaxJamLengthInVehicles="3.63" meanMaxJamLengthInMeters="25.54" maxJamLengthInVehicles="11" maxJamLengthInMeters="79.90" jamLengthInVehiclesSum="1089" jamLengthInMetersSum="7663.06" meanHaltingDuration="29.29" maxHaltingDuration="61.00" haltingDurationSum="1406.00" meanIntervalHaltingDuration="23.48" maxIntervalHaltingDuration="61.00" intervalHaltingDurationSum="1127.00" startedHalts="38.00" meanVehicleNumber="7.52" maxVehicleNumber="14" />
   <interval begin="1200.00" end="1500.00" id="lise_e_b_0" sampledSeconds="2255.84" nVehEntered="80" nVehLeft="80" nVehSeen="92" meanSpeed="6.83" meanTimeLoss="16.73" meanOccupancy="12.45" maxOccupancy="22.44" meanMaxJamLengthInVehicles="3.69" meanMaxJamLengthInMeters="26.00" maxJamLengthInVehicles="10" maxJamLengthInMeters="73.78" jamLengthInVehiclesSum="1107" jamLengthInMetersSum="7798.82" meanHaltingDuration="24.41" maxHaltingDuration="61.00" haltingDurationSum="1538.00" meanIntervalHaltingDuration="18.40" maxIntervalHaltingDuration="57.00" intervalHaltingDurationSum="1159.00" startedHalts="52.00" meanVehicleNumber="7.71" maxVehicleNumber="14" />
   <interval begin="1500.00" end="1800.00" id="lise_e_b_0" sampledSeconds="2041.71" nVehEntered="80" nVehLeft="80" nVehSeen="92" meanSpeed="7.22" meanTimeLoss="14.64" meanOccupancy="11.25" maxOccupancy="21.37" meanMaxJamLengthInVehicles="3.26" meanMaxJamLengthInMeters="22.78" maxJamLengthInVehicles="9" maxJamLengthInMeters="66.31" jamLengthInVehiclesSum="979" jamLengthInMetersSum="6834.56" meanHaltingDuration="27.53" maxHaltingDuration="59.00" haltingDurationSum="1294.00" meanIntervalHaltingDuration="21.62" maxIntervalHaltingDuration="59.00" intervalHaltingDurationSum="1016.00" startedHalts="37.00" meanVehicleNumber="6.98" maxVehicleNumber="13" />
   <interval begin="1800.00" end="2100.00" id="lise_e_b_0" sampledSeconds="2075.61" nVehEntered="74" nVehLeft="74" nVehSeen="86" meanSpeed="7.63" meanTimeLoss="15.51" meanOccupancy="11.45" maxOccupancy="20.00" meanMaxJamLengthInVehicles="3.23" meanMaxJamLengthInMeters="22.54" maxJamLengthInVehicles="11" maxJamLengthInMeters="80.14" jamLengthInVehiclesSum="969" jamLengthInMetersSum="6762.36" meanHaltingDuration="26.51" maxHaltingDuration="60.00" haltingDurationSum="1246.00" meanIntervalHaltingDuration="21.43" maxIntervalHaltingDuration="60.00" intervalHaltingDurationSum="1007.00" startedHalts="38.00" meanVehicleNumber="7.12" maxVehicleNumber="13" />
   <interval begin="2100.00" end="2400.00" id="lise_e_b_0" sampledSeconds="2227.26" nVehEntered="79" nVehLeft="79" nVehSeen="91" meanSpeed="7.24" meanTimeLoss="16.36" meanOccupancy="12.29" maxOccupancy="21.63" meanMaxJamLengthInVehicles="3.67" meanMaxJamLengthInMeters="25.89" maxJamLengthInVehicles="10" maxJamLengthInMeters="74.72" jamLengthInVehiclesSum="1101" jamLengthInMetersSum="7767.10" meanHaltingDuration="28.33" maxHaltingDuration="59.00" haltingDurationSum="1445.00" meanIntervalHaltingDuration="22.37" maxIntervalHaltingDuration="59.00" intervalHaltingDurationSum="1141.00" startedHalts="40.00" meanVehicleNumber="7.61" maxVehicleNumber="13" />
   <interval begin="2400.00" end="2700.00" id="lise_e_b_0" sampledSeconds="2210.22" nVehEntered="81" nVehLeft="81" nVehSeen="93" meanSpeed="6.54" meanTimeLoss="16.73" meanOccupancy="12.20" maxOccupancy="24.96" meanMaxJamLengthInVehicles="3.68" meanMaxJamLengthInMeters="25.87" maxJamLengthInVehicles="11" maxJamLengthInMeters="80.21" jamLengthInVehiclesSum="1104" jamLengthInMetersSum="7760.50" meanHaltingDuration="27.05" maxHaltingDuration="64.00" haltingDurationSum="1461.00" meanIntervalHaltingDuration="21.26" maxIntervalHaltingDuration="64.00" intervalHaltingDurationSum="1148.00" startedHalts="44.00" meanVehicleNumber="7.55" maxVehicleNumber="15" />
   <interval begin="2700.00" end="3000.00" id="lise_e_b_0" sampledSeconds="2252.95" nVehEntered="77" nVehLeft="77" nVehSeen="89" meanSpeed="6.67" meanTimeLoss="17.41" meanOccupancy="12.42" maxOccupancy="21.67" meanMaxJamLengthInVehicles="3.62" meanMaxJamLengthInMeters="25.51" maxJamLengthInVehicles="11" maxJamLengthInMeters="79.91" jamLengthInVehiclesSum="1085" jamLengthInMetersSum="7652.21" meanHaltingDuration="24.21" maxHaltingDuration="61.00" haltingDurationSum="1380.00" meanIntervalHaltingDuration="19.88" maxIntervalHaltingDuration="61.00" intervalHaltingDurationSum="1133.00" startedHalts="48.00" meanVehicleNumber="7.68" maxVehicleNumber="14" />
   <interval begin="3000.00" end="3300.00" id="lise_e_b_0" sampledSeconds="2149.05" nVehEntered="80" nVehLeft="81" nVehSeen="92" meanSpeed="7.43" meanTimeLoss="15.47" meanOccupancy="11.86" maxOccupancy="20.00" meanMaxJamLengthInVehicles="3.45" meanMaxJamLengthInMeters="24.20" maxJamLengthInVehicles="9" maxJamLengthInMeters="66.15" jamLengthInVehiclesSum="1035" jamLengthInMetersSum="7261.39" meanHaltingDuration="26.76" maxHaltingDuration="60.00" haltingDurationSum="1365.00" meanIntervalHaltingDuration="21.12" maxIntervalHaltingDuration="60.00" intervalHaltingDurationSum="1077.00" startedHalts="42.00" meanVehicleNumber="7.33" maxVehicleNumber="13" />
   <interval begin="3300.00" end="3600.00" id="lise_e_b_0" sampledSeconds="2076.86" nVehEntered="88" nVehLeft="87" nVehSeen="99" meanSpeed="8.00" meanTimeLoss="13.14" meanOccupancy="11.47" maxOccupancy="20.59" meanMaxJamLengthInVehicles="3.01" meanMaxJamLengthInMeters="21.04" maxJamLengthInVehicles="9" maxJamLengthInMeters="64.89" jamLengthInVehiclesSum="904" jamLengthInMetersSum="6312.54" meanHaltingDuration="25.25" maxHaltingDuration="59.00" haltingDurationSum="1212.00" meanIntervalHaltingDuration="19.64" maxIntervalHaltingDuration="59.00" intervalHaltingDurationSum="943.00" startedHalts="39.00" meanVehicleNumber="7.14" maxVehicleNumber="13" />
   <interval begin="3600.00" end="3900.00" id="lise_e_b_0" sampledSeconds="2315.94" nVehEntered="71" nVehLeft="70" nVehSeen="83" meanSpeed="6.60" meanTimeLoss="19.25" meanOccupancy="12.78" maxOccupancy="23.29" meanMaxJamLengthInVehicles="3.99" meanMaxJamLengthInMeters="28.17" maxJamLengthInVehicles="12" maxJamLengthInMeters="87.43" jamLengthInVehiclesSum="1196" jamLengthInMetersSum="8450.69" meanHaltingDuration="25.07" maxHaltingDuration="61.00" haltingDurationSum="1454.00" meanIntervalHaltingDuration="21.46" maxIntervalHaltingDuration="61.00" intervalHaltingDurationSum="1245.00" startedHalts="49.00" meanVehicleNumber="7.89" maxVehicleNumber="14" />
   <interval begin="3900.00" end="4200.00" id="lise_e_b_0" sampledSeconds="2187.13" nVehEntered="75" nVehLeft="76" nVehSeen="88" meanSpeed="7.08" meanTimeLoss="16.60" meanOccupancy="12.06" maxOccupancy="22.64" meanMaxJamLengthInVehicles="3.53" meanMaxJamLengthInMeters="24.83" maxJamLengthInVehicles="11" maxJamLengthInMeters="81.12" jamLengthInVehiclesSum="1058" jamLengthInMetersSum="7448.69" meanHaltingDuration="30.04" maxHaltingDuration="61.00" haltingDurationSum="1472.00" meanIntervalHaltingDuration="22.35" maxIntervalHaltingDuration="61.00" intervalHaltingDurationSum="1095.00" startedHalts="37.00" meanVehicleNumber="7.47" maxVehicleNumber="14" />
   <interval begin="4200.00" end="4500.00" id="lise_e_b_0" sampledSeconds="2179.35" nVehEntered="79" nVehLeft="79" nVehSeen="91" meanSpeed="7.17" meanTimeLoss="15.98" meanOccupancy="12.02" maxOccupancy="21.67" meanMaxJamLengthInVehicles="3.34" meanMaxJamLengthInMeters="23.36" maxJamLengthInVehicles="10" maxJamLengthInMeters="72.44" jamLengthInVehiclesSum="1003" jamLengthInMetersSum="7006.62" meanHaltingDuration="26.98" maxHaltingDuration="61.00" haltingDurationSum="1349.00" meanIntervalHaltingDuration="20.86" maxIntervalHaltingDuration="59.00" intervalHaltingDurationSum="1043.00" startedHalts="40.00" meanVehicleNumber="7.46" maxVehicleNumber="14" />
   <interval begin="4500.00" end="4800.00" id="lise_e_b_0" sampledSeconds="2136.79" nVehEntered="74" nVehLeft="75" nVehSeen="86" meanSpeed="6.81" meanTimeLoss="16.77" meanOccupancy="11.75" maxOccupancy="21.63" meanMaxJamLengthInVehicles="3.50" meanMaxJamLengthInMeters="24.60" maxJamLengthInVehicles="10" maxJamLengthInMeters="72.43" jamLengthInVehiclesSum="1051" jamLengthInMetersSum="7379.85" meanHaltingDuration="26.90" maxHaltingDuration="60.00" haltingDurationSum="1399.00" meanIntervalHaltingDuration="21.02" maxIntervalHaltingDuration="60.00" intervalHaltingDurationSum="1093.00" startedHalts="42.00" meanVehicleNumber="7.30" maxVehicleNumber="13" />
   <interval begin="4800.00" end="5100.00" id="lise_e_b_0" sampledSeconds="2231.16" nVehEntered="86" nVehLeft="85" nVehSeen="97" meanSpeed="6.86" meanTimeLoss="15.79" meanOccupancy="12.34" maxOccupancy="21.63" meanMaxJamLengthInVehicles="3.73" meanMaxJamLengthInMeters="26.25" maxJamLengthInVehicles="10" maxJamLengthInMeters="72.53" jamLengthInVehiclesSum="1119" jamLengthInMetersSum="7879.07" meanHaltingDuration="25.40" maxHaltingDuration="61.00" haltingDurationSum="1448.00" meanIntervalHaltingDuration="20.47" maxIntervalHaltingDuration="61.00" intervalHaltingDurationSum="1167.00" startedHalts="48.00" meanVehicleNumber="7.62" maxVehicleNumber="13" />
   <interval begin="5100.00" end="5400.00" id="lise_e_b_0" sampledSeconds="2294.08" nVehEntered="75" nVehLeft="74" nVehSeen="87" meanSpeed="6.98" meanTimeLoss="17.79" meanOccupancy="12.65" maxOccupancy="23.29" meanMaxJamLengthInVehicles="3.82" meanMaxJamLengthInMeters="26.86" maxJamLengthInVehicles="11" maxJamLengthInMeters="79.91" jamLengthInVehiclesSum="1146" jamLengthInMetersSum="8063.23" meanHaltingDuration="28.08" maxHaltingDuration="61.00" haltingDurationSum="1460.00" meanIntervalHaltingDuration="22.85" maxIntervalHaltingDuration="61.00" intervalHaltingDurationSum="1188.00" startedHalts="42.00" meanVehicleNumber="7.84" maxVehicleNumber="14" />
   <interval begin="5400.00" end="5700.00" id="lise_e_b_0" sampledSeconds="2296.67" nVehEntered="71" nVehLeft="72" nVehSeen="84" meanSpeed="6.69" meanTimeLoss="18.73" meanOccupancy="12.66" maxOccupancy="21.63" meanMaxJamLengthInVehicles="3.62" meanMaxJamLengthInMeters="25.55" maxJamLengthInVehicles="11" maxJamLengthInMeters="79.91" jamLengthInVehiclesSum="1090" jamLengthInMetersSum="7680.35" meanHaltingDuration="22.20" maxHaltingDuration="61.00" haltingDurationSum="1465.00" meanIntervalHaltingDuration="17.35" maxIntervalHaltingDuration="59.00" intervalHaltingDurationSum="1145.00" startedHalts="55.00" meanVehicleNumber="7.83" maxVehicleNumber="13" />
   <interval begin="5700.00" end="6000.00" id="lise_e_b_0" sampledSeconds="2190.87" nVehEntered="82" nVehLeft="84" nVehSeen="94" meanSpeed="7.15" meanTimeLoss="15.65" meanOccupancy="12.09" maxOccupancy="21.67" meanMaxJamLengthInVehicles="3.37" meanMaxJamLengthInMeters="23.54" maxJamLengthInVehicles="10" maxJamLengthInMeters="72.51" jamLengthInVehiclesSum="1013" jamLengthInMetersSum="7072.29" meanHaltingDuration="20.04" maxHaltingDuration="61.00" haltingDurationSum="1383.00" meanIntervalHaltingDuration="15.52" maxIntervalHaltingDuration="61.00" intervalHaltingDurationSum="1071.00" startedHalts="58.00" meanVehicleNumber="7.49" maxVehicleNumber="14" />
   <interval begin="6000.00" end="6300.00" id="lise_e_b_0" sampledSeconds="2094.25" nVehEntered="73" nVehLeft="72" nVehSeen="83" meanSpeed="6.97" meanTimeLoss="16.97" meanOccupancy="11.55" maxOccupancy="23.29" meanMaxJamLengthInVehicles="3.50" meanMaxJamLengthInMeters="24.47" maxJamLengthInVehicles="10" maxJamLengthInMeters="72.43" jamLengthInVehiclesSum="1050" jamLengthInMetersSum="7340.92" meanHaltingDuration="29.21" maxHaltingDuration="61.00" haltingDurationSum="1373.00" meanIntervalHaltingDuration="23.15" maxIntervalHaltingDuration="61.00" intervalHaltingDurationSum="1088.00" startedHalts="38.00" meanVehicleNumber="7.15" maxVehicleNumber="14" />
   <interval begin="6300.00" end="6600.00" id="lise_e_b_0" sampledSeconds="2179.56" nVehEntered="83" nVehLeft="83" nVehSeen="94" meanSpeed="7.32" meanTimeLoss="15.49" meanOccupancy="12.03" maxOccupancy="23.29" meanMaxJamLengthInVehicles="3.55" meanMaxJamLengthInMeters="24.93" maxJamLengthInVehicles="11" maxJamLengthInMeters="79.89" jamLengthInVehiclesSum="1064" jamLengthInMetersSum="7478.94" meanHaltingDuration="25.46" maxHaltingDuration="60.00" haltingDurationSum="1375.00" meanIntervalHaltingDuration="20.54" maxIntervalHaltingDuration="59.00" intervalHaltingDurationSum="1109.00" startedHalts="45.00" meanVehicleNumber="7.45" maxVehicleNumber="14" />
   <interval begin="6600.00" end="6900.00" id="lise_e_b_0" sampledSeconds="2313.03" nVehEntered="74" nVehLeft="74" nVehSeen="85" meanSpeed="6.37" meanTimeLoss="19.08" meanOccupancy="12.75" maxOccupancy="25.00" meanMaxJamLengthInVehicles="3.89" meanMaxJamLengthInMeters="27.44" maxJamLengthInVehicles="12" maxJamLengthInMeters="87.41" jamLengthInVehiclesSum="1167" jamLengthInMetersSum="8231.62" meanHaltingDuration="30.94" maxHaltingDuration="59.00" haltingDurationSum="1485.00" meanIntervalHaltingDuration="25.12" maxIntervalHaltingDuration="59.00" intervalHaltingDurationSum="1206.00" startedHalts="39.00" meanVehicleNumber="7.88" maxVehicleNumber="16" />
   <interval begin="6900.00" end="7200.00" id="lise_e_b_0" sampledSeconds="2166.96" nVehEntered="78" nVehLeft="76" nVehSeen="89" meanSpeed="6.64" meanTimeLoss="16.76" meanOccupancy="11.95" maxOccupancy="23.33" meanMaxJamLengthInVehicles="3.65" meanMaxJamLengthInMeters="25.71" maxJamLengthInVehicles="10" maxJamLengthInMeters="72.41" jamLengthInVehiclesSum="1095" jamLengthInMetersSum="7713.99" meanHaltingDuration="25.09" maxHaltingDuration="60.00" haltingDurationSum="1430.00" meanIntervalHaltingDuration="20.05" maxIntervalHaltingDuration="60.00" intervalHaltingDurationSum="1143.00" startedHalts="48.00" meanVehicleNumber="7.40" maxVehicleNumber="14" />
   <interval begin="7200.00" end="7500.00" id="lise_e_b_0" sampledSeconds="2349.06" nVehEntered="76" nVehLeft="77" nVehSeen="89" meanSpeed="6.57" meanTimeLoss="18.28" meanOccupancy="12.95" maxOccupancy="21.67" meanMaxJamLengthInVehicles="3.91" meanMaxJamLengthInMeters="27.57" maxJamLengthInVehicles="11" maxJamLengthInMeters="80.12" jamLengthInVehiclesSum="1173" jamLengthInMetersSum="8271.47" meanHaltingDuration="30.31" maxHaltingDuration="62.00" haltingDurationSum="1546.00" meanIntervalHaltingDuration="23.78" maxIntervalHaltingDuration="62.00" intervalHaltingDurationSum="1213.00" startedHalts="40.00" meanVehicleNumber="8.01" maxVehicleNumber="14" />
   <interval begin="7500.00" end="7800.00" id="lise_e_b_0" sampledSeconds="2127.05" nVehEntered="74" nVehLeft="75" nVehSeen="86" meanSpeed="7.18" meanTimeLoss="16.53" meanOccupancy="11.74" maxOccupancy="21.67" meanMaxJamLengthInVehicles="3.45" meanMaxJamLengthInMeters="24.21" maxJamLengthInVehicles="9" maxJamLengthInMeters="66.21" jamLengthInVehiclesSum="1037" jamLengthInMetersSum="7266.89" meanHaltingDuration="29.50" maxHaltingDuration="62.00" haltingDurationSum="1416.00" meanIntervalHaltingDuration="22.39" maxIntervalHaltingDuration="60.00" intervalHaltingDurationSum="1075.00" startedHalts="38.00" meanVehicleNumber="7.26" maxVehicleNumber="13" />
   <interval begin="7800.00" end="8100.00" id="lise_e_b_0" sampledSeconds="2051.64" nVehEntered="75" nVehLeft="76" nVehSeen="86" meanSpeed="7.67" meanTimeLoss="15.46" meanOccupancy="11.32" maxOccupancy="21.63" meanMaxJamLengthInVehicles="3.11" meanMaxJamLengthInMeters="21.58" maxJamLengthInVehicles="9" maxJamLengthInMeters="65.01" jamLengthInVehiclesSum="933" jamLengthInMetersSum="6473.51" meanHaltingDuration="27.37" maxHaltingDuration="61.00" haltingDurationSum="1259.00" meanIntervalHaltingDuration="21.09" maxIntervalHaltingDuration="61.00" intervalHaltingDurationSum="970.00" startedHalts="37.00" meanVehicleNumber="7.03" maxVehicleNumber="13" />
   <interval begin="8100.00" end="8400.00" id="lise_e_b_0" sampledSeconds="2260.89" nVehEntered="77" nVehLeft="76" nVehSeen="87" meanSpeed="6.76" meanTimeLoss="17.81" meanOccupancy="12.49" maxOccupancy="23.29" meanMaxJamLengthInVehicles="3.81" meanMaxJamLengthInMeters="26.92" maxJamLengthInVehicles="11" maxJamLengthInMeters="79.89" jamLengthInVehiclesSum="1145" jamLengthInMetersSum="8079.56" meanHaltingDuration="28.38" maxHaltingDuration="61.00" haltingDurationSum="1419.00" meanIntervalHaltingDuration="23.72" maxIntervalHaltingDuration="60.00" intervalHaltingDurationSum="1186.00" startedHalts="41.00" meanVehicleNumber="7.73" maxVehicleNumber="14" />
   <interval begin="8400.00" end="8700.00" id="lise_e_b_0" sampledSeconds="2272.05" nVehEntered="73" nVehLeft="71" nVehSeen="84" meanSpeed="6.76" meanTimeLoss="18.35" meanOccupancy="12.53" maxOccupancy="22.73" meanMaxJamLengthInVehicles="3.64" meanMaxJamLengthInMeters="25.50" maxJamLengthInVehicles="10" maxJamLengthInMeters="73.47" jamLengthInVehiclesSum="1091" jamLengthInMetersSum="7650.89" meanHaltingDuration="30.21" maxHaltingDuration="62.00" haltingDurationSum="1450.00" meanIntervalHaltingDuration="23.52" maxIntervalHaltingDuration="62.00" intervalHaltingDurationSum="1129.00" startedHalts="38.00" meanVehicleNumber="7.74" maxVehicleNumber="14" />
   <interval begin="8700.00" end="9000.00" id="lise_e_b_0" sampledSeconds="2293.77" nVehEntered="74" nVehLeft="73" nVehSeen="87" meanSpeed="6.91" meanTimeLoss="17.83" meanOccupancy="12.66" maxOccupancy="23.29" meanMaxJamLengthInVehicles="3.74" meanMaxJamLengthInMeters="26.30" maxJamLengthInVehicles="11" maxJamLengthInMeters="79.99" jamLengthInVehiclesSum="1123" jamLengthInMetersSum="7890.57" meanHaltingDuration="29.49" maxHaltingDuration="62.00" haltingDurationSum="1445.00" meanIntervalHaltingDuration="23.71" maxIntervalHaltingDuration="61.00" intervalHaltingDurationSum="1162.00" startedHalts="39.00" meanVehicleNumber="7.81" maxVehicleNumber="14" />
   <interval begin="9000.00" end="9300.00" id="lise_e_b_0" sampledSeconds="2201.44" nVehEntered="75" nVehLeft="78" nVehSeen="89" meanSpeed="7.04" meanTimeLoss="16.60" meanOccupancy="12.13" maxOccupancy="22.76" meanMaxJamLengthInVehicles="3.57" meanMaxJamLengthInMeters="25.12" maxJamLengthInVehicles="10" maxJamLengthInMeters="74.46" jamLengthInVehiclesSum="1072" jamLengthInMetersSum="7540.50" meanHaltingDuration="27.28" maxHaltingDuration="60.00" haltingDurationSum="1446.00" meanIntervalHaltingDuration="21.02" maxIntervalHaltingDuration="60.00" intervalHaltingDurationSum="1114.00" startedHalts="42.00" meanVehicleNumber="7.52" maxVehicleNumber="14" />
   <interval begin="9300.00" end="9600.00" id="lise_e_b_0" sampledSeconds="2157.70" nVehEntered="72" nVehLeft="70" nVehSeen="83" meanSpeed="6.74" meanTimeLoss="17.69" meanOccupancy="11.88" maxOccupancy="21.63" meanMaxJamLengthInVehicles="3.60" meanMaxJamLengthInMeters="25.33" maxJamLengthInVehicles="11" maxJamLengthInMeters="79.93" jamLengthInVehiclesSum="1079" jamLengthInMetersSum="7597.54" meanHaltingDuration="29.40" maxHaltingDuration="61.00" haltingDurationSum="1382.00" meanIntervalHaltingDuration="23.77" maxIntervalHaltingDuration="61.00" intervalHaltingDurationSum="1117.00" startedHalts="38.00" meanVehicleNumber="7.37" maxVehicleNumber="13" />
   <interval begin="9600.00" end="9900.00" id="lise_e_b_0" sampledSeconds="2175.33" nVehEntered="79" nVehLeft="80" nVehSeen="92" meanSpeed="7.45" meanTimeLoss="15.51" meanOccupancy="12.00" maxOccupancy="22.68" meanMaxJamLengthInVehicles="3.49" meanMaxJamLengthInMeters="24.49" maxJamLengthInVehicles="11" maxJamLengthInMeters="79.96" jamLengthInVehiclesSum="1047" jamLengthInMetersSum="7351.13" meanHaltingDuration="25.42" maxHaltingDuration="60.00" haltingDurationSum="1449.00" meanIntervalHaltingDuration="19.18" maxIntervalHaltingDuration="60.00" intervalHaltingDurationSum="1093.00" startedHalts="46.00" meanVehicleNumber="7.44" maxVehicleNumber="14" />
   <interval begin="9900.00" end="10200.00" id="lise_e_b_0" sampledSeconds="2234.89" nVehEntered="75" nVehLeft="75" nVehSeen="87" meanSpeed="6.74" meanTimeLoss="17.57" meanOccupancy="12.33" maxOccupancy="21.67" meanMaxJamLengthInVehicles="3.68" meanMaxJamLengthInMeters="25.90" maxJamLengthInVehicles="11" maxJamLengthInMeters="79.90" jamLengthInVehiclesSum="1105" jamLengthInMetersSum="7769.35" meanHaltingDuration="27.65" maxHaltingDuration="62.00" haltingDurationSum="1438.00" meanIntervalHaltingDuration="22.06" maxIntervalHaltingDuration="62.00" intervalHaltingDurationSum="1147.00" startedHalts="42.00" meanVehicleNumber="7.63" maxVehicleNumber="14" />
   <interval begin="10200.00" end="10500.00" id="lise_e_b_0" sampledSeconds="2278.71" nVehEntered="82" nVehLeft="83" nVehSeen="94" meanSpeed="7.09" meanTimeLoss="16.32" meanOccupancy="12.60" maxOccupancy="21.63" meanMaxJamLengthInVehicles="3.56" meanMaxJamLengthInMeters="25.04" maxJamLengthInVehicles="10" maxJamLengthInMeters="73.28" jamLengthInVehiclesSum="1069" jamLengthInMetersSum="7512.99" meanHaltingDuration="28.42" maxHaltingDuration="61.00" haltingDurationSum="1478.00" meanIntervalHaltingDuration="21.35" maxIntervalHaltingDuration="60.00" intervalHaltingDurationSum="1110.00" startedHalts="41.00" meanVehicleNumber="7.80" maxVehicleNumber="13" />
   <interval begin="10500.00" end="10800.00" id="lise_e_b_0" sampledSeconds="2283.96" nVehEntered="77" nVehLeft="76" nVehSeen="88" meanSpeed="7.21" meanTimeLoss="17.23" meanOccupancy="12.62" maxOccupancy="21.63" meanMaxJamLengthInVehicles="3.65" meanMaxJamLengthInMeters="25.71" maxJamLengthInVehicles="10" maxJamLengthInMeters="72.46" jamLengthInVehiclesSum="1094" jamLengthInMetersSum="7713.63" meanHaltingDuration="26.39" maxHaltingDuration="60.00" haltingDurationSum="1425.00" meanIntervalHaltingDuration="21.07" maxIntervalHaltingDuration="60.00" intervalHaltingDurationSum="1138.00" startedHalts="44.00" meanVehicleNumber="7.80" maxVehicleNumber="13" />
   <interval begin="10800.00" end="11100.00" id="lise_e_b_0" sampledSeconds="2180.84" nVehEntered="81" nVehLeft="82" nVehSeen="93" meanSpeed="7.57" meanTimeLoss="15.44" meanOccupancy="12.02" maxOccupancy="21.67" meanMaxJamLengthInVehicles="3.46" meanMaxJamLengthInMeters="24.32" maxJamLengthInVehicles="10" maxJamLengthInMeters="72.52" jamLengthInVehiclesSum="1038" jamLengthInMetersSum="7294.52" meanHaltingDuration="29.62" maxHaltingDuration="60.00" haltingDurationSum="1422.00" meanIntervalHaltingDuration="22.39" maxIntervalHaltingDuration="56.00" intervalHaltingDurationSum="1075.00" startedHalts="37.00" meanVehicleNumber="7.47" maxVehicleNumber="14" />
   <interval begin="11100.00" end="11400.00" id="lise_e_b_0" sampledSeconds="2125.79" nVehEntered="72" nVehLeft="71" nVehSeen="83" meanSpeed="7.16" meanTimeLoss="16.96" meanOccupancy="11.73" maxOccupancy="22.73" meanMaxJamLengthInVehicles="3.48" meanMaxJamLengthInMeters="24.41" maxJamLengthInVehicles="11" maxJamLengthInMeters="79.93" jamLengthInVehiclesSum="1043" jamLengthInMetersSum="7323.87" meanHaltingDuration="26.29" maxHaltingDuration="58.00" haltingDurationSum="1341.00" meanIntervalHaltingDuration="21.27" maxIntervalHaltingDuration="58.00" intervalHaltingDurationSum="1085.00" startedHalts="42.00" meanVehicleNumber="7.25" maxVehicleNumber="14" />
   <interval begin="11400.00" end="11700.00" id="lise_e_b_0" sampledSeconds="2261.23" nVehEntered="68" nVehLeft="66" nVehSeen="80" meanSpeed="6.20" meanTimeLoss="19.99" meanOccupancy="12.46" maxOccupancy="23.29" meanMaxJamLengthInVehicles="3.75" meanMaxJamLengthInMeters="26.36" maxJamLengthInVehicles="10" maxJamLengthInMeters="72.52" jamLengthInVehiclesSum="1125" jamLengthInMetersSum="7908.22" meanHaltingDuration="25.69" maxHaltingDuration="62.00" haltingDurationSum="1490.00" meanIntervalHaltingDuration="20.21" maxIntervalHaltingDuration="62.00" intervalHaltingDurationSum="1172.00" startedHalts="47.00" meanVehicleNumber="7.70" maxVehicleNumber="14" />
   <interval begin="11700.00" end="12000.00" id="lise_e_b_0" sampledSeconds="2302.25" nVehEntered="76" nVehLeft="77" nVehSeen="90" meanSpeed="6.80" meanTimeLoss="17.41" meanOccupancy="12.71" maxOccupancy="23.29" meanMaxJamLengthInVehicles="3.78" meanMaxJamLengthInMeters="26.67" maxJamLengthInVehicles="10" maxJamLengthInMeters="72.41" jamLengthInVehiclesSum="1134" jamLengthInMetersSum="8000.11" meanHaltingDuration="27.04" maxHaltingDuration="62.00" haltingDurationSum="1514.00" meanIntervalHaltingDuration="21.07" maxIntervalHaltingDuration="57.00" intervalHaltingDurationSum="1180.00" startedHalts="46.00" meanVehicleNumber="7.87" maxVehicleNumber="14" />
</detector>
